Workbook

Sheet Control de Cambios
A1: Revision | B1: Fecha | C1: Descripción del cambio
A2: 7 | B2: 43242 | C2: Incorporación de columna de separación de cuerpo legal (N° y Descripción) para mejorar identificación y busqueda.
C3: Incorporación de requisitos legales: • D.S Nº 206/1970 Ministerio del Trabajo y Previsión Social Modifica el Decreto Nº54 de 1969, que Aprobó el Reglamento de Comités Paritarios de Higiene y Seguridad: • Decreto Nº 76/06 Ministerio del Trabajo y Previsión Social Aprueba Reglamento para la Aplicación del Artículo Nº 66 Bis de a Ley Nº 16.744 sobre la Gestión de la Seguridad y Salud en el Trabajo en Obras, Faenas o Servicios. • Resolución Exenta Nº 3.457 de 2012 del Ministerio de Salud, que Aprueba la “Guía para la selección y control de protección ocular y facial”, elaborada por el Departamento de Salud Ocupacional del Instituto de Salud Pública. • Resolución Exenta Nº 218 del Ministerio de Salud, que Aprueba instrumento de evaluación de medidas para la prevención de riesgos psicosociales en el trabajo, elaborado por el Departamento de Salud Ocupacional. • D.S. Nº144/1961 Ministerio de Salud. Normas para Evitar Emanaciones o Contaminantes Atmosféricos de Cualquier Naturaleza.. • D.S.Nº103/2000 Ministerio de Transportes y Telecomunicaciones Norma de emisión de hidrocarburos no mecánicos para vehículos livianos y medianos. • D.S. N°149/2007 Ministerio de Transportes y Telecomunicaciones Establece norma de emisión de NO, HC y CO para el control del NOx en vehículos en uso, de encendido por chispa (Ciclo OTTO), que cumplen con las Normas de Emisión Establecidas en el DS. Nº 211. • Resolución N°499/2006, Ministerio de Salud. Aprueba documento electronico de declaración de residuos peligrosos. • Ley 20123, Ministerios del Trabajo y Previsión Social, Regula el trabajo en regimen de subcontratación, el funcionamiento de las empresas de servicios transitorios y el contrato de trabajo de servicios transitorios
C4: Revisión y actualización de cumplimiento de DS 594, DS 18, DS 43, NCh 2056
A5: 8 | B5: 43352 | C5: Incorporación de Leyes al Raglamento Interno de Higiene y Seguridad no contempladas en Matriz Legal: Ley 20584, Ley 20393, Ley 21012, Ley 20830, Ley 20348, Ley 21015, Ley 20422, Ley 19284, Ley 20764, Ley 21042
A6: 9 | B6: 43453 | C6: Incorporación de columna de indicador de menor tiempo de revisión de controles operacionales; además se verifican los controles operacionales de la normativa incluida en la matriz legal. Se actualiza Ordenanza Municipal 35 a 46, tambien se referencia nuevo plano regulador
A7: 10 | B7: 43472 | C7: Se verifican los distintos controles operacionales de toda la normativa aplicable
A8: 11 | B8: 43572 | C8: Se verifican los distintos controles operacionales de toda la normativa aplicable, se incluye NCh2245:2015
A9: 12 | B9: 43598 | C9: Se incorporan Ley 21018 y 21122 , además se verifican los distintos controles operacionales de toda la normativa aplicable
A10: 13 | B10: 43626 | C10: Se verifican los distintos controles operacionales de toda la normativa aplicable
A11: 14 | B11: 43671 | C11: Se verifican los distintos controles operacionales de toda la normativa aplicable
A12: 15 | B12: 43705 | C12: Se verifican los distintos controles operacionales de toda la normativa aplicable
A13: 16 | B13: 43720 | C13: Se incorpora norma técnica 142, además se verifican los distintos controles operacionales de toda la normativa aplicable de acuerdo a su tiempo de revisión.
A14: 17 | B14: 43759 | C14: Se verifican los distintos controles operacionales de toda la normativa aplicable
A15: 18 | B15: 43794 | C15: Se verifican los distintos controles operacionales de toda la normativa aplicable
A16: 19 | B16: 43826 | C16: Se verifican los distintos controles operacionales de toda la normativa aplicable
... A38: 41 | B38: 45939 | C38: 1. Revisión interna, se modifica complementariamente las evidencias de cumplimiento del Decreto 44 2. Se eliminan columnas de Calidad, Ambiente y Seguridad y solo se conserva columna Area, que cumple misma función

Sheet RESUMEN
A1: MATRIZ IDENTIFICACION Y EVALUACION DE REQUISITOS LEGALES | L1: Revisión Área Legal dic-2023, ene-24
A2: ITEM | B2: N°/Código | C2: Titular | D2: Año Publicación | E2: Descripción Cuerpo Legal | F2: Mecanismo de Evaluación | G2: Fecha última Evaluación | H2: Estado de Cumplimiento | I2: Plan de Acción | J2: Estado Plan de Acción | K2: Periodicidad | L2: Vigencia / última modificación | M2: Aplicación general / particular | N2: Área
A3: 1 | B3: Decreto Supremo N° 100 | C3: Ministerio Secretaria General de la Presidencia | D3: 38617 | E3: ='DS 100'!B1 -> DECRETO SUPREMO 100 / 2005, MINISTERIO SECRETARIA GENERAL DE LA PRESIDENCIA, FIJA EL TEXTO REFUNDIDO, COORDINADO Y SISTEMATIZADO DE LA CONSTITUCION POLITICA DE LA REPUBLICA DE CHILE | F3: REVISION DOCUMENTACION | G3: 45512 | H3: ='DS 100'!B2 -> 1 | I3: N/A | J3: No Aplica | K3: Mensual | L3: Vigente. Última modificación 07/11/2023, ley 21.626 (plebiscito constitucional; no aplica a DSS) | M3: General, no sólo los artículos que se indican en el detalle | N3: Calidad / Ambiente / S&ST
A4: 2 | B4: Ley N° 16744 | C4: Ministerio del Trabajo y Previsión Social, Subsecretaría de Previsión Social | D4: 24869 | E4: ='Ley 16,744'!B1 -> Ley Nº 16.744 "Establece Normas sobre Accidentes del Trabajo y Enfermedades Profesionales" | F4: REVISION DOCUMENTACION | G4: 45512 | H4: ='Ley 16,744'!B2 -> 1 | I4: N/A | J4: No Aplica | K4: Mensual | L4: 10/12/2021, ley 21.400 (modifica diversos cuerpos legales para regular, en igualdad de condiciones, el matrimonio entre personas del mismo sexo) | M4: General | N4: Calidad/Ambiente
A5: 3 | B5: D.S. N° 148 | C5: Ministerio de Salud | D5: 38154 | E5: ='DS148'!B1 -> DS 148 APRUEBA REGLAMENTO SANITARIO SOBRE MANEJO DE RESIDUOS PELIGROSOS | F5: INSPECCION | G5: 45512 | H5: ='DS148'!B2 -> 1 | I5: SI | J5: Cerrado | K5: Mensual | L5: Vigente, versión única | M5: General, siempre que la empresa almecene o transporte residuos que la norma contempla como peligrosos | N5: Ambiente
A6: 6 | B6: D.S. N° 594 | C6: Ministerio de Salud | D6: 36645 | E6: ='DS 594'!B1 -> DS 594 "Reglamento sobre condiciones sanitarias y ambientales básicas en los lugares de trabajo" | F6: INSPECCION | G6: 45512 | H6: ='DS 594'!B2 -> 1 | I6: SI | J6: Cerrado | K6: Mensual | L6: Vigente. Última modificación 20/06/2019, Decreto 10 | M6: General | N6: S&ST
A7: 7 | B7: DFL N° 1 | C7: Ministerio de Transporte y telecomunicaciones; Subsecretaría de Transporte; Ministerio de Justicia; Subsecretaría de Justicia | D7: 40115 | E7: DFL 1 FIJA TEXTO REFUNDIDO, COORDINADO Y SISTEMATIZADO DE LA LEY DE TRÁNSITO | F7: REVISION DOCUMENTACION | G7: 45512 | H7: 1 | I7: N/A | J7: No Aplica | K7: Mensual | L7: Vigente. Última modificación ley 21.601 (modifica la ley de tránsito para prevenir la venta de vehículos motorizados robados y sancionar las conductas que indica) | M7: General | N7: S&ST
A8: 8 | B8: Res. Ex. N° 1930 | C8: Ministerio de Defensa Nacional; Subsecretaría de Defensa; Dirección General de Movilización Nacional | D8: 43626 | E8: DEJA SIN EFECTO NORMA CHILENA 2190 DEL AÑO 1993 "SUSTANCIAS PELIGROSAS" Y APRUEBA LA NCH. N° 2190 DE 28.ENE.2019 | F8: INSPECCION | G8: 45512 | H8: 1 | I8: N/A | J8: No Aplica | K8: Mensual | L8: Vigente, versión única | M8: General, siempre que empresa transporte sustancias peligrosas definidas en NCh382 y NCh2120/1 a NCh2120/9 | N8: S&ST
A9: 9 | B9: Decreto 44 | C9: Ministerio de Economía, Fomento y Turismo | D9: 43151 | E9: APRUEBA REGLAMENTO QUE ESTABLECE REQUISITOS DE SEGURIDAD Y ROTULACIÓN DE EXTINTORES PORTÁTILES | F9: INSPECCION | G9: 45512 | H9: 1 | I9: N/A | J9: No Aplica | K9: Mensual | L9: Vigente. Última modificación 31-03-2020, Decreto 24 | M9: General | N9: S&ST
A10: 10 | B10: DS 67 | C10: Ministerio del Trabajo y Previsión Social; Subsecretaria de Previsión Social | D10: 36592 | E10: ='DS67'!B1 -> DS 67 APRUEBA REGLAMENTO PARA APLICACION DE ARTICULOS 15 Y 16 DE LEY Nº16.744, SOBRE EXENCIONES, REBAJAS Y RECARGOS DE LA COTIZACION ADICIONAL DIFERENCIADA | F10: REVISION DOCUMENTACION | G10: 45512 | H10: ='DS67'!B3 -> 1 | I10: N/A | J10: No Aplica | K10: Bianual | L10: Vigente. Última modificación 30-06-2023, Decreto 24 | M10: General | N10: S&ST
A11: 11 | B11: Ley 20949 | C11: Ministerio del Trabajo y Previsión Social | D11: 42630 | E11: ='Ley 20949'!B1 -> Ley 20949 MODIFICA EL CÓDIGO DEL TRABAJO PARA REDUCIR EL PESO DE LAS CARGAS DE MANIPULACIÓN MANUAL | F11: REVISION DOCUMENTACION | G11: 45512 | H11: ='Ley 20949'!B2 -> 1 | I11: N/A | J11: No Aplica | K11: Anual | L11: Vigente, versión única | M11: General | N11: S&ST
A12: 12 | B12: Decreto 63 | C12: Ministerio del Trabajo y Previsión Social; Subsecretaria de Previsión Social | D12: 38607 | E12: ='DS 63'!B1 -> Decreto 63 APRUEBA REGLAMENTO PARA LA APLICACION DE LA LEY Nº 20.001, QUE REGULA EL PESO MAXIMO DE CARGA HUMANA | F12: REVISION DOCUMENTACION | G12: 45512 | H12: ='DS 63'!B2 -> 1 | I12: N/A | J12: No Aplica | K12: Anual | L12: Vigente. Última modificación 17-01-2018, decreto 48 | M12: General | N12: S&ST
A13: 13 | B13: NCH N° 1411 | C13: Instituto Nacional de Normalización | E13: ='NCH1411'!B1 -> NCH Nº 1411 | F13: INSPECCION | G13: 45512 | H13: ='NCH1411'!B2 -> 1 | I13: N/A | J13: No Aplica | K13: Mensual | L13: Vigente parcial. Decreto N° 90. Ministerio de Transportes y Telecomunicaciones del 9-06-1993, nula y reemplaza la Norma NCh 1411/V.Of79- Prevención de riesgos - Parte V: Rotulado para el transporte marítimo de mercaderías peligrosas, declarada Oficial de la República de Chile, por Decreto N° 47 de 1979, del Ministerio de Salud. | M13: General | N13: S&ST
A14: 14 | B14: Ley 20005 | C14: Ministerio del Trabajo y Previsión Social; Subsecretaría del Trabajo | D14: 38429 | E14: ='LEY 20005'!B1 -> Ley 20005 Tipifica y sanciona el acoso sexual | F14: REVISION DOCUMENTACION | G14: 45512 | H14: ='LEY 20005'!B2 -> 1 | I14: N/A | J14: No Aplica | K14: Mensual | L14: Vigente, versión única | M14: General | N14: Calidad / S&ST
A15: 15 | B15: Ley 20096 | C15: Ministerio Secretaría General de la Presidencia | D15: 38799 | E15: ='LEY 20096'!B1 -> Ley 20096 Establece Mecanismos de Control Aplicables a las Sustancias Agotadoras de la Capa de Ozono | F15: REVISION DOCUMENTACION | G15: 45512 | H15: 1 | I15: N/A | J15: No Aplica | K15: Anual | L15: Vigente, versión única | M15: General | N15: Ambiente
A16: 16 | B16: DS 18 | C16: Ministerio de Salud Publica | D16: 30033 | E16: ='DS18'!B1 -> D.S. Nº 18 Certificacion de Calidad de EPP | F16: INSPECCION | G16: 45512 | H16: ='DS18'!B2 -> 1 | I16: N/A | J16: No Aplica | K16: Anual | L16: Vigente. Última versión 06-09-1995 | M16: General | N16: S&ST
A17: 17 | B17: DS 254 | C17: Ministerio de Salud | D17: 38014 | E17: ='DS254'!B1 -> D.S.Nº 254 Hoja de datos de seguridad de productos Quimicos | F17: INSPECCION | G17: 45512 | H17: ='DS254'!B2 -> 1 | I17: SI | J17: Cerrado | K17: Anual | L17: Vigente, versión única | M17: General | N17: Ambiente
A18: 18 | B18: DS 109 | C18: Ministerio del Trabajo y Previsión Social | D18: 24996 | E18: ='DS109'!B1 -> D.S.Nº 109 Evaluaciòn de accidente de trabajo y enfermedades profesionales | F18: REPORTE MUTUAL | G18: 45512 | H18: ='DS109'!B2 -> 1 | I18: N/A | J18: No Aplica | K18: Mensual | L18: Vigente. Última modificación 07-03-2006, Decreto 73 | M18: General | N18: S&ST
A19: 19 | B19: Ley 20.105 | C19: Ministerio de Salud; Subsecretaría de Salud Pública | D19: 38853 | E19: ='LEY20105'!B1 -> Ley Nº 19.419 REGULA ACTIVIDADES QUE INDICA RELACIONADAS CON EL TABACO | F19: REVISION DOCUMENTACION | G19: 45512 | H19: ='LEY20105'!B2 -> 1 | I19: N/A | J19: No Aplica | K19: Mensual | L19: Vigente, última modificación 01-02-2022, ley N° 21.413 | M19: General | N19: Ambiente / S&ST
A20: 20 | B20: Ley 20.047 | C20: Ministerio del Trabajo y Previsión Social; Subsecretaría del Trabajo | D20: 38597 | E20: ='LEY20047'!B1 -> Ley Nº 20.047 Establece permiso Paternal | F20: REVISION DOCUMENTACION | G20: 45512 | H20: ='LEY20047'!B2 -> 1 | I20: N/A | J20: No Aplica | K20: Mensual | L20: Vigente, versión única | M20: General | N20: Calidad / S&ST
A21: 21 | B21: DS 43 | C21: Ministerio de Salud | D21: 42458 | E21: ='DS43'!B1 -> DS 43 APRUEBA EL REGLAMENTO DE ALMACENAMIENTO DE SUSTANCIAS PELIGROSAS | F21: INSPECCION | G21: 45512 | H21: ='DS43'!B2 -> 1 | I21: SI | J21: Cerrado | K21: Semestral | L21: Vigente. Última modificación 17-08-2022, Decreto 60 | M21: General, siempre que DSS disponga de almacenamiento de sustancias que la norma califica como peligrosas | N21: Ambiente / S&ST
A22: 22 | B22: DFL 458 | C22: Ministerio de Vivienda y Urbanismo | D22: 27863 | E22: ='DS 458'!B1 -> DFL 458 APRUEBA NUEVA LEY GENERAL DE URBANISMO Y CONSTRUCCIONES | F22: REVISION DOCUMENTACION | G22: 45512 | H22: ='DS 458'!B2 -> 1 | I22: N/A | J22: No Aplica | K22: Mensual | L22: Vigente, última modificación 17/12/2023, ley 21.636 | M22: Particular, en las materias que se detallan en la pestaña respectiva | N22: Calidad
A23: 23 | B23: DS 47 | C23: Ministerio de Vivienda y Urbanismo | D23: 33760 | E23: ='DS 47'!B1 -> DS 47 FIJA NUEVO TEXTO DE LA ORDENANZA GENERAL DE LA LEY GENERAL DE URBANISMO Y CONSTRUCCIONES | F23: REVISION DOCUMENTACION | G23: 45512 | H23: ='DS 47'!B2 -> 1 | I23: N/A | J23: No Aplica | K23: Anual | L23: Vigente, última modificación 28/09/2023, Decreto 7 | M23: Particular, en las materias que se detallan en la pestaña respectiva | N23: Calidad
A24: 24 | B24: DFL 1 | C24: Ministerio del Trabajo y Previsión Social; Subsecretaría del Trabajo | D24: 37637 | E24: ='DFL1'!B1 -> D.F.L. Nº 1 FIJA EL TEXTO REFUNDIDO, COORDINADO Y SISTEMATIZADO DEL CÓDIGO DEL TRABAJO | F24: REVISION DOCUMENTACION | G24: 45512 | H24: ='DFL1'!B2 -> 1 | I24: N/A | J24: No Aplica | K24: Mensual | L24: Vigente, última modificación 21/06/2003, ley 21.592 (establece un estatuto de protección en favor del denunciante) | M24: General | N24: Calidad / S&ST
A25: 25 | B25: DFL 725 | C25: Ministerio de Salud Pública | D25: 24868 | E25: ='DFL 725 Codigo Sanitario'!B1 -> DFL 725 CODIGO SANITARIO | F25: REVISION DOCUMENTACION | G25: 45512 | H25: ='Ley 18490'!B2 -> 1 | I25: N/A | J25: No Aplica | K25: Mensual | L25: Vigente, última modificación 03-10-2023, Resolución Exenta N° 19.333 | M25: General | N25: Calidad / Ambiente / S&ST
A26: 26 | B26: Ley 18490 | C26: Ministerio de Hacienda | D26: 31416 | E26: ='Ley 18490'!B1 -> Ley 18490 ESTABLECE SEGURO OBLIGATORIO DE ACCIDENTES PERSONALES CAUSADOS POR CIRCULACION DE VEHICULOS MOTORIZADOS | F26: REVISION DOCUMENTACION | G26: 45512 | H26: ='Ley 18490'!B2 -> 1 | I26: N/A | J26: No Aplica | K26: Mensual | L26: Vigente, última modificación 09-01-2014, ley 20.720 | M26: General | N26: Calidad / S&ST
A27: 27 | B27: DS 609 | C27: Ministerio de Obras Públicas | D27: 38238 | E27: ESTABLECE NORMA DE EMISION PARA LA REGULACION DE CONTAMINANTES ASOCIADOS A LAS DESCARGAS DE RESIDUOS INDUSTRIALES LIQUIDOS A SISTEMAS DE ALCANTARILLADO | F27: REVISION DOCUMENTACION | G27: 45512 | H27: ='DS 601'!B2 -> 1 | I27: N/A | J27: No Aplica | K27: Anual | L27: Vigente. Última modificación 08-09-2004, Decreto 601 | M27: General | N27: Ambiente
A28: 28 | B28: Decreto 238 | C28: Ministerio de Relaciones Exteriores | D28: 32991 | E28: ='Decreto 238'!B1 -> PROMULGA PROTOCOLO DE MONTREAL RELATIVO A LAS SUSTANCIAS AGOTADORAS DE LA CAPA DE OZONO DE 16 DE SEPTIEMBRE DE 1987 | F28: REVISION DOCUMENTACION | G28: 45512 | H28: ='Decreto 238'!B2 -> 1 | I28: N/A | J28: No Aplica | K28: Anual | L28: Vigente, versión única | M28: General | N28: Ambiente
A29: 29 | B29: Decreto 55 | C29: Ministerio de Transportes y Telecomunicaciones | D29: 34440 | E29: ='Decreto 55'!B1 -> ESTABLECE NORMAS DE EMISION APLICABLES A VEHICULOS MOTORIZADOS PESADOS QUE INDICA | F29: REVISION DOCUMENTACION | G29: 45512 | H29: ='Decreto 55'!B2 -> 1 | I29: N/A | J29: No Aplica | K29: Anual | L29: Vigente. Última modificación 16/05/2012, Decreto 4 | M29: General | N29: Ambiente
A30: 30 | B30: Ley 20160 | C30: Ministerio de Economía, Fomento y Reconstrucción; Subsecretaría de Economía, Fomento y Reconstrucción | D30: 39108 | E30: ='Ley 20160'!B1 -> MODIFICA LA LEY Nº 19.039 SOBRE PROPIEDAD INDUSTRIAL | F30: REVISION DOCUMENTACION | G30: 45512 | H30: ='Ley 20160'!B2 -> 1 | I30: N/A | J30: No Aplica | K30: Anual | L30: Vigente, versión única | M30: General | N30: Calidad
A31: 31 | B31: Decreto 719 | C31: Ministerio de Relaciones Exteriores | D31: 32940 | E31: ='Decreto 719'!B1 -> PROMULGA EL CONVENIO DE VIENA PARA LA PROTECCION DE LA CAPA DE OZONO Y SUS ANEXOS I Y II | F31: REVISION DOCUMENTACION | G31: 45512 | H31: ='Decreto 719'!B2 -> 1 | I31: N/A | J31: No Aplica | K31: Anual | L31: Vigente, versión única | M31: General | N31: Ambiente
A32: 32 | B32: Ley 20435 | C32: Ministerio de Educación | D32: 40302 | E32: PROPIEDAD INTELECTUAL | F32: REVISION DOCUMENTACION | G32: 45512 | H32: 1 | I32: SI | J32: Cerrado | K32: Anual | L32: Vigente, versión única | M32: General | N32: Calidad
A33: 33 | B33: RES EX 218 | C33: Ministerio de Salud; Subsecretaría de Salud Pública; Instituto de Salud Pública | D33: 41310 | E33: ='RES EX 218'!B1 -> RESOLUCION EXENTA 218, MINISTERIO DE SALUD, APRUEBA INSTRUMENTO DE EVALUACION DE MEDIDAS PARA LA PREVENCION DE RIESGO PSICOSOCIALES EN EL TRABAJO | F33: EVALUACIONES | G33: 45512 | H33: ='RES EX 218'!B2 -> 1 | I33: SI | J33: Cerrado | K33: Anual | L33: Vigente, versión única | M33: General | N33: S&ST
A34: 34 | B34: RES EX 1448 | C34: Ministerio de Salud; Subsecretaría de Salud Pública | D34: 44859 | E34: ='RES EX 1448'!B1 -> RESOLUCION EXENTA 1448, MINISTERIO DE SALUD, SUBSECRETARIA DE SALUD PUBLICA, ACTUALIZA PROTOCOLO DE VIGILANCIA DE RIESGOS PSICOSOCIALES EN EL TRABAJO Y DEJA SIN EFECTO LA RESOLUCIÓN Nº 1.433 EXENTA, DE 2017, DEL MINISTERIO DE SALUD | F34: IMPLEMENTACION PROTOCOLO | G34: 45512 | H34: ='RES EX 1448'!B2 -> 1 | I34: SI | J34: Cerrado | K34: Anual | L34: Vigente, versión única | M34: General | N34: S&ST
A35: 35 | B35: NT TMERT | C35: Ministerio de Salud | D35: 41190 | E35: =TMERT!B1 -> NORMA TÉCNICA DE IDENTIFICACIÓN Y EVALUACIÓN DE FACTORES DE RIESGO DE TRASTORNOS MUSCULOESQUELÉTICOS RELACIONADOS AL TRABAJO (TMERT) | F35: EVALUACIONES | G35: 45512 | H35: =TMERT!B2 -> 1 | I35: N/A | J35: No Aplica | K35: Anual | L35: Vigente, versión única | M35: General | N35: S&ST
A36: 36 | B36: DS 1 | C36: Ministerio del Medio Ambiente | D36: 41396 | E36: ='DS 1 RECT'!B1 -> DS 1 APRUEBA REGLAMENTO DEL REGISTRO DE EMISIONES Y TRANSFERENCIAS DE CONTAMINANTES, RETC | F36: REVISION DOCUMENTACION | G36: 45512 | H36: ='DS 1 RECT'!B2 -> 1 | I36: N/A | J36: No Aplica | K36: Mensual | L36: Vigente. Última modificación 11-12-2018, Decreto 31 | M36: General | N36: Ambiente
A37: 37 | B37: Ordenanza 46 | C37: Ilustre Municipalidad de San Pedro de la Paz | D37: 41951 | E37: ='ORD MUN 46'!B1 -> Ordenanza Municipal N° 46 Gestión Ambiental Comunal | F37: INSPECCION | G37: 45512 | H37: ='ORD MUN 46'!B2 -> 1 | I37: N/A | J37: No Aplica | K37: Mensual | L37: Vigente, versión única | M37: General | N37: Ambiente
A38: 38 | B38: Ordenanza 56 | C38: Ilustre Municipalidad de San Pedro de la Paz | D38: 41661 | E38: ='ORD MUN 56'!B1 -> ORDENANZA 56, FIJASE EL SIGUIENTE TEXTO REFUNDIDO DE LA ORDENANZA LOCAL N°01, DE 24 DE DICIEMBRE 1996, QUE DETERMINA LA TARIFA DE ASEO DOMICILIARIO, SUS EXENCIONES Y EL COBRO ADICIONAL POR SOBREPRODUCCIÓN | F38: INSPECCION | G38: 45512 | H38: ='ORD MUN 56'!B2 -> 1 | I38: N/A | J38: No Aplica | K38: Anual | L38: Vigente, Última modificación 22-10-2014 | M38: General | N38: Ambiente
A39: 39 | B39: PRC San Pedro de la Paz | C39: Ilustre Municipalidad de San Pedro de la Paz | D39: 40598 | E39: ='Plan Regulador'!B1 -> PLAN REGULADOR COMUNAL SAN PEDRO DE LA PAZ DE 24 DE FEBRERO 2011 | F39: INSPECCION | G39: 45512 | H39: ='Plan Regulador'!B2 -> 1 | I39: N/A | J39: No Aplica | K39: Anual | L39: Vigente. Última modificación de 17 de enero de 2019, publicada en el Diario Oficial el 09 de febrero de 2019 | M39: General | N39: Calidad
A40: 40 | B40: DS 206 | C40: Ministerio del Trabajo y Previsión Social; Subsecretaria de Previsión Social | D40: 25865 | E40: ='DS 206'!B1 -> DS 206 de 1970 MODIFICA EL REGLAMENTO DE COMITES PARITARIOS DE HIGIENE Y SEGURIDAD | F40: REVISION DOCUMENTACION | G40: 45512 | H40: ='DS 206'!B2 -> 1 | I40: N/A | J40: No Aplica | K40: Anual | L40: Vigente, versión única | M40: General | N40: S&ST
A41: 41 | B41: Ley 20123 | C41: Ministerio del Trabajo y Previsión Social; Subsecretaría del Trabajo | D41: 39006 | E41: LEY 20123, MINISTERIO DEL TRABAJO Y PREVISIÓN SOCIAL, REGULA EL TRABAJO EN REGIMEN DE SUBCONTRATACIÓN, EL FUNCIONAMIENTO DE LAS EMPRESAS DE SERVICIOS TRANSITORIOS Y EL CONTRATO DE SERVICIOS TRANSITORIOS | F41: REVISION DOCUMENTACION | G41: 45512 | H41: ='Ley 20123'!B2 -> 1 | I41: N/A | J41: No Aplica | K41: Anual | L41: Vigente, versión única | M41: General, en caso de ejercer subcontratación y/o servicios transitorios | N41: Calidad / S&ST
A42: 42 | B42: DS 76 | C42: Ministerio del Trabajo y Previsión Social; Subsecretaria de Previsión Social | D42: 39100 | E42: DS 76 APRUEBA REGLAMENTO PARA LA APLICACIÓN DEL ARTICULO 66 BIS DE LA LEY N°16.744 SOBRE LA GESTIÓN DE LA SEGURIDAD Y SALUD EN EL TRABAJO EN OBRAS, FAENAS O SERVICIOS QUE INDICA. | F42: REVISION DOCUMENTACION | G42: 45512 | H42: ='DS 76'!B2 -> 1 | I42: N/A | J42: No Aplica | K42: Anual | L42: Vigente, versión única | M42: General | N42: Calidad / S&ST
A43: 43 | B43: RES EX 3457 | C43: Ministerio de Salud; Subsecretaría de Salud Pública; Instituto de Salud Pública | D43: 41286 | E43: ='RES EX 3457'!B1 -> APRUEBA GUÍA PARA LA SELECCIÓN Y CONTROL DE PROTECCIÓN OCULAR Y FACIAL, ELABORADA POR EL DEPARTAMENTO DE SALUD OCUPACIONAL | F43: REVISION DOCUMENTACION | G43: 45512 | H43: ='RES EX 3457'!B2 -> 1 | I43: N/A | J43: No Aplica | K43: Mensual | L43: Vigente, versión única | M43: General | N43: S&ST
A44: 44 | B44: DS 144 | C44: Ministerio de Salud | D44: 22419 | E44: ='DS 144'!B1 -> DECRETO SUPREMO 144 / 1961, MINISTERIO DE SALUD, ESTABLECE NORMAS PARA EVITAR EMANACIONES O CONTAMINANTES ATMOSFERICOS DE CUALQUIERA NATURALEZA | F44: REVISION DOCUMENTACION | G44: 45512 | H44: ='DS 144'!B2 -> 1 | I44: N/A | J44: No Aplica | K44: Mensual | L44: Vigente, versión única | M44: General | N44: S&ST
A45: 45 | B45: DS 103 | C45: Ministerio de Transportes y Telecomunicaciones; Subsecretaría de Transportes | D45: 36784 | E45: ='DS 103'!B1 -> DECRETO SUPREMO 103, MINISTERIO DE TRANSPORTE Y TELECOMUNICACIONES, ESTABLECE NORMA DE EMISION DE HIDROCARBUROS NO METANICOS PARA VEHICULOS LIVIANOS Y MEDIANOS | F45: REVISION DOCUMENTACION | G45: 45512 | H45: ='DS 103'!B2 -> 1 | I45: N/A | J45: No Aplica | K45: Mensual | L45: Vigente, versión única | M45: General | N45: Ambiente
A46: 46 | B46: DS 149 | C46: Ministerio de Transportes y Telecomunicaciones; Subsecretaría de Transportes | D46: 39196 | E46: ='DS 149'!B1 -> DECRETO SUPREMO 149 / 2007, MINISTERIO DE TRANSPORTE Y TELECUMUNICACIONES, ESTABLECE NORMA DE EMISION DE NO, HC Y CO PARA EL CONTROL DEL NOX EN VEHICULOS EN USO, DE ENCENDIDO POR CHISPA (CICLO OTTO), QUE CUMPLEN CON LAS NORMAS DE EMISION ESTABLECIDAS EN EL DS. Nº 211 DE 1991 Y DS. Nº 54, DE 1994 | F46: REVISION DOCUMENTACION | G46: 45512 | H46: ='DS 149'!B2 -> 1 | I46: N/A | J46: No Aplica | K46: Mensual | L46: Vigente. Última modificación 12-03-2018, Decreto 35 | M46: General | N46: Ambiente
A47: 47 | B47: DS 54 | C47: Ministerio de Transportes y Telecomunicaciones | D47: 34457 | E47: ='DS 54 MTT'!B1 -> DECRETO SUPREMO 54 / 1994, MINISTERIO DE TRANSPORTE Y TELECUMUNICACIONES, ESTABLECE NORMAS DE EMISIÓN APLICABLES A VEHICULOS MOTORIZADOS MEDIANOS | F47: REVISION DOCUMENTACION | G47: 45512 | H47: ='DS 54 MTT'!B2 -> 1 | I47: N/A | J47: No Aplica | K47: Mensual | L47: Vigente. Última modificación 30-09-2020, Decreto 40 | M47: General | N47: Ambiente
A48: 48 | B48: NCh 2056 | C48: Instituto Nacional de Normalización | D48: 43732 | E48: ='NCh 2056'!B1 -> NCh 2056, Extintores portátiles - Inspección, mantención y recarga - Requisitos generales Instalaciones fijas de extinción | F48: REVISION DOCUMENTACION | G48: 45512 | H48: ='NCh 2056'!B2 -> 1 | I48: N/A | J48: No Aplica | K48: Mensual | L48: Vigente, sin constancia de existir versión actualizada | M48: General | N48: Calidad / S&ST
A49: 49 | B49: RES EX 499 | C49: Ministerio de Salud; Subsecretaría de Salud Pública | D49: 38946 | E49: ='RES 499'!B1 -> RESOLUCIÓN N°499/2006, MINISTERIO DE SALUD. APRUEBA DOCUMENTO ELECTRONICO DE DECLARACIÓN DE RESIDUOS PELIGROSOS | F49: REVISION DOCUMENTACION | G49: 45512 | H49: ='NCh 2056'!B2 -> 1 | I49: N/A | J49: No Aplica | K49: Anual | L49: Vigente, versión única | M49: General | N49: Ambiente
A50: 50 | B50: Ley 20584 | C50: Ministerio de Salud; Subsecretaría de Salud Pública | D50: 41023 | E50: ='Ley 20584'!B1 -> LEY 20584 / 2012, MINISTERIO DE SALUD, REGULA LOS DERECHOS Y DEBERES QUE TIENEN LAS PERSONAS EN RELACION CON ACCIONES VINCULADAS A SU ATENCIÓN EN SALUD | F50: REVISION DOCUMENTACION | G50: 45512 | H50: ='Ley 20584'!B2 -> 1 | I50: N/A | J50: No Aplica | K50: Anual | L50: Vigente. Última modificación 17-03-2023, ley N° 21.541 | M50: General | N50: S&ST
A51: 51 | B51: Ley 20393 | C51: Ministerio de Hacienda; Subsecretaría de Hacienda | D51: 40149 | E51: ='Ley 20393'!B1 -> LEY 20393 / 2016, MINISTERIO DE HACIENDA, ESTABLECE LA RESPONSABILIDAD PENAL DE LAS PERSONAS JURIDICAS EN LOS DELITOS DE LAVADOS DE ACTIVOS, FINANCIAMIENTO DEL TERRORISMO Y DELITOS DE COHECHO QUE INDICA | F51: REVISION DOCUMENTACION | G51: 45512 | H51: 0.5 | I51: SI | J51: Implementación | K51: Semestral | L51: Vigente. Última modificación 27-09-2022, ley N° 21.488 | M51: General | N51: Calidad
A52: 52 | B52: Ley 21012 | C52: Ministerio del Trabajo y Previsión Social | D52: 42895 | E52: ='Ley 21012'!B1 -> LEY 21012 / 2017, MINISTERIO DE TRABAJO Y PREVISIÓN SOCIAL, GARANTIZA SEGURIDAD DE LOS TRABAJADORES EN SITUACIONES DE RIESGO Y EMERGENCIA | F52: REVISION DOCUMENTACION | G52: 45512 | H52: ='Ley 21012'!B2 -> 1 | I52: N/A | J52: No Aplica | K52: Semestral | L52: Vigente, versión única | M52: General | N52: S&ST
A53: 53 | B53: Ley 20830 | C53: Ministerio Secretaría General de Gobierno | D53: 42115 | E53: ='Ley 20830'!B1 -> LEY 20830 / 2015, MINISTERIO SECRETARIA GENERAL DE GOBIERNO, CREA EL ACUERDO DE UNIÓN CIVIL | F53: REVISION DOCUMENTACION | G53: 45512 | H53: ='Ley 20830'!B2 -> 1 | I53: N/A | J53: No Aplica | K53: Anual | L53: Vigente. Última modificación 10-12-2021, ley 21.400 | M53: General | N53: Calidad
A54: 54 | B54: Ley 20348 | C54: Ministerio del Trabajo y Previsión Social; Subsecretaría del Trabajo | D54: 39983 | E54: ='Ley 20348'!B1 -> LEY 20348 / 2009, MINISTERIO DEL TRABAJO Y PREVISIÓN SOCIAL; SUBSECRETARÍA DEL TRABAJO, RESGUARDA EL DERECHO A LA IGUALDAD EN LAS REMUNERACIONES | F54: REVISION DOCUMENTACION | G54: 45512 | H54: ='Ley 20348'!B2 -> 1 | I54: N/A | J54: No Aplica | K54: Anual | L54: Vigente, versión única | M54: General | N54: Calidad
A55: 55 | B55: Ley 21015 | C55: Ministerio de Desarrollo Social | D55: 42901 | E55: ='Ley 21015'!B1 -> LEY 21015 / 2017, MINISTERIO DE DESARROLLO SOCIAL, INCENTIVA LA INCLUSIÓN DE PERSONAS CON DISCAPACIDAD AL MUNDO LABORAL | F55: REVISION DOCUMENTACION | G55: 45512 | H55: ='Ley 21015'!B2 -> 1 | I55: N/A | J55: No Aplica | K55: Anual | L55: Vigente, versión única | M55: General | N55: Calidad
A56: 56 | B56: Ley 20422 | C56: Ministerio de Planificación | D56: 40219 | E56: ='Ley 20422'!B1 -> LEY 20422 / 2010, MINISTERIO DE PLANIFICACIÓN, ESTABLECE NORMAS SOBRE IGUALDAD DE OPORTUNIDADES E INCLUSIÓN SOCIAL DE PERSONAS CON DISCAPACIDAD | F56: REVISION DOCUMENTACION | G56: 45512 | H56: ='Ley 20422'!B2 -> 1 | I56: N/A | J56: No Aplica | K56: Anual | L56: Vigente.Última modificación 18-02-2023, Decreto 2271 | M56: General | N56: Calidad
A57: 57 | B57: Ley 19284 | C57: Ministerio de Planificación y Cooperación | D57: 34348 | E57: ='Ley 19284'!B1 -> LEY 19284 / 1994, MINISTERIO DE PLANIFICACIÓN Y COOPERACIÓN, ESTABLECE NORMAS PARA LA PLENA INTEGRACION SOCIAL DE PERSONAS CON DISCAPACIDAD | F57: REVISION DOCUMENTACION | G57: 45512 | H57: ='Ley 19284'!B2 -> 1 | I57: N/A | J57: No Aplica | K57: Anual | L57: Vigente. Última modificación 10-02-2010, ley 20.422 | M57: General | N57: Calidad / S&ST
A58: 58 | B58: Ley 20764 | C58: Ministerio del Trabajo y Previsión Social; Subsecretaría del Trabajo | D58: 41838 | E58: ='Ley 20764'!B1 -> LEY 20764 / 2014, MINISTERIO DEL TRABAJO Y PREVISIÓN SOCIAL, MODIFICA EL CÓDIGO DEL TRABAJO EN MATERIA DE PROTECCIÓN A LA MATERNIDAD, LA PATERNIDAD Y LA VIDA FAMILIAR Y ESTABLECE UN PERMISO POR MATRIMONIO DEL TRABAJADOR | F58: REVISION DOCUMENTACION | G58: 45512 | H58: ='Ley 20764'!B2 -> 1 | I58: N/A | J58: No Aplica | K58: Anual | L58: Vigente, versión única | M58: General | N58: Calidad
A59: 59 | B59: Ley 21042 | C59: Ministerio del Trabajo y Previsión Social | D59: 43047 | E59: ='Ley 21042'!B1 -> LEY 21042 / 2017, MINISTERIO DEL TRABAJO Y PREVISIÓN SOCIAL, APLICA AL TRABAJADOR QUE CELEBRA UN ACUERDO DE UNIÓN CIVIL EL PERMISO LABORAL QUE SE OTORGA A QUIEN CONTRAE MATRIMONIO | F59: REVISION DOCUMENTACION | G59: 45512 | H59: ='Ley 21042'!B2 -> 1 | I59: N/A | J59: No Aplica | K59: Anual | L59: Vigente, versión única | M59: General | N59: Calidad
A60: 60 | B60: NCh2245:2021 | C60: Ministerio de Salud | E60: HOJA DE DATOS DE SEGURIDAD PARA PRODUCTOS QUIMICOS - CONTENIDO Y ORDEN DE LAS SECCIONES | F60: INSPECCION | G60: 45512 | H60: ='NCh2245'!B2 -> 1 | I60: SI | J60: Cerrado | K60: Mensual | L60: Sin certificación de vigencia | M60: General | N60: Ambiente
A61: 61 | B61: Ley 21018 | C61: Ministerio del Trabajo y Previsión Social | D61: 42906 | E61: ='Ley 21018'!B1 -> CONFIERE COMPETENCIA A LOS TRIBUNALES LABORALES PARA CONOCER DE LAS CONTIENDAS EN QUE, LOS CAUSAHABIENTES DEL TRABAJADOR, BUSCAN HACER EFECTIVA LA RESPONSABILIDAD DEL EMPLEADOR, DERIVADA DE ACCIDENTES DEL TRABAJO O ENFERMEDADES PROFESIONALES | F61: REVISION DOCUMENTACION | G61: 45512 | H61: ='Ley 21018'!B2 -> 1 | I61: N/A | J61: No Aplica | K61: Mensual | L61: Vigente, versión única | M61: General | N61: Calidad
A62: 62 | B62: Ley 21122 | C62: Ministerio del Trabajo y Previsión Social | D62: 43432 | E62: ='Ley 21122'!B1 -> MODIFICA EL CÓDIGO DEL TRABAJO EN MATERIA DE CONTRATO DE TRABAJO POR OBRA O FAENA | F62: REVISION DOCUMENTACION | G62: 45512 | H62: ='Ley 21122'!B2 -> 1 | I62: N/A | J62: No Aplica | K62: Mensual | L62: Vigente, versión única | M62: General | N62: Calidad
A63: 63 | B63: NT 142 | C63: Ministerio de Salud | D63: 41108 | E63: ='NT 142'!B1 -> NORMA TECNICA N° 142, NOTIFICACION ACCIDENTES GRAVES Y FATALES | F63: REVISION DOCUMENTACION | G63: 45512 | H63: ='NT 142'!B2 -> 1 | I63: N/A | J63: No Aplica | K63: Mensual | L63: Sin certificación de vigencia | M63: General | N63: S&ST
A64: 64 | B64: Ley 19.983 | C64: Ministerio de Economía, Fomento y Turismo | D64: 43924 | E64: ='Ley 21217'!B1 -> Ley Nº 19.983, que regula la transferencia y otorga mérito ejecutivo a copia de la factura. | F64: REVISION DOCUMENTACION | G64: 45512 | H64: ='Ley 21217'!B2 -> 1 | I64: N/A | J64: No Aplica | K64: Anual | L64: Vigente. Última modificación 03-04-2020, ley N° 21.217 | M64: General | N64: Calidad
A65: 65 | B65: Ley 21220 | C65: Ministerio del Trabajo y Previsión Social | D65: 43916 | E65: ='Ley 21220'!B1 -> Ley Nº 21.220, Modifica el Código del Trabajo en materia de trabajo a distancia. | F65: EVALUACIONES | G65: 45512 | H65: ='Ley 21220'!B2 -> 1 | I65: N/A | J65: No Aplica | K65: Anual | L65: Vigente, versión única | M65: General | N65: Ambiente
A66: 66 | B66: ORD 1389/007 DT | C66: Dirección del Trabajo; Departamento Jurídico y Fiscalía | D66: 43929 | E66: ='ORD 1389 007 DT'!B1 -> Dictamen Ordinario Nº 1389/007 de la Dirección del Trabajo. | F66: REVISION DOCUMENTACION | G66: 45512 | H66: ='ORD 1389 007 DT'!B2 -> 1 | I66: N/A | J66: No Aplica | K66: Anual | L66: Vigente, versión única | M66: General | N66: Calidad / S&ST
A67: 67 | B67: RES EX 144 | C67: Ministerio del Medio Ambiente | D67: 43887 | E67: ='RES EX 144'!B1 -> Resolución Exenta 144, APRUEBA NORMA BÁSICA PARA LA IMPLEMENTACIÓN DE MODIFICACIÓN AL REGLAMENTO DEL REGISTRO DE EMISIONES Y TRANSFERENCIAS DE CONTAMINANTES, RETC | F67: REVISION DOCUMENTACION | G67: 45512 | H67: ='RES EX 144'!B2 -> 1 | I67: N/A | J67: No Aplica | K67: Anual | L67: Vigente, versión única | M67: General | N67: Ambiente
A68: 68 | B68: DS 18 de 2020 | C68: Ministerio del Trabajo y Previsión Social; Subsecretaria del Trabajo | D68: 44015 | E68: Aprueba Reglamento del articulo 152 quater M del Código del trabajo. Que establece condiciones específicas de seguridad y salud en el trabajo a que deberán sujetarse los trabajadores que prestan servicios en las modalidades de trabajo a distancia o teletrabajo, de acuerdo con los principios y condiciones de la ley N° 16.744 | F68: REVISION DOCUMENTACION | G68: 45512 | H68: 1 | I68: N/A | J68: No Aplica | K68: Anual | L68: Vigente, versión única | M68: General | N68: Calidad / S&ST
A69: 69 | B69: RES EX 1854 | C69: Ministerio de Economía, Fomento y Turismo; subsecretaría de Pesca y Acuicultura | D69: 44806 | E69: Resolución Exenta 1854, DECLARA AREA DE PLAGA Y DE RIESGO DE PLAGA DIDYMO EN CUERPOS DE AGUA QUE SEÑALA | F69: VERIFICACIÓN | G69: 45512 | H69: 1 | I69: N/A | J69: No Aplica | K69: Anual | L69: Vigencia 2 años | M69: General | N69: Ambiental
A70: 70 | B70: Ley 21561 | C70: Ministerio del Trabajo y Previsión Social | D70: 45042 | E70: MODIFICA EL CODIGO DEL TRABAJO CON EL OBJETO DE REDUCIR LA JORNADA LABORAL | F70: REVISION DOCUMENTACION | G70: 45512 | H70: 1 | I70: N/A | J70: No Aplica | K70: Anual | L70: Vigente, Versión Unica | M70: General | N70: Calidad / S&ST
A71: 71 | B71: Ley 21645 | C71: Ministerio del Trabajo y Previsión Social | D71: 45289 | E71: MODIFICA EL TÍTULO II DEL LIBRO II DEL CÓDIGO DEL TRABAJO "DE LA PROTECCIÓN A LA MATERNIDAD, PATERNIDAD Y VIDA FAMILIAR" Y REGULA UN RÉGIMEN DE TRABAJO A DISTANCIA Y TELETRABAJO EN LAS CONDICIONES QUE INDICA | F71: REVISION DOCUMENTACION | G71: 45512 | H71: 1 | I71: N/A | J71: No Aplica | K71: Anual | L71: Vigente, Versión Unica | M71: General | N71: Calidad / S&ST
A72: 72 | B72: Ley 21643 | C72: Ministerio del Trabajo y Previsión Social | D72: 45306 | E72: MODIFICA EL CÓDIGO DEL TRABAJO Y OTROS CUERPOS LEGALES, EN MATERIA DE PREVENCIÓN, INVESTIGACIÓN Y SANCIÓN DEL ACOSO LABORAL, SEXUAL O DE VIOLENCIA EN EL TRABAJO | F72: REVISION DOCUMENTACION | G72: 45512 | H72: 1 | I72: N/A | J72: No Aplica | K72: Anual | L72: Vigente, Versión Unica | M72: General | N72: Calidad / S&ST
A73: 73 | B73: Decreto 160 | C73: Ministerio de Economía, Fomento y Reconstrucción; Subsecretaría de Economía, Fomento y Reconstrucción | D73: 40001 | E73: APRUEBA REGLAMENTO DE SEGURIDAD PARA LAS INSTALACIONES Y OPERACIONES DE PRODUCCIÓN Y REFINACIÓN, TRANSPORTE, ALMACENAMIENTO, DISTRIBUCIÓN Y ABASTECIMIENTO DE COMBUSTIBLES LÍQUIDOS | F73: VERIFICACION | G73: 45512 | H73: 1 | I73: N/A | J73: No Aplica | K73: Anual | L73: Vigente, Versión Unica | M73: General | N73: Calidad / Ambiente / S&ST
A74: 74 | B74: Decreto 44 | C74: Ministerio del Trabajo y Previsión Social; Subsecretaría de Prevención social | D74: 45500 | E74: APRUEBA NUEVO REGLAMENTO SOBRE GESTION PREVENTIVA DE LOS RIESGOS LABORALES PARA UN ENTORNO DE TRABAJO SEGURO Y SALUDABLE | F74: REVISION DOCUMENTACION | G74: 45796 | H74: 0.9 | I74: SI | J74: Implementación | K74: Anual | L74: Vigente, Versión Unica | M74: General | N74: S&ST

Sheet Decreto 44
A1: CUERPO LEGAL | B1: APRUEBA NUEVO REGLAMENTO SOBRE GESTION PREVENTIVA DE LOS RIESGOS LABORALES PARA UN ENTORNO DE TRABAJO SEGURO Y SALUDABLE | C1: EVALUACION DE CUMPLIMIENTO
A2: CUMPLIMIENTO | B2: 0.9
A3: Articulos | B3: Ambito de Aplicación | C3: Frecuencia de Evaluación | D3: Cumple | E3: Parcial | F3: No Cumple | G3: N/A | H3: Registro o Forma de Evidenciar el Cumplimiento
A4: TODOS | B4: Decreto 44: MINISTERIO DEL TRABAJO Y PREVISIÓN SOCIAL, SUBSECRETARIA DE PREVISIÓN SOCIAL | C4: Anual | D4: 0.9 | H4: CUMPLIMIENTO CON IRL MIPER PLAN DE EMERGENCIA PLAN DE GESTION DE RIESGOS DE DESASTRES Y CATASTROFES MAPA DE RIESGOS Y RECURSOS (INTERNO) MAPA DE RIESGOS Y RECURSOS EXTERIOR

Sheet Decreto 160
A1: CUERPO LEGAL | B1: APRUEBA REGLAMENTO DE SEGURIDAD PARA LAS INSTALACIONES Y OPERACIONES DE PRODUCCIÓN Y REFINACIÓN, TRANSPORTE, ALMACENAMIENTO, DISTRIBUCIÓN Y ABASTECIMIENTO DE COMBUSTIBLES LÍQUIDOS | C1: EVALUACION DE CUMPLIMIENTO
A2: CUMPLIMIENTO | B2: =AVERAGE(D4:G4) -> 1
A3: Articulos | B3: Ambito de Aplicación | C3: Frecuencia de Evaluación | D3: Cumple | E3: Parcial | F3: No Cumple | G3: N/A | H3: Registro o Forma de Evidenciar el Cumplimiento
A4: TODOS | B4: Decreto 160: MINISTERIO DE ECONOMIA, FOMENTO Y RECONSTRUCCION, SUBSECRETARIA DE ECONOMIA FOMENTO Y RECONSTRUCCION: REGLAMENTO DE SEGURIDAD PARA LAS INSTALACIONES Y OPERACIONES DE PRODUCCIÓN Y REFINACIÓN, TRANSPORTE, ALMACENAMIENTO, DISTRIBUCIÓN Y ABASTECIMIENTO DE COMBUSTIBLES LÍQUIDOS | C4: Anual | D4: 1 | H4: Condiciones de almacenaje

Sheet Ley 21643
A1: CUERPO LEGAL | B1: 'MODIFICA EL CÓDIGO DEL TRABAJO Y OTROS CUERPOS LEGALES, EN MATERIA DE PREVENCIÓN, INVESTIGACIÓN Y SANCIÓN DEL ACOSO LABORAL, SEXUAL O DE VIOLENCIA EN EL TRABAJO | C1: EVALUACION DE CUMPLIMIENTO
A2: CUMPLIMIENTO | B2: =AVERAGE(D4:G4) -> 1
A3: Articulos | B3: Ambito de Aplicación | C3: Frecuencia de Evaluación | D3: Cumple | E3: Parcial | F3: No Cumple | G3: N/A | H3: Registro o Forma de Evidenciar el Cumplimiento
A4: TODOS | B4: Ley 21643: MINISTERIO DEL TRABAJO Y PREVISION SOCIAL: PREVENCION, INVESTIGACIÓN Y SANCIÓN DEL ACOSO LABORAL, SEXUAL O DE VIOLENCIA EN EL TRABAJO | C4: Anual | D4: 1 | H4: RIOHS Aplicación de protocolo

Sheet Ley 21645
A1: CUERPO LEGAL | B1: MODIFICA EL TÍTULO II DEL LIBRO II DEL CÓDIGO DEL TRABAJO "DE LA PROTECCIÓN A LA MATERNIDAD, PATERNIDAD Y VIDA FAMILIAR" Y REGULA UN RÉGIMEN DE TRABAJO A DISTANCIA Y TELETRABAJO EN LAS CONDICIONES QUE INDICA | C1: EVALUACION DE CUMPLIMIENTO
A2: CUMPLIMIENTO | B2: =AVERAGE(D4:G4) -> 1
A3: Articulos | B3: Ambito de Aplicación | C3: Frecuencia de Evaluación | D3: Cumple | E3: Parcial | F3: No Cumple | G3: N/A | H3: Registro o Forma de Evidenciar el Cumplimiento
A4: TODOS | B4: Ley 21645: MINISTERIO DEL TRABAJO Y PREVISION SOCIAL: DE LA PROTECCIÓN A LA MATERNIDAD, PATERNIDAD Y VIDA FAMILIAR" Y REGULA UN RÉGIMEN DE TRABAJO A DISTANCIA Y TELETRABAJO | C4: Anual | D4: 1 | H4: Verificación de contratos MIPER Teletrabajo ODI Teletrabajo

Sheet Ley 21561
A1: CUERPO LEGAL | B1: MODIFICA EL CODIGO DEL TRABAJO CON EL OBJETO DE REDUCIR LA JORNADA LABORAL | C1: EVALUACION DE CUMPLIMIENTO
A2: CUMPLIMIENTO | B2: =AVERAGE(D4:G4) -> 1
A3: Articulos | B3: Ambito de Aplicación | C3: Frecuencia de Evaluación | D3: Cumple | E3: Parcial | F3: No Cumple | G3: N/A | H3: Registro o Forma de Evidenciar el Cumplimiento
A4: TODOS | B4: Ley 21561: MINISTERIO DEL TRABAJO Y PREVISION SOCIAL: MODIFICA EL CODIGO DEL TRABAJO CON EL OBJETO DE REDUCIR LA JORNADA LABORAL | C4: Anual | D4: 1 | H4: Verificación de contratos y registros de hora

Sheet RES EX 144
A1: CUERPO LEGAL | B1: Resolución Exenta 144, APRUEBA NORMA BÁSICA PARA LA IMPLEMENTACIÓN DE MODIFICACIÓN AL REGLAMENTO DEL REGISTRO DE EMISIONES Y TRANSFERENCIAS DE CONTAMINANTES, RETC | C1: EVALUACION DE CUMPLIMIENTO
A2: CUMPLIMIENTO | B2: =AVERAGE(D4:G4) -> 1
A3: Articulos | B3: Ambito de Aplicación | C3: Frecuencia de Evaluación | D3: Cumple | E3: Parcial | F3: No Cumple | G3: N/A | H3: Registro o Forma de Evidenciar el Cumplimiento
A4: TODOS | B4: Resolucion Exenta 144, MINISTERIO DE MEDIO AMBIENTE, NORMA BÁSICA PARA LA IMPLEMENTACIÓN DE MODIFICACIÓN AL REGLAMENTO DEL REGISTRO DE EMISIONES Y TRANSFERENCIAS DE CONTAMINANTES, RETC | C4: Anual | D4: 1 | H4: Declaraciones en VU RETC, Retiro de RESPEL

Sheet ORD 1389 007 DT
A1: CUERPO LEGAL | B1: Dictamen Ordinario Nº 1389/007 de la Dirección del Trabajo. | C1: EVALUACION DE CUMPLIMIENTO
A2: CUMPLIMIENTO | B2: =AVERAGE(D4:G4) -> 1
A3: Articulos | B3: Ambito de Aplicación | C3: Frecuencia de Evaluación | D3: Cumple | E3: Parcial | F3: No Cumple | G3: N/A | H3: Registro o Forma de Evidenciar el Cumplimiento
A4: TODOS | B4: Fija sentido y alcance de la Ley N°21.220, de 26.03.2020 | C4: Anual | D4: 1 | H4: Contratos de trabajo

Sheet Ley 21217
A1: CUERPO LEGAL | B1: Ley Nº 19.983, que regula la transferencia y otorga mérito ejecutivo a copia de la factura. | C1: EVALUACION DE CUMPLIMIENTO
A2: CUMPLIMIENTO | B2: =AVERAGE(D4:G4) -> 1
A3: Articulos | B3: Ambito de Aplicación | C3: Frecuencia de Evaluación | D3: Cumple | E3: Parcial | F3: No Cumple | G3: N/A | H3: Registro o Forma de Evidenciar el Cumplimiento
A4: TODOS | B4: Regula transferencia y otorga mérito ejecutivo a copia de la factura. | C4: Anual | D4: 1 | H4: En ejercicio, Horarios, mantención funciones y cargos, recursos para funcionar.

Sheet Ley 21220
A1: CUERPO LEGAL | B1: Ley Nº 21.220, Modifica el Código del Trabajo en materia de trabajo a distancia. | C1: EVALUACION DE CUMPLIMIENTO
A2: CUMPLIMIENTO | B2: =AVERAGE(D4:G4) -> 1
A3: Articulos | B3: Ambito de Aplicación | C3: Frecuencia de Evaluación | D3: Cumple | E3: Parcial | F3: No Cumple | G3: N/A | H3: Registro o Forma de Evidenciar el Cumplimiento
A4: TODOS | B4: Modifica el Código del Trabajo en materia de trabajo a distancia. | C4: Anual | D4: 1 | H4: En ejercicio, Horarios, mantención funciones y cargos, recursos para funcionar.

Sheet Ley 21122
A1: CUERPO LEGAL | B1: MODIFICA EL CÓDIGO DEL TRABAJO EN MATERIA DE CONTRATO DE TRABAJO POR OBRA O FAENA | C1: EVALUACION DE CUMPLIMIENTO
A2: CUMPLIMIENTO | B2: =AVERAGE(D4:G4) -> 1
A3: Articulos | B3: Ambito de Aplicación | C3: Frecuencia de Evaluación | D3: Cumple | E3: Parcial | F3: No Cumple | G3: N/A | H3: Registro o Forma de Evidenciar el Cumplimiento
A4: TODOS | B4: Modifica Codigo del Trabajo en materia de trabajo por obra o faena | C4: Cada vez | D4: 1 | H4: Contratos

Sheet Ley 21018
A1: CUERPO LEGAL | B1: CONFIERE COMPETENCIA A LOS TRIBUNALES LABORALES PARA CONOCER DE LAS CONTIENDAS EN QUE, LOS CAUSAHABIENTES DEL TRABAJADOR, BUSCAN HACER EFECTIVA LA RESPONSABILIDAD DEL EMPLEADOR, DERIVADA DE ACCIDENTES DEL TRABAJO O ENFERMEDADES PROFESIONALES | C1: EVALUACION DE CUMPLIMIENTO
A2: CUMPLIMIENTO | B2: =AVERAGE(D4:G4) -> 1
A3: Articulos | B3: Ambito de Aplicación | C3: Frecuencia de Evaluación | D3: Cumple | E3: Parcial | F3: No Cumple | G3: N/A | H3: Registro o Forma de Evidenciar el Cumplimiento
A4: Artículo único | B4: "Artículo único.- Reemplázase la letra f) del artículo 420 del Código del Trabajo, por la siguiente: "f) los juicios iniciados por el propio trabajador o sus causahabientes, en que se pretenda hacer efectiva la responsabilidad contractual del empleador por los daños producidos como consecuencia de accidentes del trabajo o enfermedades profesionales. Respecto de la responsabilidad extracontractual se seguirán las reglas del artículo 69 de la ley Nº 16.744, y".". | C4: Cada vez que se presente producto de accidente o enfermedad profesional | D4: 1 | H4: Demanda Existente

Sheet NCh2245
A1: CUERPO LEGAL | B1: HOJA DE DATOS DE SEGURIDAD PARA PRODUCTOS QUIMICOS - CONTENIDO Y ORDEN DE LAS SECCIONES | C1: EVALUACION DE CUMPLIMIENTO
A2: CUMPLIMIENTO | B2: =AVERAGE(D4:G4) -> 1
A3: Articulos | B3: Ambito de Aplicación | C3: Frecuencia de Evaluación | D3: Cumple | E3: Parcial | F3: No Cumple | G3: N/A | H3: Registro o Forma de Evidenciar el Cumplimiento
A4: TODOS | B4: Documento que explica contenido y orden de secciones que debe contener una Hoja de Seguridad de productos con sustancias peligrosas dentro del territorio nacional. | C4: Semestral | D4: 1 | H4: Archivo de HDS

Sheet DS 100
A1: CUERPO LEGAL | B1: DECRETO SUPREMO 100 / 2005, MINISTERIO SECRETARIA GENERAL DE LA PRESIDENCIA, FIJA EL TEXTO REFUNDIDO, COORDINADO Y SISTEMATIZADO DE LA CONSTITUCION POLITICA DE LA REPUBLICA DE CHILE | C1: EVALUACION DE CUMPLIMIENTO
A2: CUMPLIMIENTO | B2: =AVERAGE(D4,D5,D6) -> 1
A3: Articulos | B3: Ambito de Aplicación | C3: Frecuencia de Evaluación | D3: Cumple | E3: Parcial | F3: No Cumple | G3: N/A | H3: Registro o Forma de Evidenciar el Cumplimiento
A4: Art. 19 | B4: La Constitución asegura a todas las personas: Nº8 El derecho a vivir en un medio ambiente libre de contaminación. Es deber del Estado velar para que este derecho no sea afectado y tutelar la preservación de la naturaleza. La ley podrá establecer restricciones específicas al ejercicio de determinados derechos o libertades para proteger el medio ambiente; | C4: Cada vez se genera una nueva incorporacion | D4: 1 | H4: Contrato de Trabajo, Entrega de RIOHS, Pago previsionales
A5: Art. 19 | B5: Nº9 El derecho a la protección de la salud. El estado protege el libre e igualitario acceso a las acciones de pomoción, protección y recuperación de la salud y de rehabilitación del individuo. le corresponderá, asimismo, la coordinación y control de las acciones relacionadas con la salud, sea que se presten a través de instituciones públicas o privadas, en la forma y condiciones que determine la ley, la que podrá establecer cotizaciones obligatorias. cada persona tendrá el derecho a elegir el sistema de salud al que desee acogerse, sea éste público o privado; | C5: Cada vez se genera una nueva incorporacion | D5: 1 | H5: Contrato de Trabajo, Entrega de RIOHS, Pago previsionales
A6: Art. 19 | B6: Nº18 El derecho a la seguridad social. Las leyes que regulen el ejercicio de este derecho serán de quorum calificado. La acción del Estado estará dirigida a garantizar el acceso de todos los habitantes al goce de prestaciones básicas uniformes. | C6: Mensual | D6: 1 | H6: Contrato de Trabajo, Entrega de RIOHS, Pago previsionales

Sheet Ley 16,744
A1: CUERPO LEGAL | B1: Ley Nº 16.744 "Establece Normas sobre Accidentes del Trabajo y Enfermedades Profesionales" | C1: EVALUACION DE CUMPLIMIENTO
A2: CUMPLIMIENTO | B2: =AVERAGE(D4:G16) -> 1
A3: Articulos | B3: Ambito de Aplicación | C3: Frecuencia de Evaluación | D3: Cumple | E3: Parcial | F3: No Cumple | G3: N/A | H3: Registro o Forma de Evidenciar el Cumplimiento
B4: Elaboración de REGLAMENTO INTERNO DE ORDEN, HIGIENE Y SEGURIDAD, contempla entre otras las siguientes modificaciones: -Jornadas de trabajo de 45 hrs. -Ley Nº 20949, sobre carga máxima humana -Ley Nº 20096, sobre protección solar -Ley Nº 20101, amplia concepto de Accidente de Trabajo modificaciones de D.S. 101, contiene el Reglamente General de la Ley Nª 16774. -Ley Nº20137 que 0torga permiso laboral por muerte y nacimiento de perientes que indica. -Ley Nº 20166 quw extiende el derecho de las madres trabajadoras a amamantar a sus hijos aún cuando no exista sala cuna. -Circular Nº 3705 de la Superintendencia de seguridad Social. | C4: Anual | D4: 1 | H4: Carpeta personal, Reglamento interno
A5: Artículo 4°.- | B5: La afiliación de un trabajador, hecha en una Caja de Previsión para los demás efectos de seguridad social, se entenderá hecha, por el ministerio de la ley, para este seguro, salvo que la entidad empleadora para la cual trabaje se encuentre adherida a alguna Mutualidad. Respecto de los trabajadores de contratistas o subcontratistas, deberán observarse, además, las siguientes reglas: El dueño de la obra, empresa o faena, será, subsidiariamente, responsable de las obligaciones que, en materia de afiliación y cotización, afecten a sus contratistas respecto de sus trabajadores. Igual responsabilidad afectará al contratista en relación con las obligaciones de sus subcontratistas. | C5: Cada vez que se contrate a un nuevo trabajador | D5: 1 | H5: Certificado de adhesión
A6: Artículo 5° | B6: Para los efectos de esta ley se entiende por accidente del trabajo toda lesión que una persona sufra a causa o con ocasión del trabajo, y que le produzca incapacidad o muerte. Son también accidentes del trabajo los ocurridos en el trayecto directo, de ida o regreso, entre la habitación y el lugar del trabajo, y aquéllos que ocurran en el trayecto directo entre dos lugares de trabajo, aunque correspondan a distintos empleadores. En este último caso, se considerará que el accidente dice relación con el trabajo al que se dirigía el trabajador al ocurrir el siniestro. Se considerarán también accidentes del trabajo los sufridos por dirigentes de instituciones sindicales a causa o con ocasión del desempeño de sus cometidos gremiales. Exceptúanse los accidentes debidos a fuerza mayor extraña que no tenga relación alguna con el trabajo y los producidos intencionalmente por la víctima. La prueba de las excepciones corresponderá al organismo administrador. | C6: Cada vez que se reporte un accidente | D6: 1 | H6: Registro Investigación de Accidente/DIAT
A7: Artículo 7°, inciso 1.- | B7: Es enfermedad profesional la causada de una manera directa por el ejercicio de la profesión o el trabajo que realice una persona y que le produzca incapacidad o muerte. | C7: Cada vez que se reporte una enfermedad | D7: 1 | H7: Protocolos en caso de enfermedad profesional, según infomación reportada por Mutual , DIEP
A8: Artículo 66° | B8: En toda industria o faena en que trabajen más de 25 personas deberán funcionar uno o más Comités Paritarios de Higiene y Seguridad, que tendrán las siguientes funciones: 1.- Asesorar e instruir a los trabajadores para la correcta utilización de los instrumentos de protección; 2.- Vigilar el cumplimiento, tanto por parte de las empresas como de los trabajadores, de las medidas de prevención, higiene y seguridad. 3.- Investigar las causas de los accidentes del trabajo y enfermedades profesionales, que se produzcan en la empresa y de cualquiera otra afección que afecte en forma reiterada o general a los trabajadores y sea presumible que tenga su origen en la utilización de productos fitosanitarios, químicos o nocivos para la salud; 4.- Indicar la adopción de todas las medidas de higiene y seguridad, que sirvan para la prevención de los riesgos profesionales; 5.- Cumplir las demás funciones o misiones que le encomiende el organismo administrador respectivo. El representante o los representantes de los trabajadores serán designados por los propios trabajadores. comerciales que ocupen a más de 100 trabajadores será obligatoria la existencia de un Departamento de Prevención de Riesgos Profesionales, el que será dirigido por un experto en prevención, el cual formará parte, por derecho propio, de los Comités Paritarios. Las empresas estarán obligadas a adoptar y poner en práctica las medidas de prevención que les indique el Departamento de Prevención y/o el Comité Paritario; pero podrán apelar de tales resoluciones ante el respectivo organismo administrador, dentro del plazo de 30 días, desde que le sea notificada la resolución del Departamento de Prevención o del Comité Paritario de Higiene y Seguridad. El i cumplimiento de las medidas acordadas por el Departamento de Prevención o por el Comité Paritario, cuando hayan sido ratificadas por el respectivo organismo administrador, será sancionado en la forma que preceptúa el artículo 68°. | C8: Anual | D8: 1 | H8: Constitución CPHS
A9: Art. 67 | B9: Las empresas estarán obligadas a mantener al día los reglamentos internos de higiene y seguridad en el trabajo y los trabajadores a cumplir con las exigencias de que dichos reglamentos les impongan. Los reglamentos deberán consultar la aplicación de multas a los trabajadores que no utilicen los elementos de protección personal que se les haya proporcionado o que no cumplan las obligaciones que les impónganlas normas, reglamentaciones o instrucciones sobre higiene y seguridad en el trabajo. | C9: Anual o cada vez que exista cambio o incorporación legal pertinente | D9: 1 | H9: Reglamento Interno
A10: Artículo 68°.- | B10: Las empresas o entidades deberán implantar todas las medidas de higiene y seguridad en el trabajo que les prescriban directamente el Servicio Nacional de Salud o, en su caso, el respectivo organismo administrador a que se encuentren afectas, el que deberá indicarlas de acuerdo con las normas y reglamentaciones vigentes. El i cumplimiento de tales obligaciones será sancionado por el Servicio Nacional de Salud de acuerdo con el procedimiento de multas y sanciones previsto en el Código Sanitario, y en las demás disposiciones legales, sin perjuicio de que el organismo administrador respectivo aplique, además, un recargo en la cotización adicional, en conformidad a lo dispuesto en la presente ley. Asimismo, las empresas deberán proporcionar a sus trabajadores, los equipos e implementos de protección necesarios, no pudiendo en caso alguno cobrarles su valor. Si no dieren cumplimiento a esta obligación serán sancionados en la forma que preceptúa el inciso anterior. El Servicio Nacional de Salud queda facultado para clausurar las fábricas, talleres, minas o cualquier sitio de trabajo que signifique un riesgo inminente para la salud de los trabajadores o de la comunidad. | C10: cada vez que seincorpore un nuevo trabajador | D10: 1 | H10: ODI, Entrega EPP, RIOHS
A11: Artículo 69°.- | B11: Cuando, el accidente o enfermedad se deba a culpa o dolo de la entidad empleadora o de un tercero, sin perjuicio de las acciones criminales que procedan, deberán observarse las siguientes reglas: a) El organismo administrador tendrá derecho a repetir en contra del responsable del accidente, por las prestaciones que haya otorgado o deba otorgar, y b) La víctima y las demás personas a quienes el accidente o enfermedad cause daño podrán reclamar al empleador o terceros responsables del accidente, también las otras indemnizaciones a que tengan derecho, con arreglo a las prescripciones del derecho común, incluso el daño moral. | C11: Cada vez que se produzca un accidente | D11: 1 | H11: Registro de investigacion de Accidente/DIAT
A12: Artículo 70°.- | B12: Si el accidente o enfermedad ocurre debido a negligencia inexcusable de un trabajador se le deberá aplicar una multa, de acuerdo con lo preceptuado en el artículo 68°, aún en el caso de que él mismo hubiere sido víctima del accidente. Corresponderá al Comité Paritario de Higiene y Seguridad decidir si medió negligencia inexcusable. | C12: Cada vez que se reporte por parte del organismo administrador una enfermedad profesional o accidente | D12: 1 | G12: -- | H12: Evaluación Mutual, informe investigación incidentes CPHS /DIAT /DIEP
A13: Artículo 71°.- | B13: Los afiliados afectados de alguna enfermedad profesional deberán ser trasladados, por la empresa donde presten sus servicios, a otras faenas donde no estén expuestos al agente causante de la enfermedad. Los trabajadores que sean citados para exámenes de control por los servicios médicos de los organismos administradores, deberán ser autorizados por su empleador para su asistencia, y el tiempo que en ello utilicen será considerado como trabajado para todos los efectos legales. Las empresas que exploten faenas en que trabajadores suyos puedan estar expuestos al riesgo de neumoconiosis, deberán realizar un control radiográfico semestral de tales trabajadores. | C13: Cada vez que exista el riesgo de una exposición a enfermedad profesional | D13: 1 | G13: -- | H13: Examenes pre-ocupacionales, ocupacionales
A14: Artículo 76° | B14: La entidad empleadora deberá denunciar al organismo administrador respectivo, inmediatamente de producido, todo accidente o enfermedad que pueda ocasionar incapacidad para el trabajo o la muerte de la víctima. El accidentado o enfermo, o sus derecho-habientes, o el médico que trató o diagnosticó la lesión o enfermedad, como igualmente el Comité Paritario de Seguridad, tendrán también, la obligación de denunciar el hecho en dicho organismo administrador, en el caso de que la entidad empleadora no hubiere realizado la denuncia. Las denuncias mencionadas en el inciso anterior deberán contener todos los datos que hayan sido indicados por el Servicio Nacional de Salud. Los organismos administradores deberán informar al Servicio Nacional de Salud los accidentes o enfermedades que les hubieren sido denunciados y que hubieren ocasionado incapacidad para el trabajo o la muerte de la víctima, en la forma y con la periodicidad que señale el reglamento. Sin perjuicio de lo dispuesto en los incisos precedentes, en caso de accidentes del trabajo fatales y graves, el empleador deberá informar inmediatamente a la Inspección del Trabajo y a la Secretaría Regional Ministerial de Salud que corresponda, acerca de la ocurrencia de cualquiera de estos hechos. Corresponderá a la Superintendencia de Seguridad Social impartir las instrucciones sobre la forma en que deberá cumplirse esta obligación. En estos mismos casos el empleador deberá suspender de forma inmediata las faenas afectadas y, de ser necesario, permitir a los trabajadores la evacuación del lugar de trabajo. La reanudación de faenas sólo podrá efectuarse cuando, previa fiscalización del organismo fiscalizador, se verifique que se han subsanado las deficiencias constatadas. Las infracciones a lo dispuesto en los incisos cuarto y quinto, serán sancionadas con multa a beneficio fiscal de cincuenta a ciento cincuenta unidades tributarias mensuales, las que serán aplicadas por los servicios fiscalizadores a que se refiere el inciso cuarto. | C14: Cada vez que se genere un accidente o enfermedad | D14: 1 | G14: -- | H14: DIAT - DIEP
A15: Artículo 77 bis.- | B15: El trabajador afectado por el rechazo de una licencia o de un reposo médico por parte de los organismos de los Servicios de Salud, de las Instituciones de Salud Previsional o de las Mutualidades de Empleadores, basado en que la afección invocada tiene o no tiene origen profesional, según el caso, deberá concurrir ante el organismo de régimen previsional a que esté afiliado, que no sea el que rechazó la licencia o el reposo médico, el cual estará obligado a cursarla de inmediato y a otorgar las prestaciones médicas o pecuniarias que correspondan, sin perjuicio de los reclamos posteriores y reembolsos, si procedieren, que establece este artículo. En la situación prevista en el inciso anterior, cualquier persona o entidad interesada podrá reclamar directamente en la Superintendencia de Seguridad Social por el rechazo de la licencia o del reposo médico, debiendo ésta resolver, con competencia exclusiva y sin ulterior recurso, sobre el carácter de la afección que dio origen a ella, en el plazo de treinta días contado desde la recepción de los antecedentes que se requieran o desde la fecha en que el trabajador afectado se hubiere sometido a los exámenes que disponga dicho Organismo, si éstos fueren posteriores. | C15: Cada vez que se genere un accidente | D15: 1 | G15: -- | H15: SUSESO
A16: Artículo 79°.- | B16: Las acciones para reclamar las prestaciones por accidentes del trabajo o enfermedades profesionales prescribirán en el término de cinco años contado desde la fecha del accidente o desde el diagnóstico de la enfermedad. En el caso de la neumoconiosis el plazo de prescripción será de quince años, contado desde que fue diagnosticada. Esta prescripción no correrá contra los menores de 16 años. | C16: Cada vez que se genere un accidente o enfermedad | D16: 1 | G16: -- | H16: SUSESO

Sheet DS148
A1: CUERPO LEGAL | B1: DS 148 APRUEBA REGLAMENTO SANITARIO SOBRE MANEJO DE RESIDUOS PELIGROSOS | C1: EVALUACION DE CUMPLIMIENTO
A2: CUMPLIMIENTO | B2: =AVERAGE(D5:G23) -> 1
A3: Articulos | B3: Ambito de Aplicación | C3: Frecuencia de Evaluación | D3: Cumple | E3: Parcial | F3: No Cumple | G3: N/A | H3: Registro o Forma de Evidenciar el Cumplimiento
A4: Art. 1 | B4: Este Reglamento establece las condiciones sanitarias y de seguridad mínimas a que deberá someterse la generación, tenencia, almacenamiento, transporte, tratamiento, reuso, reciclaje, disposición final y otras formas de eliminación de los residuos peligrosos. | C4: Anual | D4: 1 | H4: Registros Sidrep
A5: Art 4 | B5: Los residuos peligrosos deberan identificarse y etiquetarse de acuerdo a la clasificacion y tipo de riesgo que establece la NCH 2190 OF 93. Esta obligación será exigible desde que tales residuos se almacenen y hasta su eliminacion | C5: Semestral | D5: 1 | H5: Rotulado de residuos peligrosos
A6: Art 6, inciso 1° | B6: Durante el manejo de los residuos peligrosos se deberan tomar todas las precauciones necesarias para prevenir su inflamación o reacción entre ellas su separación y protección frente a cualquier fuente de riesgo capaz de provocar tales efectos | C6: Cada vez que se generen residuos peligrosos | D6: 1 | H6: Rotulado de residuos peligrosos
A7: Art 8 | B7: Artículo 8 Los contenedores de residuos peligrosos deberán cumplir con los siguientes requisitos: a) tener un espesor adecuado y estar construidos con materiales que sean resistentes al residuo almacenado y a prueba de filtraciones, b) estar diseñados para ser capaces de resistir los esfuerzos producidos durante su manipulación, así como durante la carga y descarga y el traslado de los residuos, garantizando en todo momento que no serán derramados, c) estar en todo momento en buenas condiciones, debiéndose reemplazar todos aquellos contenedores que muestren deterioro de su capacidad de contención, d) estar rotulados indicando, en forma claramente visible, las características de peligrosidad del residuo contenido de acuerdo a la Norma Chilena NCh 2.190 Of 93, el proceso en que se originó el residuo, el código de identificación y la fecha de su ubicación en el sitio de almacenamiento. Los contenedores sólo podrán ser movidos manualmente si su peso total incluido el contenido, no excede de 30 kilogramos. Si dicho peso fuere superior, se deberán mover con equipamiento mecánico. Sólo se podrán reutilizar contenedores cuando no se trate de residuos incompatibles, a menos que hayan sido previamente descontaminados. | C7: Anual | D7: 1 | H7: Resolución Sanitaria Bodega Residuos Peligrosos
A8: Art 9 | B8: Sólo se podrán mezclar o poner en contacto entre sí residuos peligrosos cuando sean de naturaleza similar o compatible. Para estos efectos la “Tabla de Incompatibilidades” del artículo 87 tendrá carácter referencial. Con todo, en los procesos de eliminación podrán mezclarse residuos de los grupos A y B de dicha Tabla, cuando se demuestre que los efectos de la reacción que ellos generan se encuentran bajo control. | C8: Anual | D8: 1 | H8: Resolución Sanitaria Bodega Residuos Peligrosos / Inspeccion APR
A9: Art 10 | B9: Un residuo o una mezcla de residuos es peligrosa si presenta riesgo para la salud pública y/o efectos adversos al medio ambiente ya sea directamente o debido a su manejo actual o previsto, como consecuencia de presentar alguna de las características que se definen en el artículo siguiente. | C9: Cada vez que se generen residuos peligrosos | D9: 1 | H9: Resolución Sanitaria Bodega Residuos Peligrosos / Inspeccion APR
A10: Art 15 | B10: Un residuo tendrá la característica de inflamabilidad si presenta cualquiera de las siguientes propiedades: a) Es líquido y presenta un punto de inflamación inferior a 61ºC en ensayos de copa cerrada o no superior a 65,6 ºC en ensayos de copa abierta. No incluyéndose en esta definición las soluciones acuosas con una concentración en volumen de alcohol inferior o igual al 24%. b) No es líquido y es capaz de provocar, bajo condiciones estándares de presión y temperatura (1 atm y 25 °C), fuego por fricción, por absorción de humedad o 10 cambios químicos espontáneos y, cuando se inflama, lo hace en forma tan vigorosa y persistente que ocasiona una situación de peligro. c) Es un gas comprimido inflamable. Se dice que un gas o una mezcla de gases es inflamable cuando al combinarse con aire constituye una mezcla que tiene un punto de inflamación inferior a 61°C. d) Es una sustancia oxidante, tal como los cloratos, permanganatos, peróxidos inorgánicos o nitratos, que genera oxígeno lo suficientemente rápido como para estimular la combustión de materia orgánica. | C10: Cada vez que se generen residuos peligrosos | D10: 1 | H10: Resolución Sanitaria Bodega Residuos Peligrosos / Inspeccion APR
A11: Artículo 18 | B11: Los residuos incluidos en los siguientes listados de categorías se considerarán peligrosos a menos que su generador pueda demostrar ante la Autoridad Sanitaria que no presentan ninguna característica de peligrosidad. El generador podrá proponer a la Autoridad Sanitaria los análisis de caracterización de peligrosidad a realizar sobre la base del conocimiento de sus residuos y de los procesos que los generan, sin perjuicio de lo cual, la Autoridad Sanitaria podrá exigir análisis adicionales a los propuestos conforme a lo señalado en los artículos 12 al 17. | C11: Cada vez que se generen residuos peligrosos | D11: 1 | H11: Resolución Sanitaria Bodega Residuos Peligrosos/ Registro de disposicion final
A12: Art 19 | B12: Los residuos incluidos en la Lista A del artículo 90 se considerarán igualmente peligrosos. No obstante el generador podrá demostrar ante la Autoridad Sanitaria, conforme a lo establecido en los artículos 12 al 17 del presente reglamento, que tales residuos no son peligrosos. A la inversa, se considerará que los residuos incluidos en la Lista B del artículo 90 no son peligrosos. La Autoridad Sanitaria tendrá siempre la facultad de comprobar que un residuo cualquiera es peligroso por presentar alguna característica de peligrosidad conforme a lo establecido en los artículos 12 al 17. | C12: Cada vez que se generen residuos peligrosos | D12: 1 | H12: Resolución Sanitaria Bodega Residuos Peligrosos / Inspeccion CPHS
A13: Artículo 21 | B13: Toda instalación, equipo o contenedor, o cualquiera de sus partes, que haya estado en contacto directo con residuos peligrosos, deberá ser manejado como tal y no podrá ser destinado a otro uso sin que haya sido previamente descontaminado. | C13: Cada vez que ocurra | D13: 1 | H13: Resolución Sanitaria Bodega Residuos Peligrosos / Inspeccion APR
A14: Artículo 22 | B14: Las sustancias químicas incluidas en los Artículos 88 y 89 del presente Reglamento, serán consideradas residuos peligrosos cuando sean descartadas, se encuentren vencidas o fuera de especificación o se encuentren como remanentes en envases y recipientes. Lo mismo procederá respecto de los derrames de cualquiera de dichas sustancias químicas y los materiales contaminados con ellas que deban desecharse. | C14: Cada vez que ocurra | D14: 1 | H14: Inspeccion APRS / Registro disposición final
A15: Artículo 25 | B15: Las instalaciones, establecimientos o actividades que anualmente den origen a más de 12 kilogramos de residuos tóxicos agudos o a más de 12 toneladas de residuos peligrosos que presenten cualquier otra característica de peligrosidad deberán contar con un Plan de Manejo de Residuos Peligrosos presentado ante la Autoridad Sanitaria. | C15: Anual | G15: 1 | H15: Resolución Sanitaria Bodega Residuos Peligrosos / Inspeccion APR
A16: Artículo 29 | B16: Todo sitio destinado al almacenamiento de residuos peligrosos deberá contar con la correspondiente autorización sanitaria de instalación, a menos que éste se encuentre incluido en la autorización sanitaria de la actividad principal. El diseño, la construcción, ampliación y/o modificación de todo sitio que implique almacenamiento de dos o más residuos peligrosos incompatibles o que contemple el almacenamiento de 12 o más kilogramos de residuos tóxicos agudos o 12 o más toneladas de residuos peligrosos que presenten cualquier otra característica de peligrosidad, deberá contar con un proyecto previamente aprobado por la Autoridad Sanitaria. Este proyecto de ingeniería deberá ser elaborado por un profesional idóneo. | C16: En proceso de validacion por Seremi Salud | G16: 1 | H16: Resolución Sanitaria Bodega Residuos Peligrosos / Inspeccion APR
A17: Artículo 31 | B17: El período de almacenamiento de los residuos peligrosos no podrá exceder de 6 meses. Sin embargo, en casos justificados, se podrá solicitar a la Autoridad Sanitaria, una extensión de dicho período hasta por un lapso igual, para lo cual se deberá presentar un informe técnico. | C17: Cada 5 meses desde la fecha de ingreso del primer residuo rotulado | D17: 1 | H17: Rotulado de residuos peligrosos
A18: Artículo 32 | B18: En caso de inexistencia de una Instalación de Eliminación, imposibilidad de acceso a ella u otros casos calificados, la Autoridad Sanitaria podrá autorizar el almacenamiento de residuos peligrosos por períodos prolongados determinados superiores a los establecidos en el artículo precedente. En este caso, el almacenamiento será considerado una Instalación de Eliminación de Residuos Peligrosos y se ajustará en todo a las normas establecidas en el Párrafo I del Título VI del presente Reglamento, sin perjuicio de la aplicación de las disposiciones especiales de este párrafo. Estas Instalaciones sólo podrán almacenar los residuos expresamente autorizados por la Autoridad Sanitaria, la que igualmente deberá autorizar el retiro total o parcial de éstos. | C18: Anual | D18: 1 | H18: Resolución Sanitaria Bodega Residuos Peligrosos
A19: Artículo 33 | B19: Los sitios donde se almacenen residuos peligrosos deberán cumplir las siguientes condiciones: a) Tener una base continua, impermeable y resistente estructural y químicamente a los residuos. b) Contar con un cierre perimetral de a lo menos 1,80 metros de altura que impida el libre acceso de personas y animales. c) Estar techados y protegidos de condiciones ambientales tales como humedad, temperatura y radiación solar. d) Garantizar que se minimizará la volatilización, el arrastre o la lixiviación y en general cualquier otro mecanismo de contaminación del medio ambiente que pueda afectar a la población. e) Tener una capacidad de retención de escurrimientos o derrames no inferior al volumen del contenedor de mayor capacidad ni al 20% del volumen total de los contenedores almacenados. f) Contar con señalización de acuerdo a la Norma Chilena NCh 2.190 Of 93 Excepcionalmente se podrán autorizar sitios de almacenamiento que no cumplan con alguna de estas condiciones, tales como piscinas, lagunas artificiales u otros, si se justifica técnicamente que su diseño protege de la misma forma la salud de la población. | C19: Anaul | D19: 1 | H19: Resolución Sanitaria Bodega Residuos Peligrosos
A20: Art 34 | B20: El sitio de almacenamiento debera tener acceso restingido,en terminos que solo podra ingresar personal debidamente autorizado por el responsable de la instalacion | C20: mensual | D20: 1 | H20: Resolución Sanitaria Bodega Residuos Peligrosos
A21: Artículo 35 | B21: El sitio de almacenamiento de residuos reactivos o inflamables, deberá estar a 15 metros, a lo menos, de los deslindes de la propiedad. | C21: Anual | D21: 1 | H21: Resolución Sanitaria Bodega Residuos Peligrosos
A22: Artículo 80 | B22: Los tenedores de residuos peligrosos quedan sujetos a un Sistema de Declaración y Seguimiento de tales residuos, válido para todo el país, que tiene por objeto permitir a la autoridad sanitaria disponer de información completa, actual y oportuna sobre la tenencia de tales residuos desde el momento que salen del establecimiento de generación hasta su recepción en una instalación de eliminación. Corresponderá a la Autoridad Sanitaria, en su respectivo territorio, implementar el sistema referido ajustándose a las normas del presente título y a las instrucciones que imparta el Ministerio de Salud. | C22: Semestral | D22: 1 | H22: Resolución Sanitaria Bodega Residuos Peligrosos / RETC
A23: Artículo 81 | B23: Desde que un residuo peligroso sale del establecimiento de generación deberá estar permanentemente acompañado del Documento de Declaración que Será responsable del cumplimiento del presente artículo el actual tenedor de los residuos sin perjuicio de otras responsabilidades.corresponde emitir al generador. | C23: Cada 5 meses/ o autorizacion SEREMI en caso de no contar con la cantidad sufiente de retiro | D23: 1 | H23: Resolución Sanitaria Bodega Residuos Peligrosos / RETC

Sheet DS 594
A1: CUERPO LEGAL | B1: DS 594 "Reglamento sobre condiciones sanitarias y ambientales básicas en los lugares de trabajo" | C1: EVALUACION DEL CUMPLIMIENTO
A2: CUMPLIMIENTO | B2: =AVERAGE(D5:G62) -> 1
A3: Articulos | B3: Ambito de Aplicación | C3: Frecuencia de Evaluación | D3: Cumple | E3: Parcial | F3: No Cumple | G3: N/A | H3: Registro o Forma de Evidenciar el Cumplimiento
A4: Artículo 1 | B4: El presente reglamento establece las condiciones sanitarias y ambientales básicas que deberá cumplir todo lugar de trabajo, sin perjuicio de la reglamentación específica que se haya dictado o se dicte para aquellas faenas que requieren condiciones especiales. Establece, además, los límites permisibles de exposición ambiental a agentes químicos y agentes físicos, y aquellos límites de tolerancia biológica para trabajadores expuestos a riesgo ocupacional. | C4: Anual
A5: Artículo 3° | B5: La empresa está obligada a mantener en los lugares de trabajo las condiciones sanitarias y ambientales necesarias para proteger la vida y la salud de los trabajadores que en ellos se desempeñan, sean éstos dependientes directos suyos o lo sean de terceros contratistas que realizan actividades para ella. | C5: Anual | D5: 1 | H5: Inspecciones APR y MUTUAL, cualitativo
A6: Artículo 4° | B6: La construcción, reconstrucción, alteración, modificación y reparación de los establecimientos y locales de trabajo en general, se regirán por la Ordenanza General de Urbanismo y Construcciones vigente. | C6: anual | D6: 1 | H6: Patente comercial
A7: Art. 5 | B7: Los Pavimentos y revestimientos de los piso serán, en general sólidos y no resbaladizos. En aquellos lugares de trabajo donde se almacene, fabriquen o manipulen productos toxicos corrosivos de cualquier naturaleza,los pisos deben ser de material resistente a estos, <impermeables y no porosos de tal manera que faciliten un alimpieza oportuna y completa. Cuando las operaciones o el proceso exopngan a la humedad del piso, existiran sistemas de drenaje u otros dispositivos que protejan a las pesonas contra la humedad. Para efectos del presente reglamento se entenderá por sustancias tóxicas, corrosivas, peligrosas, infecciosas, radiactivas, venenosas, explosivas o inflamables aquellas definidas en la Norma Oficial NCh 382:2013. | C7: anual | D7: 1 | H7: Inspecciones APR y MUTUAL, cualitativo
A8: Art.6 | B8: Las paredes interiores de los lugares de trabajo, los cielos rasos, puertas y ventanas y demás elementos estructurales, serán mantenidos en buen estado de limpieza y conservación, y será pintados, cuando el caso lo requiera, de acuerdo a la naturaleza de las labores que se ejecutan. | C8: anual | D8: 1 | H8: Inspecciones APR y MUTUAL, cualitativo
A9: Art.7 | B9: Los pisos de lugares de trabajo, así como los pasillo de tránsitos , se mantendrán libres de todo obstáculo que impida un fácil y seguro desplazamiento de los trabajadores, tanto en las tareas normales como en situaciones de emergencia. | C9: Mensual | D9: 1 | H9: Inspección CPHS
A10: Art 8 | B10: Los pasillos de circulacion seran lo suficientemente amplios de modo que permitanel movimiento seguro del personal tanto en sus desplazamientos habituales como para el movimiento de materiales, sin exponerlo a accidentes. Asi tambien los espacios entre maquinas por donde circulen psersonas no deberan ser inferiores a 150 cm. | C10: anual | D10: 1 | H10: Inspecciones APR y MUTUAL, cualitativo /CPHS
A11: Art 10 | B11: En los trabajos que necesariamente deban ser realizados en locales descubiertos o en sitios a cielo abierto, deberan tomarse precauciones adecuadas que protejan a los trabajadores contra las inclemencias del tiempo. | C11: cada vez | D11: 1 | H11: ODI, EPP, AST Terreno, Programa Radiación UV Solar
A12: Art. 11 | B12: Los lugares de trabajo deberán mantenerse en buenas condiciones de orden y limpieza. Además, deberán tomarse medidas efectivas para evitar la entrada o eliminar la presencia de insectos, roedores y otras plagas de interés sanitario. | C12: Mensual | D12: 1 | H12: Contrato Empresa Control de plagas y resolución sanitaria
A13: Art 12 | B13: Todo lugar de trabajo debera contar con agua potable destinada al consumo humano y necesidades basicas de higiene y aseo personal de uso individual y colectivo. Las instalaciones, artefactos, canalizaciones y dispoositivos complementarios de los servicios de agua potable deberan cumpir con las disposiciones legales vigentes sobre la materia. Las redes de distribucion de aguas provenientes de abastecimientos distintos de la red publica de agua potable, deberan ser totalmente independientes de esta ultima, sin interconexiones de ninguna especie entre ambas. | C13: Mensual | D13: 1 | H13: Boleta agua
A14: Art 13 | B14: Cualquiera sea los sistemas de abastecimiento, el agua potable debera cumplir con los requisitos fisicos, quimicos, radiactivos y bacteriologiocs, establecidos en la reglamentacion vigente sobre la materia | C14: Mensual | D14: 1 | H14: boleta de agua
A15: Art. 16: | B15: No podrán vaciarse a la red pública de desagües de aguas servidas sustancias radiactivas, corrosivas, venenosas, infecciosas, explosivas o inflamables o que tengan carácter peligroso en conformidad a la legislación y reglamentación vigente. La descarga de contaminantes al sistema de alcantarillado se ceñirá a lo dispuesto en la Ley de Bases Generales del Medio Ambiente y las normas de emisión y demás normativa complementaria de ésta | C15: Mensual | D15: 1 | H15: Boleta agua
A16: Art.22 | B16: En los lugares de trabajo donde laboren hombres y mujeres deberán existir servicios higiénicos independientes y separados. Será responsabilidad del empleador mantenerlos protegidos del ingreso de vectores de interés sanitario. Asimismo, deberá asegurar su buen estado de funcionamiento y limpieza de sus artefactos, así como disponer, en su interior, de jabón líquido para la limpieza de manos, de sistemas higiénicos desechables para el secado de manos y papel higiénico en cantidad suficiente. Los servicios higiénicos deberán contar con un sistema de ventilación natural o artificial. Sin perjuicio de lo dispuesto en el inciso primero, cuando el número total de trabajadores y trabajadoras sea de diez o menos, el empleador podrá habilitar un servicio higiénico de uso universal para hombres y mujeres, el que deberá contar con cierre interior y cumplir con las exigencias dispuestas en el inciso precedente. | C16: Anual | D16: 1 | H16: Inspecciones APR y MUTUAL, cualitativo
... A19: Artículo 26 | B19: : Las aguas servidas de carácter doméstico deberán ser conducidas al alcantarillado público, o en su defecto, su disposición final se efectuará por medio de sistemas o plantas particulares en conformidad a los reglamentos específicos vigentes. | C19: Mensual | D19: 1 | H19: boleta de agua
A20: Art. 27, incisos 1 y 2 | B20: Todo lugar de trabajo donde el tipo de actividad requiera el cambio de ropa, deberá estar dotado de un recinto fijo o móvil destinado a vestidor, cuyo espacio interior deberá estar limpio y protegido de condiciones climáticas externas. Cuando trabajen hombres y mujeres los vestidores deberán ser independientes y separados. En este recinto deberán disponerse los casilleros guardarropas, los que estarán en buenas condiciones, serán ventilados y en número igual al total de trabajadores ocupados en el trabajo o faena. | C20: cuando aplique | G20: 1 | H20: Inspección CPHS
A21: Artículo 28 | B21: Cuando por la naturaleza o modalidad del trabajo que se realiza, los trabajadores se vean precisados a consumir alimentos en el sitio de trabajo, se dispondrá de un comedor para este propósito, el que estará completamente aislado de las áreas de trabajo y de cualquier fuente de contaminación ambiental y será reservado para comer, pudiendo utilizarse además para celebrar reuniones y actividades recreativas. El empleador deberá adoptar las medidas necesarias para mantenerlo en condiciones higiénicas adecuadas. El comedor estará provisto con mesas y sillas con cubierta de material lavable y piso de material sólido y de fácil limpieza, deberá contar con sistemas de protección que impidan el ingreso de vectores y estará dotado con agua potable para el aseo de manos y cara. Además, en el caso que los trabajadores deban llevar su comida al inicio del turno de trabajo, dicho comedor deberá contar con un medio de refrigeración, cocinilla, lavaplatos y sistema de energía eléctrica. | C21: anual | D21: 1 | H21: Inspecciones APR y MUTUAL, cualitativo
A22: Art 32 | B22: Todo lugar de trabajo debera mantener por medios naturales o artificiales una ventilacion que contribuya a proporcionar condiciones ambientales confortables y que no causen molestias o perjudiquen la salud del trabajador. | C22: anual | D22: 1 | H22: Inspecciones APR y MUTUAL, cualitativo
A23: Artículo 33 | B23: Cuando existan agentes definidos de contaminación ambiental que pudieran ser perjudiciales para la salud del trabajador, tales como aerosoles, humos, gases, vapores u otras emanaciones nocivas, se deberá captar los contaminantes desprendidos en su origen e impedir su dispersión por el local de trabajo. Con todo, cualquiera sea el procedimiento de ventilación empleado se deberá evitar que la concentración ambiental de tales contaminantes dentro del recinto de trabajo exceda los límites permisibles vigentes. | C23: anual | G23: 1 | H23: Inspecciones de la MUTUAL, cualitativo
A24: Art 34 | B24: Los locales de trabajo se diseñarán de forma que por cada trabajador se provea un volumen de 10 metros cúbicos, como mínimo, salvo que se justifique una renovación adecuada del aire por medios mecánicos. En este caso deberán recibir aire fresco y limpio a razón de 20 metros cúbicos por hora y por persona o una cantidad tal que provean 6 cambios por hora, como mínimo, pudiéndose alcanzar hasta los 60 cambios por hora, según sean las condiciones ambientales existentes, o en razón de la magnitud de la concentración de los contaminantes. | C24: Anual | D24: 1 | H24: Inspecciones de la MUTUAL, cualitativo
A25: Artículo 36 | B25: Los elementos estructurales de la construcción de los locales de trabajo y todas las maquinarias, instalaciones, así como las herramientas y equipos, se mantendrán en condiciones seguras y en buen funcionamiento para evitar daño a las personas. | C25: anual | D25: 1 | H25: Inspecciones de la MUTUAL, cualitativo, Inventario de Equipos
A26: Art. 37 inc. 1 | B26: Deberá suprimirse en los lugares de trabajo cualquier factor de peligro que pueda afectar la salud o integridad física de los trabajadores
A27: Art. 37 inc. 2 | B27: Todos los locales o lugares de trabajo deberán de contar con vías de evacuación horizontales y/o verticales que, además de cumplir con las exigencias de la Ordenanza General de Urbanismo y Construcción, dispongan de salidas en número, capacidad y ubicación y con la identificación apropiada para permitir la segura, rápida y expedita salida de todos sus ocupantes hacia zonas de seguridad. Las puertas de salida no deberán abrirse en contra del sentido de evacuación y sus accesos deberán conservarse señalizados y libres de obstrucciones. Estas salidas podrán mantenerse entornadas, pero no cerradas con llave, candado u otro medio que impida su fácil apertura. | C27: Anual | D27: 1 | H27: Inspecciones de la MUTUAL, cualitativo
A28: Art. 37 inc. 3 | B28: Las dependencias de los establecimientos públicos o privados deberán contar con señalización visible y permanente en las zonas de peligro, indicando el agente y/o condición de riesgo, así como las vías de escape y zonas de seguridad ante emergencias. | C28: Anual | D28: 1 | H28: Inspecciones de la MUTUAL, cualitativo
A29: Art. 37 inc. 4 | B29: Además deberá indicarse claramente por medio de señalización visible y permanente la necesidad de uso de elementos de protección personal específicos cuando sea necesario. | C29: Anual | G29: 1 | H29: Inspecciones de la MUTUAL, cualitativo
A30: Art. 37 inc 5 | B30: Los símbolos y palabras que se utilicen en la señalización, deberán estar de acuerdo con la normativa nacional vigente, y la falta de ella con la que determinen las normas chilenas oficiales y aparecer en el idioma oficial del país y, en caso necesario cuando haya trabajadores de otro idioma, además en el de ellos. | C30: Anual | D30: 1 | H30: Inspecciones de la MUTUAL, cualitativo
A31: Art 38 | B31: Deberan estar debidamente protegidas las partes moviles, transmisiones y puntos de operación de maquinarias y equipos | C31: Cuando corresponda | G31: 1 | H31: Inspecciones de la MUTUAL, cualitativo
A32: Artículo 39 | B32: Las instalaciones eléctricas y de gas de los lugares de trabajo deberán ser construidas, instaladas, protegidas y mantenidas de acuerdo a las normas establecidas por la autoridad competente. | C32: Anual | D32: 1 | H32: Patente comercial
A33: Artículo 40 | B33: Se prohíbe a los trabajadores cuya labor se ejecuta cerca de maquinarias en movimiento y órganos de transmisión, el uso de ropa suelta, cabello largo y suelto, y adornos susceptibles de ser atrapados por las partes móviles. | C33: Anual | G33: 1 | H33: Inspecciones de la MUTUAL, cualitativo
A34: Art. 42, inciso 1 | B34: El almacenamiento de materiales deberá realizarse por procedimientos y en lugares apropiados y seguros para los trabajadores. | C34: anual | D34: 1 | H34: Inspecciones del CPHS
A35: Art. 42 | B35: Las sustancias peligrosas deberán almacenarse sólo en recintos específicos destinados para tales efectos, en las condiciones adecuadas a las características de cada sustancia y estar identificadas de acuerdo a las normas chilenas oficiales en la materia. | C35: cada vez | D35: 1 | H35: resolución Sanitaria Bodega de Residuos Peligrosos
A36: Art. 42 | B36: El empleador mantendrá disponible permanentemente en el recinto de trabajo, un plan detallado de acción para enfrentar emergencias, y una hoja de seguridad donde se incluyan, a lo menos, los siguientes antecedentes de las sustancias peligrosas: nombre comercial, formula química, compuesto activo, cantidad almacenada, características físico químicas, tipo de riesgo más probable ante una emergencia, croquis de ubicación dentro del recinto donde se señalen las vías de acceso y elementos existentes para prevenir y controlar las emergencias. | C36: Semestral | D36: 1 | H36: Plan de Emergencia, HDS
A37: Art. 42 | B37: Con todo, las sustancias inflamables deberán almacenarse en forma independiente y separada del resto de las sustancias peligrosas, en bodegas construidas con resistencia al fuego de acuerdo a lo establecido en la Ordenanza General de Urbanismo y Construcción. | C37: Anual | G37: 1 | H37: Inspecciones del MUTUAL, cualitativo
A38: Art 43 | B38: Para conducir maquinarias automotrices en los lugares de trabajo, como gruas, motoniveladoras, retroexcavadoras y otros similares, los trabajadores deberan poseer licencia de conducir de acuerdo a lo que exige la Ley de Transito. Las grúas, camiones y otros vehículos de carga y maquinaria móvil, deberán contar con alarma de retroceso de tipo sonoro. | C38: Cuando corresponda | G38: 1 | H38: Licencia de Conducir
A39: Art. 44 inc 1 | B39: En todo lugar de trabajo deberán implementarse las medidas necesarias para la prevención de incendios con el fin de disminuir la posibilidad de inicio de un fuego, controlando las cargas combustibles y las fuentes de calor e inspeccionando las instalaciones a través de un programa preestablecido. | C39: Anual | D39: 1 | H39: Inspecciones del MUTUAL, cualitativo, Plan Emergencia
A40: Art. 44 inc 2 | B40: El control de los productos combustibles deberá incluir medidas tales como programas de orden y limpieza y racionalización de la cantidad de materiales combustibles, tanto almacenados como en proceso. | C40: Anual | D40: 1 | H40: Inspecciones del MUTUAL, cualitativo, Plan Emergencia
A41: Art 44 inc 3 | B41: El control de las fuentes de calor deberá adoptarse en todos aquellos lugares o procesos donde se cuente con equipos e instalaciones eléctricas, maquinarias que puedan originar fricción, chispas mecánicas o de combustión y/o superficies calientes, cuidando que su diseño, ubicación, estado y condiciones de operación, esté de acuerdo a la reglamentación vigente sobre la materia.
A42: Art. 44 inc 4 | B42: En áreas donde exista una gran cantidad de productos combustibles o donde se almacenen, trasvasijen o procesen sustancias inflamables o de fácil combustión, deberá establecerse una estricta prohibición de fumar o encender fuegos, debiendo existir procedimientos específicos de seguridad para la realización de labores de soldadura, corte de metales o similares. | C42: Anual | D42: 1 | H42: Inspecciones del MUTUAL, cualitativo, Plan Emergencia
A43: Art. 45 | B43: Todo lugar de trabajo en que exista algún riesgo de incendio, ya sea por la estructura del edificio por la naturaleza del trabajo que se realiza, deberá contar con extintores de incendio, del tipo adecuado a los materiales combustibles o inflamables que en el existan o se manipulen. El número total de extintores dependerá de la superficie a proteger de acuerdo a lo señalado en el artículo 46°. Los extintores deberán cumplir con los requisitos y características que establece el decreto supremo Nº 369, de 1996, del Ministerio de Economía, Fomento y Reconstrucción, o el que lo reemplace, y en lo no previsto por éste por las normas chilenas oficiales. Además, deberán estar certificados por un laboratorio acreditado de acuerdo a lo estipulado en dicho reglamento. | C43: anual | D43: 1 | H43: factura de recambio, plano de emergencia
A44: Artículo 46. | B44: El potencial de extinción mínimo por superficie de cubrimiento y distancia de traslado será el indicado en la siguiente tabla (ver tabla del artículo 46 DS 594). El número mínimo de extintores deberá determinarse dividiendo la superficie a proteger por la superficie de cubrimiento máxima del extintor indicada en la tabla precedente y aproximando el valor resultante al entero superior. Este número de extintores deberá distribuirse en la superficie a proteger de modo tal que desde cualquier punto, el recorrido hasta el equipo más cercano no supere la distancia máxima de traslado correspondiente. Podrán utilizarse extintores de menor capacidad que los señalados en la tabla precedente, pero en cantidad tal que su contenido alcance el potencial mínimo exigido, de acuerdo a la correspondiente superficie de cubrimiento máxima por extintor. En caso de existir riesgo de fuego clase B, el potencial mínimo exigido para cada extintor será 10B, con excepción de aquellas zonas de almacenamiento de combustible en las que el potencial mínimo exigido será 40 B. | C44: anual | D44: 1 | H44: Inspecciones del MUTUAL, cualitativo
A45: Art. 47 | B45: Los extintores se ubicarán en sitios de fácil acceso y clara identificación, libres de cualquier obstáculo, y estarán en condiciones de funcionamiento máximo. Se colocarán a una altura máxima de 1.3 metros, medidos desde el suelo hasta la base del extintor y estarán debidamente señalizado | C45: anual | D45: 1 | H45: Inspecciones del MUTUAL, cualitativo
A46: Art 48 | B46: Todo el personal que se desempeña en un lugar de trabajo debera ser instruido y entrenado sobre la manera de usar los extintores en caso de emergencia | C46: anual | D46: 1 | H46: Hoja de capacitaciones Mutual
A47: Art 49 | B47: Los extintores que precisan estar situados en intemperie deberan colocarse en un nicho o gaveta que permitiran su retiro expedito y podran tener una puerta de vidrio simple, facil de romper en caso de emergencia. | C47: anual | D47: 1 | H47: Inspecciones del MUTUAL, cualitativo, Plano ubicación extintores
A48: Art. 51 | B48: Los extintores deberán ser sometidos a revisión, control y mantención preventiva según las normas chilenas oficiales, realizada por el fabricante o servicio técnico, de acuerdo con lo indicado en el Decreto N°369 de 1996, del Ministerio de Economía, Fomento y Reconstrucción, por lo menos una vez al año, haciendo constar esta circunstancia en la etiqueta correspondiente, a fin de verificar sus condiciones de funcionamiento. Será responsabilidad del empleador tomar las medidas necesarias para evitar que los lugares de trabajo queden desprovistos de extintores cuando se deba proceder a dicha mantención. | C48: anual | D48: 1 | H48: factura de recambio, plano de emergencia
A49: Artículo 52 | B49: En los lugares en que se almacenen o manipulen sustancias peligrosas, la autoridad sanitaria podrá exigir un sistema automático de detección de incendios. Además, en caso de existir alto riesgo potencial, dado el volumen o naturaleza de las sustancias, podrá exigir la instalación de un sistema automático de extinción de incendios, cuyo agente de extinción sea compatible con el riesgo a proteger. | C49: anual | D49: 1 | H49: Inspecciones del MUTUAL, cualitativo / Inspecciones del CPHS
A50: Art. 53 | B50: El empleador deberá proporcionar a sus trabajadores, libres de todo costo y cualquiera sea la función que éstos desempeñen en la empresa, los elementos de protección personal que cumplan con los requisitos, características y tipos que exige el riesgo a cubrir y la capacitación teórica y práctica necesaria para su correcto empleo debiendo, además, mantenerlos en perfecto estado de funcionamiento. Por su parte el trabajador deberá usarlos en forma permanente mientras se encuentre expuesto al riesgo. | C50: nuevo contratacion | D50: 1 | H50: Acta entrega de EPP/ Registro capacitación
A51: Artículo 54: | B51: Los elementos de protección personal usados en los lugares de trabajo, sean éstos de procedencia nacional o extranjera, deberán cumplir con las normas y exigencias de calidad que rijan a tales artículos según su naturaleza, de conformidad a lo establecido en el decreto N°18, de 1982, del Ministerio de Salud, sobre Certificación de Calidad de Elementos de Protección Personal contra Riesgos Ocupacionales. Sin embargo, si no fuese posible aplicar dicho procedimiento, por la inexistencia de entidades certificadoras, el Instituto de Salud Pública de Chile podrá, transitoriamente, validar la certificación de origen. | C51: anual/ cada vez que se requiera | D51: 1 | H51: certificados de calidad EPP
A52: Art 57 | B52: En caso en que una medicion representativa de las concentraciones de sustancias contaminantes existentes en el ambiente de trabajo o de la exposicion a agentes fisicos, demuestre que han sido sobrepasados los valores que que se establecen como limites permisibles, el empleador debera iniciar de inmediato las acciones necesarias para el control del riesgo en su origen. Si no es factible implementar la o las medidas preventivas en su totalidad, el empleador deberá proteger al trabajador del riesgo residual entregándole la protección personal de acuerdo a lo establecido en el artículo 53 del presente reglamento. En cualquier caso, el empleador será responsable de evitar que los trabajadores realicen su trabajo en condiciones de riesgo para su salud. | C52: anual | G52: 1 | H52: Inspecciones del MUTUAL, cualitativo
A53: Artículo 58: | B53: Se prohíbe la realización de trabajos, sin la protección personal correspondiente, en ambientes en que la atmósfera contenga menos de 18% de oxígeno. Sin embargo, deberá considerarse que la disponibilidad real de oxígeno depende de la presión parcial de esta sustancia. | C53: Anual | G53: 1 | H53: Inspecciones del MUTUAL, cualitativo
A54: Artículo 60: | B54: El promedio ponderado de las concentraciones ambientales de contaminantes químicos no deberá superar los límites permisibles ponderados (LPP) establecidos en el artículo 66 del presente Reglamento. Se podrán exceder momentáneamente estos límites, pero en ningún caso superar cinco veces su valor. Con todo, respecto de aquellas sustancias para las cuales se establece además un límite permisible temporal (LPT), tales excesos no podrán superar estos límites. Tanto los excesos de los límites permisibles ponderados, como la exposición a límites permisibles temporales, no podrán repetirse más de cuatro veces en la jornada diaria, ni más de una vez en una hora. | C54: Cambio de Actividad | G54: 1 | H54: Inspecciones del MUTUAL, cualitativo
A55: Artículo 61: | B55: Las concentraciones ambientales de las sustancias capaces de causar rápidamente efectos narcóticos, cáusticos o tóxicos, de carácter grave o fatal, no podrán exceder en ningún momento los límites permisibles absolutos siguientes: (Ver tabla del Art. 61 DS 594) | C55: Cambio de Actividad | G55: 1 | H55: Inspecciones del MUTUAL, cualitativo
A56: Art.74 | B56: La exposición ocupacional a ruido estable o fluctuante deberá ser controlada de modo que para una jornada de 8 horas diarias ningún trabajador podrá estar expuesto a un nivel de presión sonora continuo equivalente superior a 85 dB(A) lento, medidos en la posición del oído del trabajador. | C56: Anual | D56: 1 | H56: Inspecciones del MUTUAL, cualitativo
A57: Art.75 | B57: Niveles de presión sonora continua equivalentes, diferentes a 85 dB(A) lento, se permitirán siempre que el tiempo de exposición a ruido del trabajador no exceda los valores indicados en la siguiente tabla: (Ver tabla del Art. 75 DS 594) Estos valores se entenderán para trabajadores expuestos sin protección auditiva personal. | C57: Anual | G57: 1 | H57: Inspecciones del MUTUAL, cualitativo
A58: Art.100 | B58: A los trabajadores expuestos al frio debera entregárseles ropa adecuada, la cual sera no muy ajustada y facilmente desabrochable y sacable.La ropa exterior en contacto con el medio debera ser de material aislante. | C58: cuando aplique | D58: 1 | H58: entrega EPP
A59: Art.103 | B59: Todo lugar de trabajo con excepción de faenas mineras subterráneas o similares deberán estar iluminadas con luz natural o artificial que dependerá de la faena o actividad que en él se realice. El valor mínimo de la iluminación promedio será la que se indica a continuación (ver tabla artículo 103 DS 594). | C59: anual | D59: 1 | H59: Evaluación de iluminación. MUTUAL
A60: Art.109 a | B60: A.- Se consideran expuestos a radiación UV aquellos trabajadores que ejecutan labores sometidos a radiación solar directa en días comprendidos entre el 1° de septiembre y el 31 de marzo, entre las 10.00 y las 17.00 horas, y aquellos que desempeñan funciones habituales bajo radiación UV solar directa con un índice UV igual o superior a 6, en cualquier época del año. El índice UV proyectado máximo diario debe ser corregido según las variables latitud, nubosidad, altitud y elementos reflectantes o absorbentes, según información proporcionada por la Dirección Metereológica de Chile. | C60: semestral / cada nuevo trabajador | D60: 1 | H60: Programa Radiacion UV
A61: Art.109 b | B61: B.- Los empleadores de trabajadores expuestos deben realizar la gestión del riesgo de radiación UV adoptando medidas de control adecuadas. Deberán tomar, a lo menos, las siguientes medidas: a) Informar a los trabajadores sobre los riesgos específicos de exposición laboral a radiación UV de origen solar y sus medidas de control en los siguientes términos: "La exposición excesiva y/o acumulada de radiación ultravioleta de fuentes naturales o artificiales produce efectos dañinos a corto y largo plazo, principalmente en ojos y piel que van desde quemaduras solares, queratitis actínica y alteraciones de la respuesta inmune hasta fotoenvejecimiento, tumores malignos de piel y cataratas a nivel ocular." b) Publicar diariamente en un lugar visible el índice UV estimado señalado por la Dirección Meteorologica de Chile y las medidas de control que se deben aplicar, incluidos los elementos de protección personal. c) Identificar los trabajadores expuestos; detectar los puestos de trabajo e individuos que requieran medidas de protección adicionales y verificar la efectividad de las medidas implementadas a su respecto. d) Las medidas específicas de control a implementar, según exposición, son las siguientes, las que deberán emplearse siguiendo las indicaciones señaladas en la Guía Técnica de Radiación UV de Origen Solar dictada por el Ministerio de Salud mediante decreto emitido bajo la fórmula "Por Orden del Presidente de la República": * Ingeniería: realizar un adecuado sombraje de los lugares de trabajo para disminuir la exposición directa a la radiación UV tales como techar, arborizar, mallas oscuras y de trama tupida, parabrisas adecuados; * Administrativas: si la labor lo permite, calendarizar faenas, horarios de colación entre 13:00 y las 15:00hrs en lugares con sombraje adecuado, rotación de puestos de trabajo con la disminución de tiempo de exposición; * Elementos de protección personal, según el grado de exposición, tales como gorros, lentes, factor de protección solar; e) Mantener un programa de instrucción teórico práctico para los trabajadores, de duración mínima de una hora cronológica semestral, sobre el riesgo y consecuencias para la salud por la exposición a radiación UV solar y medidas preventivas a considerar, entre otros. Este programa debe constar por escrito. | C61: semestral / cada nuevo trabajador | D61: 1 | H61: Programa Radiacion UV
A62: Art.122 | B62: En los lugares de trabajo, y de acuerdo con la naturaleza del lugar y de la faena, en los baños, cocinas, comedores y en los dormitorios a que se refiere el artículo 120, deberán adoptarse medidas efectivas que tiendan a evitar la entrada, o a eliminar, la presencia de insectos, roedores y otras plagas de interés sanitario. | C62: Mensual | D62: 1 | H62: contrato Control de plagas

Sheet DFL N°1 Ley Transito
A1: CUERPO LEGAL | B1: DFL 1 FIJA TEXTO REFUNDIDO, COORDINADO Y SISTEMATIZADO DE LA LEY DE TRÁNSITO | C1: EVALUACION DEL CUMPLIMIENTO
A2: CUMPLIMIENTO | B2: =AVERAGE(D4:G62) -> 1
A3: Articulos | B3: Ambito de Aplicación | C3: Frecuencia de Evaluación | D3: Cumple | E3: Parcial | F3: No Cumple | G3: N/A | H3: Registro o Forma de Evidenciar el Cumplimiento
A4: Art. 5, incisos 1, 4 y 5 | B4: Ninguna persona podrá conducir un vehículo motorizado o a tracción animal, sin poseer una licencia expedida por el Director del Departamento de Tránsito y Transporte Público Municipal de una Municipalidad autorizada al efecto; o un permiso provisional que los Tribunales podrán otorgar sólo a los conductores que tengan su licencia retenida por proceso pendiente; o una boleta de citación al Juzgado, dada por los funcionarios a que se refiere el artículo 4° en reemplazo de la licencia o del permiso referido; o algún documento extendido en el extranjero y con validez en Chile en virtud de tratados o acuerdos internacionales en que Chile sea parte. Los documentos antes indicados otorgados en el país, son instrumentos públicos. Se exceptúa de la exigencia establecida en el inciso primero de este artículo a los alumnos en práctica de las escuelas de conductores que, acompañados de un instructor habilitado, lo hagan en vehículos de la escuela. | C4: Cada vez que se genere contrato que implique manejo de maquinarias de estas caracteristicas | D4: 1 | H4: Carpeta de Personal
A5: Art. 6 | B5: Los conductores de vehículos motorizados o a tracción animal, salvo la excepción del artículo anterior, deberán llevar consigo su licencia, permiso o boleta de citación y, requeridos por la autoridad competente, acreditar su identidad y entregar los documentos que los habilitan para conducir.Asimismo, tratándose de vehículos motorizados, deberán portar y entregar el certificado vigente de póliza de un seguro obligatorio de accidentes, el que deberá ser devuelto, siempre y en el acto, al conductor. | C5: Cada vez que se genere contrato que implique manejo de maquinarias de estas caracteristicas | D5: 1 | H5: Carpeta de Personal
A6: Art. 7 | B6: Se prohíbe al propietario o encargado de un vehículo motorizado o a tracción animal facilitarlo a una persona que no posea licencia para conducirlo. Si se sorprendiere conduciendo un vehículo motorizado o a tracción animal a quien no porte los documentos a que se refiere el artículo anterior, Carabineros podrá retirar el vehículo de circulación para ser puesto a disposición del tribunal competente, para la aplicación de las sanciones que correspondan. Si antes de enviarse el parte al respectivo tribunal, lo que no podrá ocurrir sino pasadas cuarenta y ocho horas, el conductor acredita ante Carabineros poseer la documentación adecuada y vigente, se le devolverá el vehículo, cursándose la infracción correspondiente.
A7: Artículo 8, inciso 1 | B7: Los propietarios o encargados de vehículos motorizados y a tracción animal no podrán celebrar actos o contratos que impliquen la conducción de esos vehículos por persona que no tenga una licencia vigente para conducir la clase de vehículo de que se trate | C7: Cada vez que se genere contrato que implique manejo de maquinarias de estas caracteristicas | D7: 1 | H7: Carpeta de Personal
A8: Artículo 61 | B8: Los vehículos deberán estar provistos de los sistemas y accesorios que la ley establece, los que deberán estar en perfecto estado de funcionamiento, de manera que permitan al conductor maniobrar con seguridad. El remolque de vehículos motorizados deberá efectuarse en las condiciones que determine el reglamento. | C8: cada vez que se ocupe por salidas a terreno | D8: 1 | H8: Lista de verificación de camioneta
A9: Artículo 62, primera parte inciso 1.- | B9: Los vehículos deberán reunir las características técnicas de construcción, dimensiones y condiciones de seguridad, comodidad, presentación y mantenimiento que establezca el Ministerio de Transportes y Telecomunicaciones, y no podrán exceder los pesos máximos permitidos por el Ministerio de Obras Públicas. | C9: Anual | D9: 1 | H9: Revision tecnica al dia
A10: Artículo 62, inciso 3 | B10: Los vehículos motorizados deberán contar con su placa patente única grabada, de forma permanente, en sus vidrios y espejos laterales. Un reglamento del Ministerio de Transportes y Telecomunicaciones deberá establecer las características de este grabado.
A11: Artículo 64. | B11: El transporte de carga deberá efectuarse en las condiciones de seguridad que determinen los reglamentos y en vehículos que reúnan los requisitos que aquellos contemplen. Todo vehículo que transporte carga de terceros debe justificarla con la carta de porte a que se refieren los artículos 173º y siguientes del Código de Comercio. La infracción a lo dispuesto en este inciso, será sancionada con multa de 3 a 10 unidades tributarias mensuales, quedando obligados solidariamente a su pago el conductor infractor, el porteador y el cargador. | C11: cada vez que se ocupe por salidas a terreno | D11: 1 | H11: Lista de verificación de camioneta
A12: Artículo 65 | B12: La carga no podrá exceder los pesos máximos que las características técnicas del vehículo permitan, y deberá estar estibada y asegurada de manera que evite todo riesgo de caída desde el vehículo. | C12: cada vez que se ocupe por salidas a terreno | D12: 1 | H12: Lista de verificación de camioneta
A13: Artículo 67 | B13: En los vehículos motorizados de carga no se podrá transportar personas en los espacios destinados a carga, cualquiera que sea la clase de vehículo, salvo en casos justificados, y adoptando las medidas de seguridad apropiadas. En ningún caso los vehículos motorizados de tres ruedas destinados al transporte de carga podrán transportar personas en los espacios destinados a carga.
A14: Artículo 69.- | B14: Los vehículos motorizados deberán estar equipados con neumáticos en buen estado. No podrán circular aquellos cuyos neumáticos tengan sus bandas de rodadura desgastadas o hayan perdido sus condiciones de adherencia al pavimento, ni con reparaciones que afecten la seguridad del tránsito. | C14: cada vez que se ocupe por salidas a terreno | D14: 1 | H14: Lista de verificación de camioneta
A15: Artículo 70.- | B15: Los vehículos deberán contar con el o los sistemas de freno, luces y elementos retroreflectantes que determine el reglamento. | C15: cada vez que se ocupe por salidas a terreno | D15: 1 | H15: Lista de verificación de camioneta
A16: Artículo 101, inciso 1 | B16: Los conductores y los peatones están obligados a obedecer y respetar las señales de tránsito, salvo que reciban instrucciones en contrario de un carabinero o que se trate de las excepciones contempladas en esta ley para vehículos de emergencia. | C16: semestrales | D16: 1 | H16: Capacitacion de conduccion a la defensiva
A17: Artículo 107 | B17: Los conductores tienen derecho a transitar en sus vehículos por las vías públicas, salvo las excepciones que establece esta ley y las medidas que, en contrario y en casos especiales, adopte la autoridad competente. | C17: semestrales | D17: 1 | H17: Capacitacion de conduccion a la defensiva
A18: Artículo 108.- | B18: Todo conductor deberá mantener el control de su vehículo durante la circulación y conducirlo conforme a las normas de seguridad determinadas en esta ley, sin que motivo alguno justifique el desconocimiento o incumplimiento de ellas. Asimismo, los conductores estarán obligados a mantenerse atentos a las condiciones del tránsito del momento. Se prohíbe llevar abiertas las puertas del vehículo, abrirlas antes de su completa detención o abrirlas, mantenerlas abiertas o descender del mismo sin haberse cerciorado previamente de que ello no implica entorpecimiento o peligro para otros usuarios. | C18: Anual | D18: 1 | H18: Permiso de circulación al dia
A19: Artículo 109, inciso 1.- | B19: Ninguna persona podrá conducir un vehículo cuando se encuentre en condiciones físicas o síquicas deficientes. | C19: Anual | D19: 1 | H19: Capacitacion de conduccion a la defensiva
A20: Artículo 110.- | B20: Se prohíbe, al conductor y a los pasajeros, el consumo de bebidas alcohólicas en el interior de vehículos motorizados. Se prohíbe, asimismo, la conducción de cualquier vehículo o medio de transporte, la operación de cualquier tipo de maquinaria o el desempeño de las funciones de guardafrenos, cambiadores o controladores de tránsito, ejecutados en estado de ebriedad, bajo la influencia de sustancias estupefacientes o sicotrópicas, o bajo la influencia del alcohol. | C20: Nueva contratación | D20: 1 | H20: ODI
A21: Artículo 111.- | B21: Para la determinación del estado de ebriedad del imputado o del hecho de encontrarse bajo la influencia del alcohol, el tribunal podrá considerar todos los medios de prueba, evaluando especialmente el estado general del imputado en relación con el control de sus sentidos, como también el nivel de alcohol presente en el flujo sanguíneo, que conste en el informe de alcoholemia o en el resultado de la prueba respiratoria que hubiera sido practicada por Carabineros. Sin perjuicio de lo anterior, se entenderá que hay desempeño en estado de ebriedad cuando el informe o prueba arroje una dosificación igual o superior a 0,8 gramos por mil de alcohol en la sangre o en el organismo. Se entenderá que hay desempeño bajo la influencia del alcohol cuando el informe o prueba arroje una dosificación superior a 0,3 e inferior a 0,8 gramos por mil de alcohol en la sangre. Si la dosificación fuere menor, se estará a lo establecido en el artículo 109 y en el Nº 1 del artículo 200, si correspondiere. | C21: Nueva contratación | D21: 1 | H21: contrato de trabajo (codigo penal)
A22: Artículo 112.- | B22: En las vías de tránsito restringido, la circulación de vehículos y de peatones se hará como lo determine la autoridad y se podrá entrar o salir de ellas solamente por los lugares y en las condiciones que la Dirección de Vialidad o las Municipalidades, en su caso, establezcan mediante la señalización correspondiente. | C22: Anual | D22: 1 | H22: Capacitacion de conduccion a la defensiva
A23: Artículo 144, inciso 1.- | B23: Ninguna persona podrá conducir un vehículo a una velocidad mayor de la que sea razonable y prudente, bajo las condiciones existentes, debiendo considerar los riesgos y peligros presentes y los posibles. | C23: Anual | D23: 1 | H23: Capacitacion de conduccion a la defensiva
A24: Artículo 165.- | B24: Toda persona que conduzca un vehículo en forma de hacer peligrar la seguridad de los demás, sin consideración de los derechos de éstos o infringiendo las reglas de circulación o de seguridad establecidas en esta ley, serán responsables de los perjuicios que de ello provengan. | C24: Nueva contratación | D24: 1 | H24: contrato de trabajo (codigo penal)
A25: Artículo 167.- | B25: En los accidentes del tránsito, constituyen presunción de responsabilidad del conductor, los casos que el artículo 167 de la Ley de Tránsito señala (ver norma citada) | C25: Nueva contratación | D25: 1 | H25: ODI
... A27: Artículo 170, inciso 1.- | B27: Salvo prueba en contrario, las infracciones que se deriven del mal estado y condiciones del vehículo serán imputables a su propietario, sin perjuicio de las responsabilidad que corresponde al conductor. | C27: Anual | D27: 1 | H27: Lista de verificación de camioneta / Capacitacion de conduccion a la defensiva

Sheet REx N° 1930
A1: CUERPO LEGAL | B1: Res. Ex. N°1930 DEJA SIN EFECTO NORMA CHILENA 2190 DEL AÑO 1993 "SUSTANCIAS PELIGROSAS" Y APRUEBA LA NCH. N° 2190 DE 28.ENE.2019 | C1: EVALUACION DEL CUMPLIMIENTO
A2: CUMPLIMIENTO | B2: =AVERAGE(D4:G59) -> 1
A3: Articulos | B3: Ambito de Aplicación | C3: Frecuencia de Evaluación | D3: Cumple | E3: Parcial | F3: No Cumple | G3: N/A | H3: Registro o Forma de Evidenciar el Cumplimiento
A4: 1.1 | B4: Establece disposiciones sobre los distintivos de seguridad con que deben identificarse los riesgos que presentan las sustancias peligrosas, incluyendo requisitos sobre: características de las marcas, etiquetas y rotulos, uso de ellos, exepciones en el uso y lugares en que deben ser colocados. Esta norma se aplica en el transporte de las sustancias peligrosas definidas en NCh382 y NCh2120/1 a NCh2120/9, por vía terrestre, dentro del país y para el comercio de importación/exportación, así como en la manipulación y almacenamiento en tránsito de estas sustancias. NOTA - En nuestro país el transporte de Sustancias Peligrosas por vía marítima y aérea está regulado por el DS 777/1978 y el DS 746/1989 respectivamente, ambos del Ministerio de Defensa Nacional. | C4: Mensual | D4: 1 | H4: Rotulado Bodega, HDS

Sheet D 44
A1: CUERPO LEGAL | B1: D 44, APRUEBA REGLAMENTO QUE ESTABLECE REQUISITOS DE SEGURIDAD Y ROTULACIÓN DE EXTINTORES PORTÁTILES | C1: EVALUACION DEL CUMPLIMIENTO
A2: CUMPLIMIENTO | B2: =AVERAGE(D4:G59) -> 1
A3: Articulos | B3: Ambito de Aplicación | C3: Frecuencia de Evaluación | D3: Cumple | E3: Parcial | F3: No Cumple | G3: N/A | H3: Registro o Forma de Evidenciar el Cumplimiento
A4: Artículo 1, letra a).- | B4: Ámbito de Aplicación - El presente reglamento regulará las siguientes materias: a) Requisitos mínimos de rotulación y de seguridad que deben cumplir todos los extintores portátiles nuevos, tanto manuales como rodantes, de cualquier origen o procedencia, desde que se comercialicen por primera vez en el país | C4: Anual | D4: 1 | H4: Compra y Recarga de Extintores, debe el servicio proporcionar la iconografia adecuada a la normativa vigente.
A5: Artículo 1, letra b).- | B5: Ámbito de Aplicación - El presente reglamento regulará las siguientes materias: b) Requisitos de operación que deben cumplir los Servicios Técnicos de extintores portátiles | C5: Anual | D5: 1 | H5: Lista de chequeo 594 CPHS

Sheet DS67
A1: CUERPO LEGAL | B1: DS 67 APRUEBA REGLAMENTO PARA APLICACION DE ARTICULOS 15 Y 16 DE LEY Nº16.744, SOBRE EXENCIONES, REBAJAS Y RECARGOS DE LA COTIZACION ADICIONAL DIFERENCIADA | C1: EVALUACION DEL CUMPLIMIENTO
A2: FECHA EVALUACION | B2: 44832
A3: CUMPLIMIENTO | B3: =AVERAGE(D5:G5) -> 1
A4: Articulos | B4: Ambito de Aplicación | C4: Frecuencia de Evaluación | D4: Cumple | E4: Parcial | F4: No Cumple | G4: N/A | H4: Registro o Forma de Evidenciar el Cumplimiento
A5: TODOS | B5: Reglamenta Exenciones de las rebajas y recargas de las cotizaciones adicionales por siniestralidad efectiva. | C5: bianual | D5: 1 | H5: Cetificado de pago de cotizaciones de mutual

Sheet DS 63
A1: CUERPO LEGAL | B1: Decreto 63 APRUEBA REGLAMENTO PARA LA APLICACION DE LA LEY Nº 20.001, QUE REGULA EL PESO MAXIMO DE CARGA HUMANA | C1: EVALUACION DEL CUMPLIMIENTO
A2: CUMPLIMIENTO | B2: =AVERAGE(D4:G4) -> 1
A3: Articulos | B3: Ambito de Aplicación | C3: Frecuencia de Evaluación | D3: Cumple | E3: Parcial | F3: No Cumple | G3: N/A | H3: Registro o Forma de Evidenciar el Cumplimiento
A4: TODOS | B4: Completo digital | C4: anual | G4: 1 | H4: Lista de Chequeo inicial MMC
A5: Artículo 1 | B5: Este Reglamento tiene por objeto regular la normativa sobre: a) La exposición a los riesgos a la salud o a las condiciones físicas de los trabajadores, regidos por el Código del Trabajo, que efectúen manipulación manual inevitable de carga y descarga, y b) Las obligaciones del empleador, en la prevención, control, reducción y protección de los riesgos a los trabajadores que realizan estas labores.

Sheet Ley 20949
A1: CUERPO LEGAL | B1: Ley 20949 MODIFICA EL CÓDIGO DEL TRABAJO PARA REDUCIR EL PESO DE LAS CARGAS DE MANIPULACIÓN MANUAL | C1: EVALUACION DEL CUMPLIMIENTO
A2: CUMPLIMIENTO | B2: =AVERAGE(D4:G4) -> 1
A3: Articulos | B3: Ambito de Aplicación | C3: Frecuencia de Evaluación | D3: Cumple | E3: Parcial | F3: No Cumple | G3: N/A | H3: Registro o Forma de Evidenciar el Cumplimiento
A4: TODOS | B4: Completo digital. La presente ley modifica al Código del Trabajo, entre sus objetivos, tiende a evitar el ausentismo laboral causado por dolor lumbar, para lo cual actualiza la normativa de protección de la salud y de las condiciones físicas de los trabajadores que desarrollan labores de manipulación manual, reduciendo el peso en las operaciones de carga y descarga, de 50 a 25 kilogramos. Asimismo, establece que los menores de 18 años y las mujeres no podrán llevar o transportar carga superiores a 20 kilogramos. | C4: anual | D4: 1 | G4: N/A | H4: Lista chequeo inicial MMC

Sheet NCH1411
A1: CUERPO LEGAL | B1: NCH Nº 1411 | C1: EVALUACION DEL CUMPLIMIENTO
A2: CUMPLIMIENTO | B2: =AVERAGE(D4:G4) -> 1
A3: Articulos | B3: Ambito de Aplicación | C3: Frecuencia de Evaluación | D3: Cumple | E3: Parcial | F3: No Cumple | G3: N/A | H3: Registro o Forma de Evidenciar el Cumplimiento
A4: TODOS | B4: OF 1978 Prevención de Riesgos Parte 1 Letreros de seguridad- OF 1978 Parte 2 Señales de seguridad- OF 1978 Parte 3 Tarjetas de Seguridad- OF 2000 Parte 4 Señales de seguridad para la identificacion de riesgos de materiales- OF 1978 Parte 4 Identificacion de riesgos de materiales | C4: Anual | D4: 1 | H4: Inspecciones de CPHS

Sheet LEY 20005
A1: CUERPO LEGAL | B1: Ley 20005 Tipifica y sanciona el acoso sexual | C1: EVALUACION DEL CUMPLIMIENTO
A2: CUMPLIMIENTO | B2: =AVERAGE(D4:G4) -> 1
A3: Articulos | B3: Ambito de Aplicación | C3: Frecuencia de Evaluación | D3: Cumple | E3: Parcial | F3: No Cumple | G3: N/A | H3: Registro o Forma de Evidenciar el Cumplimiento
A4: Art 1º | B4: Art 1º Introduce las siguientes modificaciones en el Codigo del Trabajo: Modificase el Art 2º Las relaciones laborales deberan siempre fundarse en un trato compatible con la dignidad de la persona. Es contrario a ella entre otras conductas el acoso sexual, por tal el que una persona realice en forma indebida por cualquier medio requerimientos de caracter sexual, no consentidos por quien los recibe o que amenacen o perjudiquen su situacion laboral o oportunidades de empleo | C4: cada vez que se requiera | D4: 1 | H4: RIOSH, titulo vigesimo; Investigacion, medidas de resguardo y sanciones del acoso sexual.
A5: TODOS | B5: Introduce modificaciones al Código del Trabajo tipificando y sancionando el acoso sexual; y estableciendo el procedimiento para la investigación y sanción del acoso sexual

Sheet LEY 20096
A1: CUERPO LEGAL | B1: Ley 20096 Establece Mecanismos de Control Aplicables a las Sustancias Agotadoras de la Capa de Ozono | C1: EVALUACION DEL CUMPLIMIENTO
A2: CUMPLIMIENTO | B2: =AVERAGE(D5:G6) -> 0.5
A3: Articulos | B3: Ambito de Aplicación | C3: Frecuencia de Evaluación | D3: Cumple | E3: Parcial | F3: No Cumple | G3: N/A | H3: Registro o Forma de Evidenciar el Cumplimiento
A4: Artículo 1.- | B4: Las disposiciones de esta ley establecen y regulan los mecanismos de control aplicables a las sustancias agotadoras de la capa de ozono estratosférico y a los productos cuyo funcionamiento requiera del uso de dichas sustancias, las medidas destinadas a la prevención, protección y evaluación de los efectos producidos por el deterioro de la capa de ozono, por la exposición a la radiación ultravioleta, y las sanciones aplicables a quienes infrinjan dichas normas. | C4: Anual
A5: Artículo 5.- | B5: Para los efectos de esta ley, se entenderá por "sustancias controladas" aquellas definidas como tales por el Protocolo de Montreal, relativo a las sustancias que agotan la capa de ozono, individualizadas en sus Anexos A, B, C y E, ya sea en estado puro o en mezclas. Para los efectos de esta ley, se entenderá por "productos controlados" todo equipo o tecnología, sea nuevo o usado, que contenga las sustancias señaladas en el inciso anterior, individualizados en el Anexo D del Protocolo de Montreal. Sin que la enumeración sea taxativa, se comprenden en esta categoría las unidades de aire acondicionado para vehículos motorizados, ya sea incorporadas o no a estos últimos, las unidades de aire acondicionado doméstico o industrial, los refrigeradores domésticos o industriales, las bombas de calor, los congeladores, los deshumificadores, los enfriadores de agua, las máquinas de fabricación de hielo, los paneles de aislamiento y los cobertores de tuberías, que contengan sustancias controladas | C5: Anual | D5: 0 | H5: Programa de implementacion de articulado
A6: Artículo 19.- | B6: Sin perjuicio de las obligaciones establecidas en los artículos 184 del Código del Trabajo y 67 de la ley Nº 16.744, los empleadores deberán adoptar las medidas necesarias para proteger eficazmente a los trabajadores cuando puedan estar expuestos a radiación ultravioleta. Para estos efectos, los contratos de trabajo o reglamentos internos de las empresas, según el caso, deberán especificar el uso de los elementos protectores correspondientes, de conformidad con las disposiciones del Reglamento sobre Condiciones Sanitarias y Ambientales Básicas en los lugares de Trabajo. | C6: Anual | D6: 1 | H6: Programa Radicación UV Solar

Sheet DS18
A1: CUERPO LEGAL | B1: D.S. Nº 18 Certificacion de Calidad de EPP | C1: EVALUACION DEL CUMPLIMIENTO
A2: CUMPLIMIENTO | B2: =AVERAGE(D4:G4) -> 1
A3: Articulos | B3: Ambito de Aplicación | C3: Frecuencia de Evaluación | D3: Cumple | E3: Parcial | F3: No Cumple | G3: N/A | H3: Registro o Forma de Evidenciar el Cumplimiento
A4: Art Nº 1 y 2 | B4: Especificaciones técnicas y certificaciones EPP | C4: Anual | D4: 1 | H4: Certificación de Calidad EPP / Revisión desde pagina del ISP

Sheet DS254
A1: CUERPO LEGAL | B1: D.S.Nº 254 Hoja de datos de seguridad de productos Quimicos | C1: EVALUACION DEL CUMPLIMIENTO
A2: CUMPLIMIENTO | B2: =AVERAGE(D4:G4) -> 1
A3: Articulos | B3: Ambito de Aplicación | C3: Frecuencia de Evaluación | D3: Cumple | E3: Parcial | F3: No Cumple | G3: N/A | H3: Registro o Forma de Evidenciar el Cumplimiento
B4: Hoja se seguridad en el Sector que exista sustancia peligrosa | C4: Anual | D4: 1 | H4: HDS / Inspecciones CPHS
A5: Art. 1 | B5: Declárase Norma Oficial de la República de Chile la siguiente: NCh2245.Of2003 Sustancias químicas - Hojas de datos de seguridad - Requisitos.

Sheet DS109
A1: CUERPO LEGAL | B1: D.S.Nº 109 Evaluaciòn de accidente de trabajo y enfermedades profesionales | C1: EVALUACION DEL CUMPLIMIENTO
A2: CUMPLIMIENTO | B2: =AVERAGE(D4:G4) -> 1
A3: Articulos | B3: Ambito de Aplicación | C3: Frecuencia de Evaluación | D3: Cumple | E3: Parcial | F3: No Cumple | G3: N/A | H3: Registro o Forma de Evidenciar el Cumplimiento
A4: TODOS | B4: Completo digital | C4: Anual | D4: 1 | H4: Lista de clasificacion de enfermedades indicadas en DS109
C5: .

Sheet LEY20105
A1: CUERPO LEGAL | B1: Ley Nº 19.419 REGULA ACTIVIDADES QUE INDICA RELACIONADAS CON EL TABACO | C1: EVALUACION DEL CUMPLIEMTNO
A2: CUMPLIMIENTO | B2: =AVERAGE(D4:G4) -> 1
A3: Articulos | B3: Ambito de Aplicación | C3: Frecuencia de Evaluación | D3: Cumple | E3: Parcial | F3: No Cumple | G3: N/A | H3: Registro o Forma de Evidenciar el Cumplimiento
A4: TODOS | B4: Completo digital | C4: nuevo contrato trabajador | D4: 1 | H4: Reglamento interno

Sheet LEY20047
A1: CUERPO LEGAL | B1: Ley Nº 20.047 Establece permiso Paternal | C1: EVALUACION DEL CUMPLIMIENTO
A2: CUMPLIMIENTO | B2: =AVERAGE(D4:G4) -> 1
A3: Articulos | B3: Ambito de Aplicación | C3: Frecuencia de Evaluación | D3: Cumple | E3: Parcial | F3: No Cumple | G3: N/A | H3: Registro o Forma de Evidenciar el Cumplimiento
A4: TODOS | B4: Completo digital | C4: cada vez que se solicita permiso parental | D4: 1 | H4: RIOHS / Entrega de permiso
A5: Artículo único | B5: Intercálase el siguiente inciso segundo, nuevo, en el artículo 195 del Código del Trabajo, pasando los actuales incisos segundo, tercero, cuarto y quinto, a ser incisos tercero, cuarto, quinto y sexto, respectivamente: "Sin perjuicio del permiso establecido en el artículo 66, el padre tendrá derecho a un permiso pagado de cuatro días en caso de nacimiento de un hijo, el que podrá utilizar a su elección desde el momento del parto, y en este caso será de días corridos, o distribuirlo dentro del primer mes desde la fecha del nacimiento. Este permiso también se otorgará al padre que se le conceda la adopción de un hijo, contado desde la respectiva sentencia definitiva. Este derecho es irrenunciable.".

Sheet DS43
A1: CUERPO LEGAL | B1: DS 43 APRUEBA EL REGLAMENTO DE ALMACENAMIENTO DE SUSTANCIAS PELIGROSAS | C1: EVALUACION DEL CUMPLIMIENTO
A2: CUMPLIMIENTO | B2: =AVERAGE(D7:G15) -> 1
A3: Articulos | B3: Ambito de Aplicación | C3: Frecuencia de Evaluación | D3: Cumple | E3: Parcial | F3: No Cumple | G3: N/A | H3: Registro o Forma de Evidenciar el Cumplimiento
A4: Artículo 1 | B4: El presente reglamento establece las condiciones de seguridad de las instalaciones de almacenamiento de sustancias peligrosas. Estas disposiciones regirán preferentemente sobre lo establecido en materias de almacenamiento en el decreto Nº 157 de 2005, del Ministerio de Salud, Reglamento de Pesticidas de Uso Sanitario y Doméstico y de lo establecido en el artículo 42 del decreto Nº 594 de 1999, del Ministerio de Salud, Reglamento sobre Condiciones Sanitarias y Ambientales Básicas en los Lugares de Trabajo.
A5: Artículo 2 | B5: Se entenderá por sustancias peligrosas, o productos peligrosos, para efectos de la aplicación de este reglamento, aquellas que puedan significar un riesgo para la salud, la seguridad o el bienestar de los seres humanos y animales, siendo aquellas clasificadas en la Norma Chilena N° 382:2013, Sustancias Peligrosas - Clasificación (NCh 382:2013), correspondiendo a las siguientes: (revisar listado que indica la norma y las exenciones que señala el artículo N° 3)
A6: Artículo 5°.- | B6: Toda instalación de almacenamiento de sustancias peligrosas sobre 10 toneladas (t) de sustancias inflamables o 30 t de otras clases de sustancias peligrosas requerirá de Autorización Sanitaria para su funcionamiento. En el caso que en una misma planta exista más de una instalación de almacenamiento, el interesado podrá solicitar una autorización por cada una de ellas u optar por una autorización general que incluya todas las instalaciones. Para el almacenamiento de gases en cilindros, se deberá solicitar autorización sanitaria si el área de almacenamiento real es superior a 30 m2 (cilindros llenos), excluyendo pasillos. Para determinar si se debe contar con una instalación de almacenamiento de sustancias peligrosas y su respectiva autorización, en el caso de sustancias en envases, contenedores o cilindros, se deberán sumar todas las sustancias peligrosas que existan en la planta o empresa. Sin perjuicio de lo anterior, en caso que la sumatoria de las sustancias peligrosas supere las cantidades indicadas, pero que por razones debidamente fundadas éstas deban mantenerse en lugares distintos dentro del predio, la autoridad sanitaria determinará si corresponde eximirse de contar con esa instalación y su respectiva autorización, previa solicitud del interesado. En el caso de almacenamiento en estanques fijos, se deberá solicitar autorización cuando el volumen del estanque sea igual o superior a 15 m3 o cuando sea igual o se supere este valor en el caso de varios estanques ubicados a una distancia igual o inferior a 5 m entre ellos. Para el caso de patios de almacenamiento de contenedores o isotanques, se deberá solicitar autorización sanitaria, cuando se almacenen más de 1 unidad. No obstante lo anterior, si el interesado lo solicita, la Autoridad Sanitaria podrá otorgar autorización sanitaria a aquellas instalaciones que almacenen menores cantidades a las indicadas en este artículo. Para obtener la referida autorización el interesado deberá adjuntar los siguientes antecedentes a la Secretaría Regional Ministerial de Salud competente del lugar en que la instalación esté ubicada: - Identificación completa del interesado y de su representante legal en su caso. - Ubicación de la instalación de almacenamiento: calle, número, comuna, ciudad, región. - Especificaciones técnicas de las características constructivas de la instalación de almacenamiento, la cual debe ser elaborada por un profesional idóneo, indicando su nombre, RUT, título profesional, universidad que lo otorgó, fecha de titulación y firma del profesional responsable. - Memoria técnica de los sistemas de extinción de incendios, cuando proceda. - Plan de Emergencias, según lo estipulado en el Título XIV de este reglamento. - Clase de las sustancias, según la clasificación de la NCh 382:2013, que se almacenarán en la instalación, sus cantidades y capacidad máxima de almacenamiento. - Memoria técnica de ventilación, en caso de bodegas. - Procedimiento por escrito de operación de la instalación de almacenamiento. - Análisis de riesgos según lo indicado en artículo 45. Una vez obtenida la autorización, el interesado ingresará y mantendrá actualizados los datos de su instalación y las sustancias peligrosas almacenadas, declarándolos dos veces al año, con fechas límites el 20 de junio y 20 de diciembre, para cada periodo respectivamente, vía electrónica en el sistema que el Ministerio de Salud establezca mediante resolución. Cualquier modificación en la instalación de almacenamiento autorizada, debe ser comunicada a la Secretaría Regional Ministerial de Salud correspondiente, donde se determinará si corresponde otorgar una nueva autorización. | C6: Anual | D6: 1 | G6: N/A | H6: Resolución Sanitaria SEREMI Salud (voluntaria)
A7: Art. 9 | B7: Las sustancias peligrosas deberán estar contenidas en envases, debidamente etiquetadas según lo estipulado en el Título XII del presente reglamento, excepto aquellas que se almacenen a granel. | C7: Semestral | D7: 1 | H7: Inspecciones Check List RESPEL
A8: Art. 9 inc. 2 | B8: Los envases de las sustancias deberán estar diseñados de forma que impidan las pérdidas de contenido; deben ser adecuados para su conservación, ser de un material químicamente compatible con la sustancia, de difícil ruptura y que minimice eventuales accidentes. | C8: Semestral | D8: 1 | H8: Inspecciones Check List RESPEL
A9: Art. 14 | B9: Adicionalmente, también deberán estar disponibles las Hojas de Datos de Seguridad de las sustancias almacenadas de acuerdo a Norma Chilena Oficial Nº 2245:2015, Hoja de Datos de Seguridad para productos químicos - Contenido y orden de las secciones. La responsabilidad de elaborar o proveer la hoja de datos de seguridad, será del fabricante, importador o proveedor de la sustancia o producto, según corresponda. | C9: Semestral | D9: 1 | H9: Inspecciones Check List RESPEL
A10: Art.18 | B10: Estará prohibido fumar al interior de cualquier instalación donde se almacenen sustancias peligrosas, lo que deberá señalarse mediante letreros que indiquen "No fumar", en el acceso principal de la instalación y, en el caso de bodegas, al interior de la misma, en lugares fácilmente visibles. | C10: Semestral | D10: 1 | H10: Inspecciones Check List RESPEL /Prohibicion de fumadores en toda el area
A11: Art. 19 | B11: Podrán almacenarse sustancias peligrosas envasadas sobre el piso o en estanterías de material liso no absorbente, en instalaciones que no estén destinadas al almacenamiento o que no constituyan una bodega, cuando su cantidad total no sea superior a 600 kg o L. | C11: Semestral | D11: 1 | H11: Inspecciones Check List RESPEL
A12: Art.21 | B12: El lugar donde estén almacenadas las sustancias peligrosas deberá contar con un sistema de control de derrames, que puede consistir en materiales absorbentes o bandejas de contención, y contar con un sistema manual de extinción de incendios, a base de extintores, compatibles con los productos almacenados, en que las cantidades, distribución, potencial de extinción y mantenimiento, entre otros aspectos, deberán estar de acuerdo a lo establecido en el decreto Nº 594 de 1999, del Ministerio de Salud, Reglamento sobre Condiciones Sanitarias y Ambientales Básicas en los Lugares de Trabajo. | C12: Semestral | D12: 1 | H12: Inspecciones Check List RESPEL
A13: Art.23 | B13: Los envases menores o iguales a 5 kg o L y los de vidrio, deberán estar en estanterías de material no absorbente, liso y lavable, cerradas o con sistema antivuelco, con control de derrames y ventilación para evitar la acumulación de gases en su interior. Dicha estantería deberá contar con señalización que indique almacenamiento de sustancias peligrosas, de acuerdo a los rótulos de la NCh 2190 Of.2003, oficializada por decreto Nº 43 de fecha 23.04.2004 del Ministerio de Transporte y Telecomunicaciones. En el caso de sustancias tóxicas, la estantería deberá ser siempre cerrada. | C13: Semestral | D13: 1 | H13: Inspecciones Check List RESPEL
A14: Art.24 | B14: Se deberá contar con las hojas de datos de seguridad de cada una de las sustancias almacenadas a disposición de quienes las manejan. | C14: Semestral | D14: 1 | H14: Inspecciones Check List RESPEL
A15: Art.25 | B15: Podrán almacenarse sustancias peligrosas envasadas en bodegas comunes, cuando la cantidad total sea como máximo 12 t. | C15: Semestral | D15: 1 | H15: Inspecciones Check List RESPEL

Sheet DS 458
A1: CUERPO LEGAL | B1: DFL 458 APRUEBA NUEVA LEY GENERAL DE URBANISMO Y CONSTRUCCIONES | C1: EVALUACION DEL CUMPLIMIENTO
A2: CUMPLIMIENTO | B2: =AVERAGE(D4:G15) -> 1
A3: Articulos | B3: Ambito de Aplicación | C3: Frecuencia de Evaluación | D3: Cumple | E3: Parcial | F3: No Cumple | G3: N/A | H3: Registro o Forma de Evidenciar el Cumplimiento
A4: Artículo 116, inciso 1. | B4: La construcción, reconstrucción, reparación, alteración, ampliación y demolición de edificios y obras de urbanización de cualquier naturaleza, sean urbanas o rurales, requerirán permiso de la Dirección de Obras Municipales, a petición del propietario, con las excepciones que señale la Ordenanza General. | C4: anual | D4: 1 | H4: pago de patente
A5: Artículo 116 bis, inciso 1.- | B5: Los propietarios que soliciten un permiso de edificación podrán contratar un revisor independiente, con inscripción vigente en el Registro Nacional de Revisores Independientes de Obras de Construcción, del Ministerio de la Vivienda y Urbanismo creado por la ley Nº 20.071. Sin embargo, será obligatoria la contratación de un revisor independiente cuando se trate de edificios de uso público y demás casos que determine la Ordenanza General. | C5: anual | D5: 1 | H5: pago de patente
A6: Artículo 117.- | B6: Los permisos de subdivisión, loteo o urbanización predial y de construcciones podrán postergarse hasta por un plazo de tres meses, cuando el sector de ubicación del terreno esté afectado por estudios sobre modificaciones del Plan Regulador Tercomunal o Comunal, aprobados por resolución del Alcalde. Esta postergación deberá ser informada previa y favorablemente por la Secretaría Regional correspondiente del Ministerio de Vivienda y Urbanismo. En caso necesario, el citado plazo de tres meses podrá ser prorrogado hasta completar un máximo de doce meses. La prórroga se dispondrá por decreto supremo del Ministerio de Vivienda y Urbanismo dictado "por orden del Presidente de la República" o por resolución del Secretario Regional Ministerial de Vivienda y Urbanismo respectivo, según se trate de estudios sobre modificaciones de un Plan Regulador Intercomunal o de un Plan Regulador Comunal, en su caso. Tanto el decreto supremo como la resolución se publicarán en el Diario Oficial y en algún diario de los de mayor circulación en la comuna. | C6: anual | D6: 1 | H6: pago de patente
A7: Artículo 118, incisos 1 y 2 | B7: La Dirección de Obras Municipales tendrá un plazo de 30 días, contados desde la presentación de la solicitud, para pronunciarse sobre los permisos de construcción. Dicho plazo se reducirá a 15 días, si a la solicitud de permiso se acompañare el informe favorable de un revisor independiente o del arquitecto, en su caso.
A8: Artículo 119°.- | B8: Toda obra de urbanización o edificación deberá ejecutarse con sujeción estricta a los planos, especificaciones y demás antecedentes aprobados por la Dirección de Obras Municipales. Si después de concedido un permiso hubiere necesidad de introducir modificaciones o variantes en el proyecto o en las obras correspondientes, tales modificaciones se tramitarán en la forma que señale la Ordenanza General. La Dirección de Obras proveerá por escrito la información u observaciones sobre el proyecto al propietario o profesional que interviene, en formulario tipo, a solicitud del interesado. Será responsabilidad del profesional aportar los antecedentes necesarios y adecuar el proyecto a las exigencias que se le formulen. | C8: anual | D8: 1 | H8: pago de patente
A9: Artículo 121°.- | B9: La Dirección de Obras Municipales podrá, previa autorización del municipio, permitir nuevas construcciones u otras alteraciones en las construcciones existentes en los terrenos a que se refiere el artículo 59, distintas de las que admite el artículo 59 bis, siempre que el propietario del inmueble renuncie por escritura pública a toda indemnización o pago por dichas mejoras u obras, cuando posteriormente se lleve a cabo la expropiación. En dicha escritura se fijará el valor de expropiación y el plazo dentro del cual deberá adoptarse la línea oficial, siendo de su cargo la demolición. La escritura será inscrita en el Registro de Gravámenes del Conservador de Bienes Raíces y la renuncia afectará a todos los sucesores del renunciante, a cualquier título, en el dominio del inmueble. En caso de incumplimiento del interesado, la Municipalidad podrá desalojar el edificio con el auxilio de la fuerza pública y demolerlo en la parte que corresponda por cuenta del propietario, sin perjuicio de las acciones legales que correspondan, hasta el reintegro total de los costos del desalojo y la demolición. Los gastos de la demolición y desalojo podrán imputarse al valor de la expropiación. | C9: cada vez | D9: 1 | H9: pago de patente
A10: Artículo 122.- | B10: En los antejardines fijados en los planes reguladores sólo podrán efectuarse las construcciones que estén expresamente admitidas en la Ordenanza General de esta ley o en la ordenanza del respectivo instrumento de planificación. Sin perjuicio de lo anterior, podrán autorizarse construcciones provisorias, conforme al artículo 124. | C10: anual | D10: 1 | H10: pago de patente
A11: Artículo 123°.- | B11: En aquellas propiedades que no cumplan con las disposiciones del Plan Regulador y que fueren parcialmente afectadas por siniestros, las Direcciones de Obras Municipales podrán autorizar la ejecución de trabajos de emergencia y de carácter transitorio, destinados a su mantenimiento, por un plazo no mayor a seis meses, el que sólo podrá ser prorrogado por una sola vez hasta por otro periodo igual, siempre que existan causas justificadas. Vencidos los plazos señalados en el inciso anterior, el Alcalde, a petición del Director de Obras Municipales, podrá ordenar la demolición de los edificios existentes y el desalojo de sus ocupantes con el auxilio de la fuerza pública, con cargo al propietario, sin perjuicio de las demás sanciones que procedan. | C11: cada vez | D11: 1 | H11: pago de patente
A12: Artículo 124°.- | B12: El Director de Obras Municipales podrá autorizar la ejecución de construcciones provisorias por una sola vez, hasta por un máximo de tres años, en las condiciones que determine en cada caso. Sólo en casos calificados podrá ampliarse este plazo, con la autorización expresa de la Secretaría Regional respectiva del Ministerio de la Vivienda y Urbanismo. Si, vencido el plazo correspondiente, el beneficiario no retirare las referidas construcciones, el Alcalde podrá ordenar el desalojo y la demolición de las construcciones, con cargo al propietario, con el auxilio de la fuerza pública si fuere necesario, sin perjuicio de imponer las multas que correspondan. | C12: cada vez | D12: 1 | H12: pago de patente
A13: Artículo 130.- | B13: Los derechos municipales a cancelar por permisos de subdivisión, loteos, construcción, etc. no constituyen impuesto, sino el cobro correspondiente al ejercicio de una labor de revisión, inspección y recepción, y se regularán conforme a la siguiente tabla: (revisar tabla del artículo 130 de la ley citada) | C13: anual | D13: 1 | H13: pago de patente
A14: Artículo 132°.- | B14: Los derechos, aportes, garantías u otros pagos, que dicen relación con uniones, empalmes, extensiones, refuerzos o dación de servicios sanitarios y de pavimentación, serán establecidos por resolución del respectivo servicio, previa aprobación del Ministerio de la Vivienda y Urbanismo. | C14: anual | D14: 1 | H14: pago de patente
A15: Artículo 144.- | B15: Terminada una obra o parte de la misma que pueda habilitarse independientemente, el propietario y el arquitecto solicitarán su recepción definitiva por la Dirección de Obras Municipales. Sin perjuicio de las recepciones definitivas parciales, habrá, en todo caso, una recepción definitiva del total de las obras. | C15: anual | D15: 1 | H15: pago de patente

Sheet DS 47
A1: CUERPO LEGAL | B1: DS 47 FIJA NUEVO TEXTO DE LA ORDENANZA GENERAL DE LA LEY GENERAL DE URBANISMO Y CONSTRUCCIONES | C1: EVALUACION DEL CUMPLIMIENTO
A2: CUMPLIMIENTO | B2: =AVERAGE(D4:G13) -> 1
A3: Articulos | B3: Ambito de Aplicación | C3: Frecuencia de Evaluación | D3: Cumple | E3: Parcial | F3: No Cumple | G3: N/A | H3: Registro o Forma de Evidenciar el Cumplimiento
A4: Artículo 3.4.1. | B4: Terminadas todas las obras que contempla un permiso de ejecución de obras de urbanización o parte de él que pueda habilitarse independientemente, se solicitará su recepción definitiva total o parcial al Director de Obras Municipales. Para estos efectos, el urbanizador deberá presentar los planos aprobados por los Servicios competentes, y los siguientes antecedentes, según sea el caso (revisar listado de antecedentes que indica la norma citada): | C4: anual | D4: 1 | H4: patente comercial
A5: Artículo 3.4.1. bis.- | B5: Tratándose de una solicitud de recepción definitiva total o parcial que comprenda uno o más terrenos cedidos para equipamiento, de conformidad al artículo 70 de la Ley General de Urbanismo y Construcciones, deberá adjuntarse, además de los antecedentes señalados en el artículo 3.4.1. de esta Ordenanza, certificado del Conservador de Bienes Raíces respectivo que acredite que dicho terreno se encuentra libre de prohibiciones, hipotecas y gravámenes y certificado del Servicio de Impuestos Internos, así como de las empresas de servicios de utilidad pública que correspondan, en los que conste que dicho terreno se encuentra sin deudas pendientes en el pago de contribuciones y en el pago de los servicios básicos, respectivamente. | C5: anual | D5: 1 | H5: patente comercial
A6: Artículo 3.4.2 | B6: . Será de responsabilidad del urbanizador, la tramitación y obtención de las aprobaciones y la certificación de la ejecución de las obras que contemplen los proyectos, ante los servicios, empresas u organismos técnicos competentes, en forma previa a la solicitud de recepción. | C6: anual | D6: 1 | H6: patente comercial
A7: Artículo 3.4.3 (inciso 1). | B7: Se entenderá por recibido un loteo, cuando el Director de Obras Municipales emita el correspondiente certificado de recepción definitiva de las obras de urbanización. Lo anterior será igualmente aplicable a los demás casos contemplados en el artículo 2.2.4. de esta Ordenanza. | C7: anual | D7: 1 | H7: patente comercial
A8: Artículo 4.14.1. | B8: Los establecimientos industriales o de bodegaje se clasificarán según su rubro o giro de actividad para los efectos de la respectiva patente. | C8: anual | D8: 1 | H8: patente comercial
A9: Artículo 4.14.2. | B9: Los establecimientos industriales o de bodegaje serán calificados caso a caso por el Secretaría Regional Ministerial de Salud respectiva, en consideración a los riesgos que su funcionamiento pueda causar a sus trabajadores, vecindario y comunidad; para estos efectos, se calificarán como sigue: 1. Peligroso: el que por el alto riesgo potencial permanente y por la índole eminentemente peligrosa, explosiva o nociva de sus procesos, materias primas, productos intermedios o finales o acopio de los mismos, pueden llegar a causar daño de carácter catastrófico para la salud o la propiedad, en un radio que excede los límites del propio predio. 2. Insalubre o contaminante: el que por destinación o por las operaciones o procesos que en ellos se practican o por los elementos que se acopian, dan lugar a consecuencias tales como vertimientos, desprendimientos, emanaciones, trepidaciones, ruidos, que puedan llegar a alterar el equilibrio del medio ambiente por el uso desmedido de la naturaleza o por la incorporación a la biósfera de sustancias extrañas, que perjudican directa o indirectamente la salud humana y ocasionen daños a los recursos agrícolas, forestales, pecuarios, piscícolas, u otros. 3. Molesto: aquel cuyo proceso de tratamientos de insumos, fabricación o almacenamiento de materias primas o productos finales, pueden ocasionalmente causar daños a la salud o la propiedad, y que normalmente quedan circunscritos al predio de la propia instalación, o bien, aquellos que puedan atraer insectos o roedores, producir ruidos o vibraciones, u otras consecuencias, causando con ello molestias que se prolonguen en cualquier período del día o de la noche. 4. Inofensivo: aquel que no produce daños ni molestias a la comunidad, personas o entorno, controlando y neutralizando los efectos del proceso productivo o de acopio, siempre dentro del propio predio e instalaciones, resultando éste inocuo. | C9: anual | D9: 1 | H9: patente comercial
A10: Artículo 4.14.3. | B10: Los establecimientos a que se refiere este Capítulo deberán cumplir con todas las demás disposiciones de la presente Ordenanza que les sean aplicables y sólo podrán establecerse en los emplazamientos que determine el instrumento de planificación territorial correspondiente, y a falta de éste, en los lugares que determine la autoridad municipal previo informe favorable de la Secretaría Regional Ministerial de Vivienda y Urbanismo y Secretaría Regional Ministerial de Salud, respectivas. | C10: anual | D10: 1 | H10: patente comercial
A11: Artículo 4.14.10. | B11: Los locales de trabajo tendrán una capacidad volumétrica no inferior a 10 m3 por trabajador, salvo que se justifique una renovación adecuada del aire por medios mecánicos. Las ventanas deberán permitir una renovación mínima de aire de 8 m3 por hora, salvo que se establezcan medios mecánicos de ventilación. En todo caso, la ventilación de los locales de trabajo debe proyectarse de manera que pueda mantenerse en ellos una atmósfera constantemente libre de vapores, polvo, gases nocivos, o un grado de humedad que no exceda al del ambiente exterior. | C11: anual | D11: 1 | H11: Inspecciones CPHS
A12: Artículo 4.14.11. | B12: Los locales de trabajo deben tener puertas de salida que abran hacia el exterior, en número suficiente para permitir su fácil evacuación. Los establecimientos industriales que ocupen más de dos pisos tendrán escaleras en número suficiente para que no se produzcan recorridos mayores de 40 m para llegar a una de ellas. | C12: anual | D12: 1 | H12: Inspecciones CPHS
A13: Artículo 4.14.12. | B13: Los establecimientos industriales deberán estar dotados de servicios higiénicos, a lo menos con el número de artefactos exigidos por el Ministerio de Salud para los lugares de trabajo, de conformidad a la legislación vigente. Se deberá considerar asimismo, espacios e instalaciones para personas con discapacidad en los accesos, rutas accesibles, estacionamientos, circulaciones, vías de evacuación y servicios higiénicos; incluidos el o los recintos de atención de público si el proyecto lo considerare. Los establecimientos que ocupen más de 50 personas tendrán una sala destinada a primeros auxilios y también una sala cuna cuando ocupen personal femenino, en número superior a 20. | C13: anual | D13: 1 | H13: Inspecciones CPHS

Sheet DFL1
A1: CUERPO LEGAL | B1: D.F.L. Nº 1 FIJA EL TEXTO REFUNDIDO, COORDINADO Y SISTEMATIZADO DEL CÓDIGO DEL TRABAJO | C1: EVALUACION DEL CUMPLIMIENTO
A2: CUMPLIMIENTO | B2: =AVERAGE(D4:G27) -> 1
A3: Articulos | B3: Ambito de Aplicación | C3: Frecuencia de Evaluación | D3: Cumple | E3: Parcial | F3: No Cumple | G3: N/A | H3: Registro o Forma de Evidenciar el Cumplimiento
A4: Art. 22, incisos 1 y 2 | B4: La duración de la jornada ordinaria de trabajo no excederá de cuarenta horas semanales y su distribución se podrá efectuar en cada semana calendario o sobre la base de promedios semanales en lapsos de hasta cuatro semanas, con los límites y requisitos señalados en este capítulo. Quedarán excluidos de la limitación de jornada de trabajo los trabajadores que presten servicios a distintos empleadores, los gerentes, administradores, apoderados con facultades de administración y todos aquellos que trabajen sin fiscalización superior inmediata; los contratados de acuerdo con este Código para prestar servicios en su propio hogar o en lugar libremente elegido por ellos, los agentes comisionistas y de seguros, vendedores viajantes, cobradores y demás similares que no ejerzan sus funciones en el local del establecimiento. | C4: anual | D4: 1 | H4: contrato de trabajo
A5: Art.153 | B5: Las empresas establecimientos, faenas o unidades económicas que ocupen normalmente diez o más trabajadores permanentes, contados todos los que presten servicios en las distintas fábricas o secciones, aunque estén situadas en localidades diferentes, estarán obligadas a confeccionar un reglamento interno de orden, higiene y seguridad que contenga las obligaciones y prohibiciones a que deben sujetarse los trabajadores, en relación con sus labores, permanencia y vida en las dependencias de la respectiva empresa o establecimiento. Especialmente, se deberán estipular las normas que se deben observar para garantizar un ambiente laboral digno y de mutuo respeto entre los trabajadores. Una copia del reglamento deberá remitirse al Ministerio de Salud y a la Dirección del Trabajo dentro de los cinco días siguientes a la vigencia del mismo. Cualquier trabajador o las organizaciones sindicales de la empresa respectiva podrán impugnar las disposiciones del reglamento interno que estimaren ilegales, mediante presentación efectuada ante la autoridad de salud o ante la Dirección del Trabajo, según corresponda. De igual modo, esa autoridad o esa Dirección podrán, de oficio, exigir modificaciones al referido reglamento en razón de ilegalidad. Asimismo, podrán exigir que se incorporen las disposiciones que le son obligatorias de conformidad al artículo siguiente. | C5: anual | D5: 1 | H5: Reglamento interno
A6: Art.154 | B6: El reglamento interno deberá contener, a lo menos, las siguientes disposiciones: 1.- las horas en que empieza y termina el trabajo y las de cada turno, si aquél se efectúa por equipos; 2.- los descansos; 3.- los diversos tipos de remuneraciones; 4.- el lugar, día y hora de pago; 5.- las obligaciones y prohibiciones a que estén sujetos los trabajadores; 6.- la designación de los cargos ejecutivos o dependientes del establecimiento ante quienes los trabajadores deban plantear sus peticiones, reclamos, consultas y sugerencias, y en el caso de empresas de doscientos trabajadores o más, un registro que consigne los diversos cargos o funciones en la empresa y sus características técnicas esenciales; 7.- las normas especiales pertinentes a las diversas clases de faenas, de acuerdo con la edad y sexo de los trabajadores, y a los ajustes necesarios y servicios de apoyo que permitan al trabajador con discapacidad un desempeño laboral adecuado; 8.- la forma de comprobación del cumplimiento de las leyes de previsión, de servicio militar obligatorio, de cédula de identidad y, en el caso de menores, de haberse cumplido la obligación escolar; 9.- las normas e instrucciones de prevención, higiene y seguridad que deban observarse en la empresa o establecimiento; 10.- las sanciones que podrán aplicarse por infracción a las obligaciones que señale este reglamento, las que sólo podrán consistir en amonestación verbal o escrita y multa de hasta el veinticinco por ciento de la remuneración diaria; 11.- el procedimiento a que se someterá la aplicación de las sanciones referidas en el número anterior; 12.- El procedimiento al que se someterán y las medidas de resguardo y sanciones que se aplicarán en caso de denuncias por acoso sexual. En el caso de las denuncias sobre acoso sexual, el empleador que, ante una denuncia del trabajador afectado, cumpla íntegramente con el procedimiento establecido en el Título IV del Libro II, no estará afecto al aumento señalado en la letra c) del inciso primero del artículo 168, y 13.- El procedimiento a que se someterán los reclamos que se deduzcan por infracción al artículo 62 bis. En todo caso, el reclamo y la respuesta del empleador deberán constar por escrito y estar debidamente fundados. La respuesta del empleador deberá ser entregada dentro de un plazo no mayor a treinta días de efectuado el reclamo por parte del trabajador. Las obligaciones y prohibiciones a que hace referencia el número 5 de este artículo, y, en general, toda medida de control, sólo podrán efectuarse por medios idóneos y concordantes con la naturaleza de la relación laboral y, en todo caso, su aplicación deberá ser general, garantizándose la impersonalidad de la medida, para respetar la dignidad del trabajador. | C6: anual | D6: 1 | H6: Reglamento interno y Contrato de Trabajo.
A7: Art.156, inciso 1 | B7: Los reglamentos internos y sus modificaciones deberán ponerse en conocimiento de los trabajadores treinta días antes de la fecha en que comiencen a regir, y fijarse, a lo menos, en dos sitios visibles del lugar de las faenas con la misma anticipación. Deberá también entregarse una copia a los sindicatos y a los Comités Paritarios existentes en la empresa. Además, el empleador deberá entregar gratuitamente a los trabajadores un ejemplar impreso que contenga el texto del reglamento interno de la empresa y el reglamento a que se refiere la Ley N° 16.744. | C7: anual | D7: 1 | H7: carpeta personal RRHH
A8: Art. 157. | B8: Titulo III Del Reglamento Interno En los casos en que las infracciones por parte de los trabajadores a las normas de los reglamentos internos se sancionen con multa, ésta no podrá exceder de la cuarta parte de la remuneración diaria del infractor, y de su aplicación podrá reclamarse ante la Inspección del Trabajo que corresponda. | C8: anual | D8: 1 | H8: Contrato de trabajo / carpeta personal
A9: Art. 179. | B9: Título VI De la capacitación ocupacional La empresa es responsable de las actividades relacionadas con la capacitación ocupacional de sus trabajadores, entendiéndose por tal, el proceso destinado a promover, facilitar, fomentar y desarrollar las aptitudes, habilidades o grados de conocimientos de los trabajadores, con el fin de permitirles mejores oportunidades y condiciones de vida y de trabajo; y a incrementar la productividad nacional, procurando la necesaria adaptación de los trabajadores a los procesos tecnológicos y a las modificaciones estructurales de la economía, sin perjuicio de las acciones que en conformidad a la ley competen al Servicio Nacional de Capacitación y Empleo y a los servicios e instituciones del sector público. | C9: anual | D9: 1 | H9: Plan de Capacitación
A10: Art. 181. | B10: Los trabajadores beneficiarios de las acciones de capacitación ocupacional mantendrán íntegramente sus remuneraciones, cualquiera fuere la modificación de sus jornadas de trabajo. No obstante, las horas extraordinarias destinadas a capacitación no darán derecho a remuneración. El accidente que sufriere el trabajador a causa o con ocasión de estos estudios, quedará comprendido dentro del concepto que para tal efecto establece la Ley Nº 16.744 sobre Seguro Social contra Riesgos de Accidentes del Trabajo y Enfermedades Profesionales, y dará derecho a las prestaciones consiguientes. | C10: anual | D10: 1 | H10: Especificado en Reglamento interno y Contrato de Trabajo.
A11: Art.184, incisos 1 y 2 | B11: El empleador estará obligado a tomar todas las medidas necesarias para proteger eficazmente la vida y salud delos trabajadores, manteniendo las condiciones adecuadas de higiene y seguridad en las faenas, como también los implementos necesarios para prevenir accidentes y enfermedades profesionales. Deberá asimismo prestar o garantizar los elementos necesarios para que los trabajadores en caso de accidente o emergencia pueda acceder a una oportuna y adecuada atención médica, hospitalaria y farmacéutica. | C11: anual | D11: 1 | H11: Especificado en Reglamento interno y Contrato de Trabajo.
A12: Art. 194. | B12: TITULO II DE LA PROTECCION A LA MATERNIDAD La protección a la maternidad se regirá por las disposiciones del presente título y quedan sujetos a ellas los servicios de la administración pública, los servicios semifiscales, de administración autónoma, de las municipalidades y todos los servicios y establecimientos, cooperativas o empresas industriales, extractivas, agrícolas o comerciales, sean de propiedad fiscal, semifiscal, de administración autónoma o independiente, municipal o particular o perteneciente a una corporación de derecho público o privado. | C12: Cuando Aplique | D12: 1 | H12: Reglamento interno
A13: Art. 209. | B13: TITULO III DEL SEGURO SOCIAL CONTRA RIESGOS DE ACCIDENTES DEL TRABAJO Y ENFERMEDADES PROFESIONALES El empleador es responsable de las obligaciones de afiliación y cotización que se originan del seguro social obligatorio contra riesgos de accidentes del trabajo y enfermedades profesionales regulado por la ley N° 16.744. En los mismos términos, el dueño de la obra, empresa o faena es subsidiariamente responsable de las obligaciones que en materia de afiliación y cotización, afecten a los contratistas en relación con las obligaciones de sus subcontratistas. | C13: anual | D13: 1 | H13: Incorporación MUTUAL, pago mensual
A14: Art. 210. | B14: TITULO III DEL SEGURO SOCIAL CONTRA RIESGOS DE ACCIDENTES DEL TRABAJO Y ENFERMEDADES PROFESIONALES Las empresas o entidades a que se refiere la ley N° 16.744, están obligadas a adoptar y mantener medidas de higiene y seguridad en la forma, dentro de los términos y con las sanciones que señala esa ley. | C14: anual | D14: 1 | H14: Especificado en Reglamento interno y Contrato de Trabajo.
A15: Art. 211. | B15: TITULO III DEL SEGURO SOCIAL CONTRA RIESGOS DE ACCIDENTES DEL TRABAJO Y ENFERMEDADES PROFESIONALES El seguro de accidentes del trabajo y enfermedades profesionales se financia, en la forma que prescribe la ley N° 16.744, con una cotización básica general y una cotización adicional diferenciada en función de la actividad y riesgo de la empresa o entidad empleadora, ambas de cargo del empleador; y con el producto de las multas que apliquen los organismos administradores, las utilidades o rentas que produzcan la inversión de los fondos de reserva y con las cantidades que estos organismos obtengan por el ejercicio del derecho a repetir contra el empleador. | C15: anual | D15: 1 | H15: Pago mensual de MUTUAL
... A24: Art. 369. | B24: Título VI DE LA HUELGA Y DEL CIERRE TEMPORAL DE LA EMPRESA Si llegada la fecha de término del contrato, o transcurridos más de cuarenta y cinco días desde la presentación del respectivo proyecto si la negociación se ajusta al procedimiento del Capítulo I del Título II, o más de sesenta si la negociación se ajusta al procedimiento del Capítulo II del Título II, las partes aún no hubieren logrado un acuerdo, podrán prorrogar la vigencia del contrato anterior y continuar las negociaciones. | C24: Cuando Aplique | D24: 1 | H24: Reglamento interno
A25: Art. 303.- | B25: LIBRO IV DE LA NEGOCIACIÓN COLECTIVA Título I NORMAS GENERALES Partes. Las partes deben negociar de buena fe, cumpliendo con las obligaciones y plazos previstos en las disposiciones siguientes, sin poner obstáculos que limiten las opciones de entendimiento entre ambas. Para determinar si dos o más empresas deben ser consideradas como un solo empleador para efectos de la negociación colectiva, se estará a lo dispuesto en los incisos cuarto y siguientes del artículo 3°. | C25: Cuando Aplique
A26: Art. 304, inciso 1.- | B26: Ámbito de aplicación. La negociación colectiva podrá tener lugar en las empresas del sector privado y en aquellas en las que el Estado tenga aportes, participación y representación.
A27: Art. 503, inciso 1 | B27: Título II Del procedimiento de reclamación de multas y demás resoluciones administrativas . Las sanciones por infracciones a la legislación laboral y de seguridad social y a sus reglamentos, se aplicarán administrativamente por los respectivos inspectores del trabajo o por los funcionarios que se determinen en el reglamento correspondiente. Dichos funcionarios actuarán como ministros de fe. | C27: Cuando Aplique | D27: 1 | H27: Reglamento interno

Sheet DFL 725 Codigo Sanitario
A1: CUERPO LEGAL | B1: DFL 725 CODIGO SANITARIO | C1: EVALUACION DEL CUMPLIMIENTO
A2: CUMPLIMIENTO | B2: =AVERAGE(D4:G4) -> 1
A3: Articulos | B3: Ambito de Aplicación | C3: Frecuencia de Evaluación | D3: Cumple | E3: Parcial | F3: No Cumple | G3: N/A | H3: Registro o Forma de Evidenciar el Cumplimiento
A4: Art. 73, inciso 1. | B4: Prohíbese descargar las aguas servidas y los residuos industriales o mineros en ríos o lagunas, o en cualquiera otra fuente o masa de agua que sirva para proporcionar agua potable a alguna población, para riego o para balneario, sin que antes se proceda a su depuración en la forma que se señale en los reglamentos. | C4: mensual / semestral | D4: 1 | H4: boleta de agua
A5: Artículo 82 | B5: El reglamento comprenderá normas como las que se refieren a: a) las condiciones de higiene y seguridad que deben reunir los lugares de trabajo, los equipos, maquinarias, instalaciones, materiales y cualquier otro elemento, con el fin de proteger eficazmente la vida, la salud y bienestar de los obreros y empleados y de la población en general; b) las medidas de protección sanitaria y de seguridad que deben adoptarse en la extracción, elaboración y manipulación de substancias producidas o utilizadas en los lugares en que se efectúe trabajo humano; c) las condiciones de higiene y seguridad que deben reunir los equipos de protección personal y la obligación de su uso.
A6: Artículo 83, inciso 1 | B6: Las Municipalidades no podrán otorgar patentes definitivas para la instalación, ampliación o traslado de industrias, sin informe previo de la autoridad sanitaria sobre los efectos que ésta puede ocasionar en el ambiente.
A7: Artículo 84 | B7: El Servicio Nacional de Salud podrá disponer el traslado de aquellas industrias o depósitos de materiales que, a su juicio, representen un peligro para la salud, seguridad y bienestar de la población. La autoridad sanitaria no podrá exigir el traslado antes del plazo de un año, contado desde la fecha de la notificación.
A8: Artículo 87 | B8: El Servicio Nacional de Salud tendrá a su cargo la recopilación y análisis de los datos estadísticos referentes a los accidentes y enfermedades profesionales, los que le deberán ser proporcionados por el empleador, en la forma y con la periodicidad que él señale. Las enfermedades profesionales serán notificadas por el médico que las constate, en la forma y condiciones que el Servicio Nacional de Salud establezca. También, deberá notificar las afecciones que puedan derivarse de intoxicaciones producidas por el uso de plaguicidas o productos fitosanitarios.
A9: Artículo 88 | B9: Corresponde exclusivamente al Servicio Nacional de Salud determinar en cada caso las incapacidades permanentes debidas a accidentes del trabajo o enfermedades profesionales.

Sheet Ley 18490
A1: CUERPO LEGAL | B1: Ley 18490 ESTABLECE SEGURO OBLIGATORIO DE ACCIDENTES PERSONALES CAUSADOS POR CIRCULACION DE VEHICULOS MOTORIZADOS | C1: EVALUACION DEL CUMPLIMIENTO
A2: CUMPLIMIENTO | B2: =AVERAGE(D5:G7) -> 1
A3: Articulos | B3: Ambito de Aplicación | C3: Frecuencia de Evaluación | D3: Cumple | E3: Parcial | F3: No Cumple | G3: N/A | H3: Registro o Forma de Evidenciar el Cumplimiento
A4: Artículo 1° | B4: Todo vehículo motorizado que para transitar por las vías públicas del territorio nacional requiera de un permiso de circulación, deberá estar asegurado contra el riesgo de accidentes personales a que se refiere esta ley. Además, si el vehículo no contare con un seguro por los daños personales y materiales causados con ocasión de un accidente de tránsito, el vehículo conducido quedará gravado con prenda sin desplazamiento y será puesto a disposición del tribunal respectivo, de forma de responder por las indemnizaciones contempladas en esta ley. | C4: anual | D4: 1 | H4: Soap , Permiso circulacion al Dia
A5: Artículo 24 | B5: TITULO I Del Seguro de Accidentes Personales. El seguro obligatorio de accidentes personales cubre los riesgos de muerte y lesiones corporales que sufran las personas como consecuencia de accidentes en que intervengan el vehículo asegurado, sus remolques o sus cargas. Este seguro cubrirá tanto al conductor del vehículo como a las personas que estén siendo transportadas en él y cualesquier tercero afectado. Para los efectos de esta ley, se considerará igualmente que son terceros afectados, las personas transportadas en un vehículo no asegurado que hubiera intervenido en un accidente con algún vehículo asegurado, con excepción del propietario del vehículo no asegurado. | C5: anual | D5: 1 | H5: Soap , Permiso circulacion al Dia
A6: Artículo 17 | B6: La contratación del seguro obligatorio deberá constar en un certificado que hará las veces de póliza y del cual se entenderá que forman parte integrante las condiciones y cláusulas que la Superintendencia. En dicho certificado, cuya forma y contenido se fijará por la Superintendencia de Valores y Seguros, deberá constar la individualización del vehículo, el nombre del tomador del seguro, el nombre de la entidad aseguradora, el número de póliza, el inicio y término de vigencia del seguro y la firma de un apoderado del asegurador que haya emitido el documento. El aludido certificado se considerará como prueba suficiente de la contratación del seguro obligatorio. | C6: anual | D6: 1 | H6: Soap , Permiso circulacion al Dia
A7: Artículo 1º, Decreto Supremo N° 313, Ministerio del Trabajo y Previsión Social, publicado el 12-05-1973, el cual incluye a escolares en Seguro de Accidentes de acuerdo con la ley N° 16.744 | B7: Los estudiantes que tengan la calidad de alumnos regulares de establecimientos fiscales o particulares, del nivel de transición de la educación parvularia, de enseñanza básica, media normal, técnica, agrícola, comercial, industrial, de institutos profesionales, de centros de formación técnica y universitaria, dependientes del Estado o reconocidos por éste, quedarán sujetos al seguro escolar contemplado en el artículo 3º de la ley Nº 16.744 por los accidentes que sufran durante sus estudios, o en la realización de su práctica educacional o profesional, en las condiciones y con las modalidades que se establecen en el presente decreto. Se exceptúan los estudiantes a que se refiere la letra c) del artículo 2º de la ley Nº 16.744, los que continuarán regidos por las disposiciones del decreto Nº 102, de 1969, dictado a través de la Subsecretaría de Previsión Social del Ministerio del Trabajo y Previsión Social, publicado en el Diario Oficial de 25 de Agosto de 1969. Los accidentes que sufran los estudiantes que tengan al mismo tiempo la calidad de trabajadores por cuenta ajena, se considerarán como accidentes del trabajo, siendo de cargo del organismo administrador al que se encuentre afiliado en esta última calidad las prestaciones que contempla la ley Nº 16.744, que serán incompatibles con las que establece el presente decreto, sin perjuicio del beneficio establecido en el artículo 9º. Lo dicho en este inciso no se aplicará en el caso que la pensión que correspondiere en calidad de trabajador fuere inferior a la que señala el presente decreto para el estudiante. | C7: En eventual contratacion de alumno en practica | D7: 1 | H7: Seguro Escolar

Sheet DS 601
A1: CUERPO LEGAL | B1: MODIFICA DECRETO Nº 609, DE 1998, QUE ESTABLECE NORMA DE EMISION PARA LA REGULACION DE CONTAMINANTES ASOCIADOS A LAS DESCARGAS DE RESIDUOS INDUSTRIALES LIQUIDOS A SISTEMAS DE ALCANTARILLADO | C1: EVALUACION DEL CUMPLIMIENTO
A2: CUMPLIMIENTO | B2: =AVERAGE(D4:G4) -> 1
A3: Articulos | B3: Ambito de Aplicación | C3: Frecuencia de Evaluación | D3: Cumple | E3: Parcial | F3: No Cumple | G3: N/A | H3: Registro o Forma de Evidenciar el Cumplimiento
A4: Articulo Tercero | B4: Modifícase el decreto supremo Nº 609, de fecha 7 de mayo de 1998, del Ministerio de Obras Públicas, que Establece Norma de Emisión para la Regulación de Contaminantes Asociados a las Descargas de Residuos Industriales Líquidos a Sistemas de Alcantarillado, en la siguiente forma: | C4: Anual | D4: 1 | H4: boleta agua

Sheet Decreto 238
A1: CUERPO LEGAL | B1: PROMULGA PROTOCOLO DE MONTREAL RELATIVO A LAS SUSTANCIAS AGOTADORAS DE LA CAPA DE OZONO DE 16 DE SEPTIEMBRE DE 1987 | C1: EVALUACION DEL CUMPLIMIENTO
A2: CUMPLIMIENTO | B2: =AVERAGE(D4:G4) -> 1
A3: Articulos | B3: Ambito de Aplicación | C3: Frecuencia de Evaluación | D3: Cumple | E3: Parcial | F3: No Cumple | G3: N/A | H3: Registro o Forma de Evidenciar el Cumplimiento
A4: todos | B4: Digital Completo | C4: Anual | D4: 1 | G4: N/A | H4: Verificación de Equipo

Sheet Decreto 55
A1: CUERPO LEGAL | B1: ESTABLECE NORMAS DE EMISION APLICABLES A VEHICULOS MOTORIZADOS PESADOS QUE INDICA | C1: EVALUACION DEL CUMPLIMIENTO
A2: CUMPLIMIENTO | B2: =AVERAGE(D4:G4) -> 1
A3: Articulos | B3: Ambito de Aplicación | C3: Frecuencia de Evaluación | D3: Cumple | E3: Parcial | F3: No Cumple | G3: N/A | H3: Registro o Forma de Evidenciar el Cumplimiento
A4: todos | B4: completo digital | C4: Anual | D4: 1 | H4: Certificado de emisión de gases

Sheet Ley 20160
A1: CUERPO LEGAL | B1: MODIFICA LA LEY Nº 19.039 SOBRE PROPIEDAD INDUSTRIAL | C1: EVALUACION DEL CUMPLIMIENTO
A2: CUMPLIMIENTO | B2: =AVERAGE(D4:G4) -> 1
A3: Articulos | B3: Ambito de Aplicación | C3: Frecuencia de Evaluación | D3: Cumple | E3: Parcial | F3: No Cumple | G3: N/A | H3: Registro o Forma de Evidenciar el Cumplimiento
A4: todos | B4: Completo digital | C4: Anual | D4: 1 | H4: Verificación INAPI

Sheet Decreto 719
A1: CUERPO LEGAL | B1: PROMULGA EL CONVENIO DE VIENA PARA LA PROTECCION DE LA CAPA DE OZONO Y SUS ANEXOS I Y II | C1: EVALUACION DEL CUMPLIMIENTO
A2: CUMPLIMIENTO | B2: =AVERAGE(D4:G4) -> 1
A3: Articulos | B3: Ambito de Aplicación | C3: Frecuencia de Evaluación | D3: Cumple | E3: Parcial | F3: No Cumple | G3: N/A | H3: Registro o Forma de Evidenciar el Cumplimiento
A4: todos | B4: completo digital | C4: Anual | D4: 1 | H4: Verificación de Equipo

Sheet Ley 20435
A1: CUERPO LEGAL | B1: MODIFICA LA LEY N° 17.336 SOBRE PROPIEDAD INTELECTUAL | C1: EVALUACION DEL CUMPLIMIENTO
A2: CUMPLIMIENTO | B2: =AVERAGE(D4:G4) -> 1
A3: Articulos | B3: Ambito de Aplicación | C3: Frecuencia de Evaluación | D3: Cumple | E3: Parcial | F3: No Cumple | G3: N/A | H3: Registro o Forma de Evidenciar el Cumplimiento
A4: Todos | B4: Completo Digital | C4: Anual | D4: 1 | H4: Compra de licencias Prohibición de instalacion de software no licenciado Definición de usuario Administrador y usuario Normal en Equipos Auditorias Software Externos

Sheet RES EX 218
A1: CUERPO LEGAL | B1: RESOLUCION EXENTA 218, MINISTERIO DE SALUD, APRUEBA INSTRUMENTO DE EVALUACION DE MEDIDAS PARA LA PREVENCION DE RIESGO PSICOSOCIALES EN EL TRABAJO | C1: EVALUACION DEL CUMPLIMIENTO
A2: CUMPLIMIENTO | B2: =AVERAGE(D4:G4) -> 1
A3: Articulos | B3: Ambito de Aplicación | C3: Frecuencia de Evaluación | D3: Cumple | E3: Parcial | F3: No Cumple | G3: N/A | H3: Registro o Forma de Evidenciar el Cumplimiento
A4: TODOS | B4: Completo digital | C4: Anual | D4: 1 | H4: Informe Riesgo Psicosocial N°139618 DSS SA (proxima evaluacion octubre de 2022)

Sheet RES EX 1448
A1: CUERPO LEGAL | B1: RESOLUCION EXENTA 1448, MINISTERIO DE SALUD, SUBSECRETARIA DE SALUD PUBLICA, ACTUALIZA PROTOCOLO DE VIGILANCIA DE RIESGOS PSICOSOCIALES EN EL TRABAJO Y DEJA SIN EFECTO LA RESOLUCIÓN Nº 1.433 EXENTA, DE 2017, DEL MINISTERIO DE SALUD | C1: EVALUACION DEL CUMPLIMIENTO
A2: CUMPLIMIENTO | B2: =AVERAGE(D4:G4) -> 1
A3: Articulos | B3: Ambito de Aplicación | C3: Frecuencia de Evaluación | D3: Cumple | E3: Parcial | F3: No Cumple | G3: N/A | H3: Registro o Forma de Evidenciar el Cumplimiento
A4: TODOS | B4: Completo digital | C4: Anual | D4: 1 | H4: Informe Riesgo Psicosocial N°139618 DSS SA (proxima evaluacion 2024)

Sheet TMERT
A1: CUERPO LEGAL | B1: NORMA TÉCNICA DE IDENTIFICACIÓN Y EVALUACIÓN DE FACTORES DE RIESGO DE TRASTORNOS MUSCULOESQUELÉTICOS RELACIONADOS AL TRABAJO (TMERT) | C1: EVALUACION DEL CUMPLIMIENTO
A2: CUMPLIMIENTO | B2: =AVERAGE(D4:G4) -> 1
A3: Articulos | B3: Ambito de Aplicación | C3: Frecuencia de Evaluación | D3: Cumple | E3: Parcial | F3: No Cumple | G3: N/A | H3: Registro o Forma de Evidenciar el Cumplimiento
A4: TODOS | B4: Completo digital | C4: Anual | D4: 1 | H4: MUTUAL - APR

Sheet DS 1 RECT
A1: CUERPO LEGAL | B1: DS 1 APRUEBA REGLAMENTO DEL REGISTRO DE EMISIONES Y TRANSFERENCIAS DE CONTAMINANTES, RETC | C1: EVALUACION DEL CUMPLIMIENTO
A2: CUMPLIMIENTO | B2: =AVERAGE(D4:G7) -> 1
A3: Articulos | B3: Ambito de Aplicación | C3: Frecuencia de Evaluación | D3: Cumple | E3: Parcial | F3: No Cumple | G3: N/A | H3: Registro o Forma de Evidenciar el Cumplimiento
A4: Artículo 17.- | B4: Ventanilla Única. Los sujetos obligados a registrarse y los que reporten o informen sus emisiones, residuos, transferencias de contaminantes o productos prioritarios, deberán realizarlo sólo a través de la ventanilla única que se encuentra en el portal electrónico del RETC. La información que las fuentes emisoras deban proporcionar a la Superintendencia del Medio Ambiente de conformidad a las letras e), f) y h), del artículo 32 de su Ley Orgánica se realizará a través de la ventanilla única, accediéndose por dicha vía al Sistema Nacional de Información de Fiscalización Ambiental de la Superintendencia del Medio Ambiente. No obstante, la forma y modo de remisión, así como los plazos para la entrega de la información mencionada en el inciso anterior, se regirá por lo dispuesto en las instrucciones generales que dicte la Superintendencia del Medio Ambiente y en el Reglamento del Sistema Nacional de Información de Fiscalización Ambiental y de los Registros Públicos de Resoluciones de Calificación Ambiental y de Sanciones. El ingreso a la ventanilla única del RETC se realizará mediante un identificador del establecimiento o RUT, según corresponda, y su respectiva contraseña. Tanto el identificador como la contraseña serán entregados por medio de un correo electrónico. Para ello, previamente se debe haber completado un formulario en donde se ingresan los datos del establecimiento y cualquier otro que se estime necesario. La información incluida en este formulario se mantendrá en la base de datos del RETC. | C4: cada 5 meses / pedir autorizacion adicional / retiro anual ( dependiendo el caso ) | D4: 1 | H4: permiso bodega Respel SeremI / Declaracion RETC
A5: Artículo 18.- | B5: Sujetos obligados a reportar e informar. Se encuentran obligados a reportar o informar a través del Sistema de Ventanilla Única: a) Los establecimientos que deban reportar a otros órganos de la Administración del Estado, la información sobre sus emisiones, residuos y/o transferencias de contaminantes, ya sea por una norma de emisión, una resolución de calificación ambiental, un plan de prevención, un plan de descontaminación, o por exigencia de la normativa sectorial o general correspondiente. b) Los establecimientos sujetos a calificarse como fuente emisora o generadora o destinatario de residuo, según alguna norma de emisión u otra regulación. c) Los establecimientos sujetos a reportar la información de sus emisiones, residuos y/o transferencias de contaminantes conforme a lo establecido en tratados internacionales ratificados por Chile. d) Los establecimientos que emitan contaminantes, sustancias, generen o reciben residuos y/o transfieran contaminantes, respecto de los cuales una regulación determinada obligue su reporte. e) Importadores, productores, distribuidores y comercializadores de productos que contengan contaminantes y sustancias, respecto de los cuales una regulación y/o tratados internacionales ratificados por Chile obligue su reporte. f) Centros de almacenamiento de insumos para la producción industrial potencialmente dañinos para la salud y el medio ambiente, respecto de los cuales una regulación y/o tratados internacionales ratificados por Chile obligue su reporte. g) Los establecimientos que generen más de 12 toneladas de residuos al año, las municipalidades, y los destinatarios de residuos, de acuerdo a los artículos 26, 27 y 28 del presente reglamento. h) Los productores de productos prioritarios; sistemas de gestión; los gestores de residuos; y los comercializadores y distribuidores y los consumidores industriales, cuando corresponda, de acuerdo a lo indicado en la Ley Nº 20.920. i) Los establecimientos afectos a pagar impuesto a las emisiones, de acuerdo a lo indicado en el artículo 8º de la ley 20.780. | C5: cada 5 meses / pedir autorizacion adicional / retiro anual ( dependiendo el caso ) | D5: 1 | H5: permiso bodega Respel SeremI / Declaracion RETC
A6: Artículo 19.- | B6: Reportes Voluntarios. Los establecimientos podrán acordar con el Ministerio reportar voluntariamente emisiones, residuos y/o transferencias de contaminantes, respecto de los cuales no tengan la obligación de reportar, pero que se encuentren regulados en nuestro país por normativa de carácter nacional o internacional. El reporte voluntario deberá al menos contemplar los siguientes aspectos: a) La metodología utilizada para medir o estimar la emisión o cuantificar los residuos. b) La periodicidad de reporte, que no podrá ser inferior a una vez al año. c) El plazo de duración de reporte voluntario, que no podrá ser inferior a 2 años. d) El método de validación del dato. La información obtenida de los reportes voluntarios se validará por el Ministerio y se publicará en forma nominada. El Ministerio podrá retirar del registro los reportes voluntarios que no cumplan con las exigencias señaladas en este artículo. | C6: cada 5 meses / pedir autorizacion adicional / retiro anual ( dependiendo el caso ) | D6: 1 | H6: permiso bodega Respel SeremI / Declaracion RETC
A7: Artículo 25.- | B7: Generador de Residuos. Los establecimientos que generen anualmente más de 12 toneladas de residuos no sometidos a reglamentos específicos, estarán obligados a declarar al 30 de marzo de cada año sus residuos generados el año anterior, a través del Sistema de Ventanilla Única del Registro de Emisiones y Transferencias de Contaminantes (RETC). Lo anterior, sin perjuicio de las obligaciones emanadas de los DS Nº 148 de 2003, y DS Nº 6 de 2009, ambos del Ministerio de Salud, así como del DS Nº 4 de 2009, del Ministerio Secretaría General de la Presidencia, en relación a lo dispuesto al artículo 18 letra d) del presente reglamento. | C7: semestral | G7: 1 | H7: revision de los indicadores

Sheet ORD MUN 46
A1: CUERPO LEGAL | B1: Ordenanza Municipal N° 46 Gestión Ambiental Comunal | C1: EVALUACION DEL CUMPLIMIENTO
A2: CUMPLIMIENTO | B2: =AVERAGE(D4:G4) -> 1
A3: Articulos | B3: Ambito de Aplicación | C3: Frecuencia de Evaluación | D3: Cumple | E3: Parcial | F3: No Cumple | G3: N/A | H3: Registro o Forma de Evidenciar el Cumplimiento
A4: Todos | B4: Completo Digital | C4: Anual | D4: 1 | H4: Programa Ambiental

Sheet ORD MUN 56
A1: CUERPO LEGAL | B1: ORDENANZA 56, FIJASE EL SIGUIENTE TEXTO REFUNDIDO DE LA ORDENANZA LOCAL N°01, DE 24 DE DICIEMBRE 1996, QUE DETERMINA LA TARIFA DE ASEO DOMICILIARIO, SUS EXENCIONES Y EL COBRO ADICIONAL POR SOBREPRODUCCIÓN | C1: EVALUACION DEL CUMPLIMIENTO
A2: CUMPLIMIENTO | B2: =AVERAGE(D4:G4) -> 1
A3: Articulos | B3: Ambito de Aplicación | C3: Frecuencia de Evaluación | D3: Cumple | E3: Parcial | F3: No Cumple | G3: N/A | H3: Registro o Forma de Evidenciar el Cumplimiento
A4: Todos | B4: Completo Digital | C4: Anual | D4: 1 | H4: patente comercial

Sheet Plan Regulador
A1: CUERPO LEGAL | B1: PLAN REGULADOR COMUNAL SAN PEDRO DE LA PAZ DE 24 DE FEBRERO 2011 | C1: EVALUACION DEL CUMPLIMIENTO
A2: CUMPLIMIENTO | B2: =AVERAGE(D4:G4) -> 1
A3: Articulos | B3: Ambito de Aplicación | C3: Frecuencia de Evaluación | D3: Cumple | E3: Parcial | F3: No Cumple | G3: N/A | H3: Registro o Forma de Evidenciar el Cumplimiento
A4: Todos | B4: Completo Digital | C4: Anual | D4: 1 | H4: Patente Comercial

Sheet DS 206
A1: CUERPO LEGAL | B1: DS 206 de 1970 MODIFICA EL REGLAMENTO DE COMITES PARITARIOS DE HIGIENE Y SEGURIDAD | C1: EVALUACION DEL CUMPLIMIENTO
A2: CUMPLIMIENTO | B2: =AVERAGE(D4:G4) -> 1
A3: Articulos | B3: Ambito de Aplicación | C3: Frecuencia de Evaluación | D3: Cumple | E3: Parcial | F3: No Cumple | G3: N/A | H3: Registro o Forma de Evidenciar el Cumplimiento
A4: Todos | B4: Completo Digital | C4: Anual | D4: 1 | H4: Acta Constitución CPHS / Curso de capacitación CPHS

Sheet Ley 20123
A1: CUERPO LEGAL | B1: LEY 20123, MINISTERIO DEL TRABAJO Y PREVISIÓN SOCIAL, REGULA EL TRABAJO EN REGIMEN DE SUBCONTRATACIÓN, EL FUNCIONAMIENTO DE LAS EMPRESAS DE SERVICIOS TRANSITORIOS Y EL CONTRATO DE SERVICIOS TRANSITORIOS | C1: EVALUACION DEL CUMPLIMIENTO
A2: CUMPLIMIENTO | B2: =AVERAGE(D4:G4) -> 1
A3: Articulos | B3: Ambito de Aplicación | C3: Frecuencia de Evaluación | D3: Cumple | E3: Parcial | F3: No Cumple | G3: N/A | H3: Registro o Forma de Evidenciar el Cumplimiento
A4: Todos | B4: Completo Digital | C4: Anual | G4: 1 | H4: Contrato o Subcontratación

Sheet DS 76
A1: CUERPO LEGAL | B1: DS 76 APRUEBA REGLAMENTO PARA LA APLICACIÓN DEL ARTICULO 66 BIS DE LA LEY N°16.744 SOBRE LA GESTIÓN DE LA SEGURIDAD Y SALUD EN EL TRABAJO EN OBRAS, FAENAS O SERVICIOS QUE INDICA. | C1: EVALUACION DEL CUMPLIMIENTO
A2: CUMPLIMIENTO | B2: =AVERAGE(D4:G4) -> 1
A3: Articulos | B3: Ambito de Aplicación | C3: Frecuencia de Evaluación | D3: Cumple | E3: Parcial | F3: No Cumple | G3: N/A | H3: Registro o Forma de Evidenciar el Cumplimiento
A4: Todos | B4: Completo Digital | C4: Anual | G4: 1 | H4: Contrato o Subcontratación

Sheet RES EX 3457
A1: CUERPO LEGAL | B1: APRUEBA GUÍA PARA LA SELECCIÓN Y CONTROL DE PROTECCIÓN OCULAR Y FACIAL, ELABORADA POR EL DEPARTAMENTO DE SALUD OCUPACIONAL | C1: EVALUACION DEL CUMPLIMIENTO
A2: CUMPLIMIENTO | B2: =AVERAGE(D4:G4) -> 1
A3: Articulos | B3: Ambito de Aplicación | C3: Frecuencia de Evaluación | D3: Cumple | E3: Parcial | F3: No Cumple | G3: N/A | H3: Registro o Forma de Evidenciar el Cumplimiento
A4: Todos | B4: Completo digital | C4: Semestral | D4: 1 | H4: Lista de chequeo, Lista de Compra

Sheet DS 144
A1: CUERPO LEGAL | B1: DECRETO SUPREMO 144 / 1961, MINISTERIO DE SALUD, ESTABLECE NORMAS PARA EVITAR EMANACIONES O CONTAMINANTES ATMOSFERICOS DE CUALQUIERA NATURALEZA | C1: EVALUACION DEL CUMPLIMIENTO
A2: CUMPLIMIENTO | B2: =AVERAGE(D4:G4) -> 1
A3: Articulos | B3: Ambito de Aplicación | C3: Frecuencia de Evaluación | D3: Cumple | E3: Parcial | F3: No Cumple | G3: N/A | H3: Registro o Forma de Evidenciar el Cumplimiento
A4: Artículo 1° | B4: Los gases, vapores, humos, polvo, emanaciones o contaminantes de cualquiera naturaleza, producidos en cualquier establecimiento fabril o lugar de trabajo, deberán captarse o eliminarse en forma tal que no causen peligros, daños o molestias al vencindario | C4: Anual | G4: 1 | H4: Patente Comercial
A5: Artículo 2° | B5: Los equipos de combustión de los servicios de calefacción o agua caliente de cualquier tipo de edificio, que utilicen combustibles sólidos o líquidos, deberán contar con la aprobación del Servicio Nacional de Salud, organismo que la otorgará cuando estime que la combustión puede efectuarse sin producción de humos, gases o quemados, gases tóxicos o malos olores y sin que escapen al aire cenizas o residuos sólidos. | C5: Anual | G5: 1 | H5: Calefacción electrica
A6: Artículo 6° | B6: Prohíbese dentro del radio urbano de las ciudades la incineración libre, sea en la vía pública o en los recintos privados, de hojas secas, basuras u otros desperdicios. | C6: Anual | D6: 1 | H6: Patente Comercial
A7: Artículo 7° | B7: Prohíbese la circulación de todo vehículo motorizado que despida humo visible por su tubo de escape | C7: Anual | D7: 1 | H7: Revisión técnica

Sheet DS 103
A1: CUERPO LEGAL | B1: DECRETO SUPREMO 103, MINISTERIO DE TRANSPORTE Y TELECOMUNICACIONES, ESTABLECE NORMA DE EMISION DE HIDROCARBUROS NO METANICOS PARA VEHICULOS LIVIANOS Y MEDIANOS | C1: EVALUACION DEL CUMPLIMIENTO
A2: CUMPLIMIENTO | B2: =AVERAGE(D4:G4) -> 1
A3: Articulos | B3: Ambito de Aplicación | C3: Frecuencia de Evaluación | D3: Cumple | E3: Parcial | F3: No Cumple | G3: N/A | H3: Registro o Forma de Evidenciar el Cumplimiento
A4: Todos | B4: Completo digital | C4: Anual | G4: 1 | H4: Revisión Técnica

Sheet DS 149
A1: CUERPO LEGAL | B1: DECRETO SUPREMO 149 / 2007, MINISTERIO DE TRANSPORTE Y TELECUMUNICACIONES, ESTABLECE NORMA DE EMISION DE NO, HC Y CO PARA EL CONTROL DEL NOX EN VEHICULOS EN USO, DE ENCENDIDO POR CHISPA (CICLO OTTO), QUE CUMPLEN CON LAS NORMAS DE EMISION ESTABLECIDAS EN EL DS. Nº 211 DE 1991 Y DS. Nº 54, DE 1994 | C1: EVALUACION DEL CUMPLIMIENTO
A2: CUMPLIMIENTO | B2: =AVERAGE(D4:G4) -> 1
A3: Articulos | B3: Ambito de Aplicación | C3: Frecuencia de Evaluación | D3: Cumple | E3: Parcial | F3: No Cumple | G3: N/A | H3: Registro o Forma de Evidenciar el Cumplimiento
A4: Todos | B4: Completo digital | C4: Anual | D4: 1 | H4: Revisión Técnica

Sheet DS 54 MTT
A1: CUERPO LEGAL | B1: DECRETO SUPREMO 54 / 1994, MINISTERIO DE TRANSPORTE Y TELECUMUNICACIONES, ESTABLECE NORMAS DE EMISIÓN APLICABLES A VEHICULOS MOTORIZADOS MEDIANOS | C1: EVALUACION DEL CUMPLIMIENTO
A2: CUMPLIMIENTO | B2: =AVERAGE(D4:G4) -> 1
A3: Articulos | B3: Ambito de Aplicación | C3: Frecuencia de Evaluación | D3: Cumple | E3: Parcial | F3: No Cumple | G3: N/A | H3: Registro o Forma de Evidenciar el Cumplimiento
A4: Todos | B4: Completo digital | C4: Anual | D4: 1 | H4: Revisión Técnica

Sheet NCh 2056
A1: CUERPO LEGAL | B1: NCh 2056, Extintores portátiles - Inspección, mantención y recarga - Requisitos generales Instalaciones fijas de extinción | C1: EVALUACION DEL CUMPLIMIENTO
A2: CUMPLIMIENTO | B2: =AVERAGE(D4:G4) -> 1
A3: Articulos | B3: Ambito de Aplicación | C3: Frecuencia de Evaluación | D3: Cumple | E3: Parcial | F3: No Cumple | G3: N/A | H3: Registro o Forma de Evidenciar el Cumplimiento
A4: Todos | B4: Completo digital | C4: Mensual | D4: 1 | H4: Registro de inspección mensual de extintores, tarjeta de inspeccion mensual del extintor

Sheet RES 499
A1: CUERPO LEGAL | B1: RESOLUCIÓN N°499/2006, MINISTERIO DE SALUD. APRUEBA DOCUMENTO ELECTRONICO DE DECLARACIÓN DE RESIDUOS PELIGROSOS | C1: EVALUACION DEL CUMPLIMIENTO
A2: CUMPLIMIENTO | B2: =AVERAGE(D4:G4) -> 1
A3: Articulos | B3: Ambito de Aplicación | C3: Frecuencia de Evaluación | D3: Cumple | E3: Parcial | F3: No Cumple | G3: N/A | H3: Registro o Forma de Evidenciar el Cumplimiento
A4: Todos | B4: Completo digital | C4: Anual | D4: 1 | H4: Inscrito en ventanilla unica, con clave de usuario para inscripción en registro digital y declarado en Ventanilla Unica.

Sheet Ley 20584
A1: CUERPO LEGAL | B1: LEY 20584 / 2012, MINISTERIO DE SALUD, REGULA LOS DERECHOS Y DEBERES QUE TIENEN LAS PERSONAS EN RELACION CON ACCIONES VINCULADAS A SU ATENCIÓN EN SALUD | C1: EVALUACION DE CUMPLIMIENTO
A2: CUMPLIMIENTO | B2: =AVERAGE(D4:G4) -> 1
A3: Articulos | B3: Ambito de Aplicación | C3: Frecuencia de Evaluación | D3: Cumple | E3: Parcial | F3: No Cumple | G3: N/A | H3: Registro o Forma de Evidenciar el Cumplimiento
A4: TODOS | B4: Define los derechos y deberes vinculadas a su atención de salud | C4: Anual | D4: 1 | H4: RIOHS

Sheet Ley 20393
A1: CUERPO LEGAL | B1: LEY 20393 / 2016, MINISTERIO DE HACIENDA, ESTABLECE LA RESPONSABILIDAD PENAL DE LAS PERSONAS JURIDICAS EN LOS DELITOS DE LAVADOS DE ACTIVOS, FINANCIAMIENTO DEL TERRORISMO Y DELITOS DE COHECHO QUE INDICA | C1: EVALUACION DE CUMPLIMIENTO
A2: CUMPLIMIENTO | B2: =AVERAGE(D4:G4)/100 -> 0.5
A3: Articulos | B3: Ambito de Aplicación | C3: Frecuencia de Evaluación | D3: Cumple | E3: Parcial | F3: No Cumple | G3: N/A | H3: Registro o Forma de Evidenciar el Cumplimiento
A4: TODOS | B4: Establece responsabilidades de delitos economicos individuales dentro de la empresa | C4: Semestral | E4: 50 | H4: Auditoria Financiera / RIOHS / Modelo Prevención del Delito (Implementación)

Sheet Ley 21012
A1: CUERPO LEGAL | B1: LEY 21012 / 2017, MINISTERIO DE TRABAJO Y PREVISIÓN SOCIAL, GARANTIZA SEGURIDAD DE LOS TRABAJADORES EN SITUACIONES DE RIESGO Y EMERGENCIA | C1: EVALUACION DE CUMPLIMIENTO
A2: CUMPLIMIENTO | B2: =AVERAGE(D4:G4) -> 1
A3: Articulos | B3: Ambito de Aplicación | C3: Frecuencia de Evaluación | D3: Cumple | E3: Parcial | F3: No Cumple | G3: N/A | H3: Registro o Forma de Evidenciar el Cumplimiento
A4: TODOS | B4: Establece responsabilidades de empleador sobre comunicación de situaciones de riesgo y emergencia | C4: Semestral | D4: 1 | H4: RIOHS / Plan de Emergencia / ODI / Simulacros de Emergencia

Sheet Ley 20830
A1: CUERPO LEGAL | B1: LEY 20830 / 2015, MINISTERIO SECRETARIA GENERAL DE GOBIERNO, CREA EL ACUERDO DE UNIÓN CIVIL | C1: EVALUACION DE CUMPLIMIENTO
A2: CUMPLIMIENTO | B2: =AVERAGE(D4:G4) -> 1
A3: Articulos | B3: Ambito de Aplicación | C3: Frecuencia de Evaluación | D3: Cumple | E3: Parcial | F3: No Cumple | G3: N/A | H3: Registro o Forma de Evidenciar el Cumplimiento
A4: TODOS | B4: Establece creación del acuerdo de unión civil | C4: Anual | D4: 1 | H4: RIOHS

Sheet Ley 20348
A1: CUERPO LEGAL | B1: LEY 20348 / 2009, MINISTERIO DEL TRABAJO Y PREVISIÓN SOCIAL; SUBSECRETARÍA DEL TRABAJO, RESGUARDA EL DERECHO A LA IGUALDAD EN LAS REMUNERACIONES | C1: EVALUACION DE CUMPLIMIENTO
A2: CUMPLIMIENTO | B2: =AVERAGE(D4:G4) -> 1
A3: Articulos | B3: Ambito de Aplicación | C3: Frecuencia de Evaluación | D3: Cumple | E3: Parcial | F3: No Cumple | G3: N/A | H3: Registro o Forma de Evidenciar el Cumplimiento
A4: TODOS | B4: Establece el derecho a la igualdad en las remuneraciones | C4: Anual | D4: 1 | H4: RIOHS

Sheet Ley 21015
A1: CUERPO LEGAL | B1: LEY 21015 / 2017, MINISTERIO DE DESARROLLO SOCIAL, INCENTIVA LA INCLUSIÓN DE PERSONAS CON DISCAPACIDAD AL MUNDO LABORAL | C1: EVALUACION DE CUMPLIMIENTO
A2: CUMPLIMIENTO | B2: =AVERAGE(D4:G9) -> 1
A3: Articulos | B3: Ambito de Aplicación | C3: Frecuencia de Evaluación | D3: Cumple | E3: Parcial | F3: No Cumple | G3: N/A | H3: Registro o Forma de Evidenciar el Cumplimiento
A4: Artículo 2 | B4: Sustitúyese el inciso tercero del artículo 17 de la ley N° 18.834, sobre Estatuto Administrativo, cuyo texto refundido, coordinado y sistematizado fue fijado por el decreto con fuerza de ley N° 29, de 2004, del Ministerio de Hacienda, por el siguiente: Prohíbese todo acto de discriminación arbitraria que se traduzca en exclusiones o restricciones, tales como aquellas basadas en motivos de raza o etnia, situación socioeconómica, idioma, ideología u opinión política, discapacidad, religión o creencia, sindicación o participación en organizaciones gremiales o la falta de ellas, sexo, orientación sexual, identidad de género, estado civil, edad, filiación, apariencia personal o enfermedad, que tengan por objeto anular o alterar la igualdad de oportunidades o trato en el empleo | C4: Anual | D4: 1 | H4: RIOHS
A5: Artículo 3 | B5: Modifícase el título III del libro I del Código del Trabajo, de la siguiente manera: 1. Reemplázase su denominación por la siguiente: "Del Reglamento Interno y la Inclusión Laboral de Personas con Discapacidad". 2. Intercálase, a continuación del epígrafe antes señalado, lo siguiente: "Capítulo I Del Reglamento Interno" 3. Incorpóranse, a continuación del artículo 157, el siguiente capítulo II y los artículos 157 bis y 157 ter que lo componen: "Capítulo II De la Inclusión Laboral de Personas con Discapacidad Artículo 157 bis.- Las empresas de 100 o más trabajadores deberán contratar o mantener contratados, según corresponda, al menos el 1% de personas con discapacidad o que sean asignatarias de una pensión de invalidez de cualquier régimen previsional, en relación al total de sus trabajadores. Las personas con discapacidad deberán contar con la calificación y certificación señaladas en el artículo 13 de la ley N° 20.422. El empleador deberá registrar los contratos de trabajo celebrados con personas con discapacidad o asignatarios de una pensión de invalidez de cualquier régimen previsional, así como sus modificaciones o términos, dentro de los quince días siguientes a su celebración a través del sitio electrónico de la Dirección del Trabajo, la que llevará un registro actualizado de lo anterior, debiendo mantener reserva de dicha información. La fiscalización de lo dispuesto en este capítulo corresponderá a la Dirección del Trabajo, salvo lo dispuesto en el inciso cuarto del artículo siguiente, en lo relativo a la reglamentación de la letra b) de ese mismo artículo. Un reglamento dictado por el Ministerio del Trabajo y Previsión Social y suscrito por los ministros de Hacienda y de Desarrollo Social, establecerá los parámetros, procedimientos y demás elementos necesarios para dar cumplimiento a lo establecido en este capítulo. Artículo 157 ter.- Las empresas que, por razones fundadas, no puedan cumplir total o parcialmente la obligación establecida en el inciso primero del artículo anterior, deberán darle cumplimiento en forma alternativa, ejecutando alguna de las siguientes medidas: a) Celebrar contratos de prestación de servicios con empresas que tengan contratadas personas con discapacidad. b) Efectuar donaciones en dinero a proyectos o programas de asociaciones, corporaciones o fundaciones a las que se refiere el artículo 2 de la ley N° 19.885. Sólo se considerarán razones fundadas aquellas derivadas de la naturaleza de las funciones que desarrolla la empresa o la falta de personas interesadas en las ofertas de trabajo que se hayan formulado. El monto anual de los contratos celebrados de conformidad a la letra a) de este artículo no podrá ser inferior al equivalente a veinticuatro ingresos mínimos mensuales respecto de cada trabajador que debía ser contratado por la empresa. Las donaciones establecidas en la letra b) de este artículo deberán sujetarse a lo dispuesto en la ley N° 19.885, en lo que resulte aplicable, y con las excepciones que se señalan a continuación: 1.- Estas donaciones no darán derecho a los créditos y beneficios tributarios establecidos en los artículos 1 y 1 bis. Sin embargo, para efectos de lo establecido en la Ley sobre Impuesto a la Renta, contenida en el artículo 1 del decreto ley N° 824, de 1974, tendrán la calidad de gasto necesario para producir la renta de acuerdo a lo establecido en el artículo 31 del referido cuerpo legal. 2.- Las donaciones deberán dirigirse a proyectos o programas de asociaciones, corporaciones o fundaciones cuyo objeto social incluya la capacitación, rehabilitación, promoción y fomento para la creación de empleos, contratación o inserción laboral de las personas con discapacidad. 3.- Las donaciones no podrán efectuarse a instituciones en cuyo directorio participe el donante, su cónyuge, su conviviente civil o sus parientes ascendientes o descendientes hasta el tercer grado de consanguinidad. En caso que el donante sea una persona jurídica, no podrá efectuar donaciones a instituciones en cuyo directorio participen sus socios o directores o los accionistas que posean el 10% o más del capital social, o los cónyuges, convivientes civiles o parientes ascendientes o descendientes hasta el tercer grado de consanguinidad de dichos socios, directores o accionistas. 4.- El monto anual de las donaciones efectuadas no podrá ser inferior al equivalente a veinticuatro ingresos mínimos mensuales ni superior a doce veces el límite máximo imponible establecido en el artículo 16 del decreto ley Nº 3.500, de 1980, respecto de cada trabajador que debía ser contratado por la empresa. 5.- No se aplicará a las donaciones a que se refiere esta ley el límite global absoluto establecido en el artículo 10. Las empresas que ejecuten alguna de las medidas señaladas en las letras a) y b) de este artículo deberán remitir una comunicación electrónica a la Dirección del Trabajo, con copia a la Subsecretaría de Evaluación Social del Ministerio de Desarrollo Social, al Servicio Nacional de la Discapacidad y al Servicio de Impuestos Internos. La empresa deberá indicar en esta comunicación la razón invocada y la medida adoptada. Esta comunicación deberá ser efectuada durante el mes de enero de cada año y tendrá una vigencia de doce meses.". | C5: Anual | G5: 1 | H5: RIOHS
A6: Artículo 6 | B6: Modifícase la letra g) del artículo 2 de la ley N° 16.395, que fija el texto refundido de la ley de organización y atribuciones de la Superintendencia de Seguridad Social, del modo que sigue: 1. Intercálase el siguiente párrafo tercero: "Asimismo, el Sistema incorporará la información respecto de las personas que sean asignatarias de una pensión de invalidez de cualquier régimen previsional, que los organismos previsionales y de seguridad social deberán remitir mensualmente, en la forma que la Superintendencia determine.". 2. Agréganse a continuación del actual párrafo tercero, que ha pasado a ser cuarto, los siguientes párrafos quinto y sexto: "Las subsecretarías del Trabajo y de Previsión Social tendrán acceso a dicho Sistema y a la información que fuere necesaria sólo para el ejercicio de sus funciones. En tal caso, el tratamiento y uso de los datos personales que efectúen las subsecretarías quedará dentro del ámbito de su competencia. Dichas subsecretarías y su personal deberán guardar absoluta reserva y secreto de la información de que tomen conocimiento y abstenerse de usar dicha información en beneficio propio o de terceros. Para efectos de lo dispuesto en el inciso segundo del artículo 125 de la ley N° 18.834, sobre Estatuto Administrativo, cuyo texto refundido, coordinado y sistematizado fue fijado por el decreto con fuerza de ley N° 29, de 2004, del Ministerio de Hacienda, se estimará que los hechos que configuren infracciones a esta disposición vulneran gravemente el principio de probidad administrativa, sin perjuicio de las demás sanciones y responsabilidades que procedan.". | C6: Anual | G6: 1 | H6: RIOHS / Pago Previsional
